Workbook
Name lst_Units: 'Lists'!$B$6:$B$30
Name lst_ExpCat: 'Lists'!$F$6:$F$35
Name lst_Pay: 'Lists'!$J$6:$J$20
Name lst_MenuCat: 'Lists'!$L$6:$L$20
Name lst_Waste: 'Lists'!$N$6:$N$20
Name lst_Period: 'Lists'!$P$6:$P$18
Name cfg_Business: 'Settings'!$C$6
Name cfg_Symbol: 'Settings'!$C$18
Name cfg_Currency: 'Settings'!$C$19
Name cfg_Year: 'Settings'!$C$21
Name cfg_Start: 'Settings'!$C$22
Name cfg_End: 'Settings'!$C$23
Name cfg_Months: 'Settings'!$C$24
Name cfg_PeriodLabel: 'Settings'!$C$25
Name cfg_CountDate: 'Settings'!$C$26
Name cfg_LaborRate: 'Settings'!$C$27
Name cfg_TargetMargin: 'Settings'!$C$28
Name cfg_FoodCostTarget: 'Settings'!$C$29
Name cfg_Round: 'Settings'!$C$30
Name ps_rev: 'Monthly Report'!$G$25
Name ps_items: 'Monthly Report'!$G$26
Name ps_cogs: 'Monthly Report'!$G$27
Name ps_gp: 'Monthly Report'!$G$28
Name ps_gm: 'Monthly Report'!$G$29
Name ps_waste: 'Monthly Report'!$G$30
Name ps_fixed: 'Monthly Report'!$G$31
Name ps_labor: 'Monthly Report'!$G$32
Name ps_event: 'Monthly Report'!$G$33
Name ps_var: 'Monthly Report'!$G$34
Name ps_opex: 'Monthly Report'!$G$35
Name ps_net: 'Monthly Report'!$G$36
Name ps_nm: 'Monthly Report'!$G$37
Name ps_lines: 'Monthly Report'!$G$38
Name ps_avgp: 'Monthly Report'!$G$39
Name ps_active: 'Monthly Report'!$G$40
Name ps_avgopex: 'Monthly Report'!$G$41
Name ps_berev: 'Monthly Report'!$G$42
Name ps_beprog: 'Monthly Report'!$G$43
Name ps_stock: 'Monthly Report'!$G$44
Name ps_unclassified: 'Monthly Report'!$G$45
Name be_Revenue: 'Break-Even'!$H$27
Name be_Items: 'Break-Even'!$H$20

Sheet Start Here
B2: Food Truck Profit & Pricing System PRO
B3: by NoviraNest · Version 1.0.0 · Works in Microsoft Excel and Google Sheets · No macros
B6: THIS IS YOUR CLEAN TEMPLATE. Every log is empty and ready for your data. Want to see it filled in first? Open the SAMPLE file.
B8: Quick setup (about 30 minutes, once)
B9: 1 | C9: Settings | D9: Business name, currency (USD or GBP), reporting year, labour rate, target margin and food cost %.
B10: 2 | C10: Inventory | D10: List your ingredients: the unit you count them in, pack size and pack price. Cost per unit is automatic.
B11: 3 | C11: Recipe Builder | D11: First add menu item names on Menu Pricing, then here list what goes into ONE serving. Units convert automatically.
B12: 4 | C12: Menu Pricing | D12: Add packaging, prep minutes and your menu price. See the suggested price, margin, markup and status.
B13: 5 | C13: Break-Even | D13: Type your monthly fixed costs once. The Dashboard then shows your break-even progress.
B14: 6 | C14: Daily / weekly | D14: Log sales on the Sales Log, costs on Expenses and thrown-away food on the Waste Log. Then open the Dashboard.
B16: What the colours mean
C17: Cream cell, blue text | D17: Type here. These are the only cells you need to fill in.
C18: Grey cell | D18: Automatic formula. Please don't type over it.
C19: Red / pink | D19: Something needs your attention (loss-making item, unit mismatch, bad row).
C20: Blue box | D20: Instructions and explanations.
B22: Sheet directory
C23: › Dashboard | D23: KPI cards, monthly chart, expense breakdown, best sellers, most profitable items, alerts.
C24: › Settings | D24: Your business settings. Everything reads from here.
C25: › Menu Pricing | D25: Smart pricing: cost per serving, suggested price, margin vs markup, food cost %, status, sales by item.
C26: › Recipe Builder | D26: Ingredients per serving with automatic unit conversion and mismatch protection.
C27: › Inventory | D27: Ingredient prices, estimated stock on hand, stock value and reorder alerts.
C28: › Waste Log | D28: Food thrown away, valued automatically.
C29: › Sales Log | D29: Every sale: revenue, cost and gross profit calculated for you (3,000 rows).
C30: › Expenses | D30: Every business cost with a category (1,500 rows).
C31: › Monthly Report | D31: Profit & loss by month and the selected-period summary.
C32: › Break-Even | D32: Break-even items and revenue, target profit, chart.
C33: › Event Predictor | D33: Forecast an event (worst / base / best), then compare with actual results.
C34: › Scenario Simulator | D34: What-if: ingredient inflation, price changes, busy/slow season, wage rises.
C35: › Lists | D35: Units, expense categories and dropdown lists you can extend.
B37: How the numbers work
C38: Revenue | D38: Items sold x price charged (menu price unless you typed a different price on the Sales Log).
C39: COGS | D39: Cost of goods sold = items sold x (ingredients + packaging + other variable cost per serving). Labour is NOT in COGS.
C40: Gross profit | D40: Revenue - COGS. Gross margin = gross profit / revenue.
C41: Net profit | D41: Gross profit - waste - operating expenses (fixed, labour, event fees, other variable). Before income tax.
C42: Not double counted | D42: Ingredient purchases and owner's draw can be logged on Expenses but are excluded from profit: the food you used is already in COGS. Prep labour on Menu Pricing is a pricing allowance only; real wages go in Expenses.
C43: Margin vs markup | D43: Margin = profit / PRICE. Markup = profit / COST. Cost 4.00, price 10.00 -> margin 60%, markup 150%.
C44: Food cost % | D44: Ingredient cost / menu price.
C45: Break-even | D45: Monthly fixed costs / contribution per item (price - item cost - % fees).
C46: Currency | D46: USD or GBP changes symbols only. Amounts are never converted with an exchange rate.
C47: Forecasts | D47: Event Predictor and Scenario Simulator are estimates. They never change your actual figures.
B49: Good to know
B50: • | C50: Need more rows? Select the last row of a log, copy it, and paste it below - the formulas come with it. Then extend the ranges named in the Sales/Expense formulas, or simply use the 3,000 / 1,500 rows provided.
B51: • | C51: Google Sheets: File > Import > Upload, or open the .xlsx from Google Drive and choose File > Save as Google Sheets. See the Quick-Start Guide PDF for what looks different in Google Sheets.
B52: • | C52: Rows with a red 'Check' are NOT counted until fixed - the Dashboard 'Alerts' panel tells you how many.
B53: • | C53: Back up your file regularly (Excel: Save a copy; Google Sheets: File > Version history).
B54: • | C54: This tool provides management estimates, not tax or accounting advice.
B56: Version 1.0.0 (2026-10-26) · © NoviraNest. Licensed for use by one business. Do not resell or share the file. See LICENSE.txt.

Sheet Dashboard
B2: =cfg_Business | M2: NoviraNest
B3: ="Executive Dashboard · "&cfg_PeriodLabel&" · "&cfg_Currency | M3: Food Truck Profit & Pricing PRO
B4: › Start Here | D4: › Settings | F4: › Menu Pricing | H4: › Sales Log | J4: › Expenses | L4: › Break-Even | N4: › Event Predictor | P4: › Scenario Simulator
B6: =IF(ps_lines=0,"No sales recorded for "&cfg_PeriodLabel&" yet. Start with Settings, then add your menu, and log sales on the Sales Log - this dashboard fills in automatically.",IF(ISNUMBER(SEARCH("DEMO",cfg_Business)),"SAMPLE DATA: fictional demo business for illustration only - not real results. Use the TEMPLATE file for your own business.",""))
B8: TOTAL REVENUE | F8: GROSS PROFIT | J8: NET PROFIT | N8: NET PROFIT MARGIN
B9: =IF(N(ps_rev)<0,"-","")&cfg_Symbol&TEXT(ABS(N(ps_rev)),"#,##0") | F9: =IF(N(ps_gp)<0,"-","")&cfg_Symbol&TEXT(ABS(N(ps_gp)),"#,##0") | J9: =IF(N(ps_net)<0,"-","")&cfg_Symbol&TEXT(ABS(N(ps_net)),"#,##0") | N9: =IF(ps_nm="","-",TEXT(ps_nm,"0.0%"))
B10: =TEXT(ps_items,"#,##0")&" items sold · avg "&cfg_Symbol&TEXT(N(ps_avgp),"0.00")&" per item" | F10: =IF(ps_gm="","Gross margin: -","Gross margin: "&TEXT(ps_gm,"0.0%"))&" · after food & packaging" | J10: ="After waste and all operating expenses (before tax)" | N10: ="Net profit / revenue"
B12: MONTHLY OPERATING EXPENSES | F12: COST OF GOODS SOLD | J12: WASTE | N12: BREAK-EVEN PROGRESS
B13: =IF(N(ps_avgopex)<0,"-","")&cfg_Symbol&TEXT(ABS(N(ps_avgopex)),"#,##0") | F13: =IF(N(ps_cogs)<0,"-","")&cfg_Symbol&TEXT(ABS(N(ps_cogs)),"#,##0") | J13: =IF(N(ps_waste)<0,"-","")&cfg_Symbol&TEXT(ABS(N(ps_waste)),"#,##0") | N13: =IF(ps_beprog="","Set up",TEXT(ps_beprog,"0%"))
B14: =IF(cfg_Months=1,"This month","Average of "&ps_active&" active month(s)")&" · total "&cfg_Symbol&TEXT(ps_opex,"#,##0") | F14: =IF(N(ps_rev)=0,"Food + packaging + other variable","= "&TEXT(ps_cogs/ps_rev,"0.0%")&" of revenue (food + packaging)") | J14: =IF(N(ps_rev)=0,"Logged on the Waste Log",TEXT(ps_waste/ps_rev,"0.0%")&" of revenue · from the Waste Log") | N14: =IF(ps_beprog="","Enter fixed costs on Break-Even",REPT("█",MIN(10,ROUND(ps_beprog*10,0)))&REPT("░",MAX(0,10-ROUND(ps_beprog*10,0)))&" of "&cfg_Symbol&TEXT(ps_berev,"#,##0"))
B16: ="MONTHLY PERFORMANCE · "&cfg_Year | J16: ="WHERE THE MONEY GOES · "&cfg_PeriodLabel
B33: ="BEST SELLERS · "&cfg_PeriodLabel | J33: ="MOST PROFITABLE ITEMS · "&cfg_PeriodLabel
B34: # Menu item | F34: Items sold | H34: ="Revenue ("&cfg_Symbol&")" | J34: # Menu item | N34: ="Gross profit ("&cfg_Symbol&")" | P34: Status
B35: =IFERROR(IF(AND(LARGE('Menu Pricing'!$Z$7:$Z$56,1)>=1,INDEX('Menu Pricing'!$V$7:$V$56,MATCH(LARGE('Menu Pricing'!$Z$7:$Z$56,1),'Menu Pricing'!$Z$7:$Z$56,0))>0),"1. "&INDEX('Menu Pricing'!$B$7:$B$56,MATCH(LARGE('Menu Pricing'!$Z$7:$Z$56,1),'Menu Pricing'!$Z$7:$Z$56,0)),IF(1=1,"No sales in this period yet","")),"") | F35: =IFERROR(IF(AND(LARGE('Menu Pricing'!$Z$7:$Z$56,1)>=1,INDEX('Menu Pricing'!$V$7:$V$56,MATCH(LARGE('Menu Pricing'!$Z$7:$Z$56,1),'Menu Pricing'!$Z$7:$Z$56,0))>0),INDEX('Menu Pricing'!$V$7:$V$56,MATCH(LARGE('Menu Pricing'!$Z$7:$Z$56,1),'Menu Pricing'!$Z$7:$Z$56,0)),""),"") | H35: =IFERROR(IF(AND(LARGE('Menu Pricing'!$Z$7:$Z$56,1)>=1,INDEX('Menu Pricing'!$V$7:$V$56,MATCH(LARGE('Menu Pricing'!$Z$7:$Z$56,1),'Menu Pricing'!$Z$7:$Z$56,0))>0),IF(N(INDEX('Menu Pricing'!$W$7:$W$56,MATCH(LARGE('Menu Pricing'!$Z$7:$Z$56,1),'Menu Pricing'!$Z$7:$Z$56,0)))<0,"-","")&cfg_Symbol&TEXT(ABS(N(INDEX('Menu Pricing'!$W$7:$W$56,MATCH(LARGE('Menu Pricing'!$Z$7:$Z$56,1),'Menu Pricing'!$Z$7:$Z$56,0)))),"#,##0"),""),"") | J35: =IFERROR(IF(AND(LARGE('Menu Pricing'!$AA$7:$AA$56,1)>-1E+14,INDEX('Menu Pricing'!$V$7:$V$56,MATCH(LARGE('Menu Pricing'!$AA$7:$AA$56,1),'Menu Pricing'!$AA$7:$AA$56,0))>0),"1. "&INDEX('Menu Pricing'!$B$7:$B$56,MATCH(LARGE('Menu Pricing'!$AA$7:$AA$56,1),'Menu Pricing'!$AA$7:$AA$56,0)),IF(1=1,"No sales in this period yet","")),"") | N35: =IFERROR(IF(AND(LARGE('Menu Pricing'!$AA$7:$AA$56,1)>-1E+14,INDEX('Menu Pricing'!$V$7:$V$56,MATCH(LARGE('Menu Pricing'!$AA$7:$AA$56,1),'Menu Pricing'!$AA$7:$AA$56,0))>0),INDEX('Menu Pricing'!$X$7:$X$56,MATCH(LARGE('Menu Pricing'!$AA$7:$AA$56,1),'Menu Pricing'!$AA$7:$AA$56,0)),""),"") | P35: =IFERROR(IF(AND(LARGE('Menu Pricing'!$AA$7:$AA$56,1)>-1E+14,INDEX('Menu Pricing'!$V$7:$V$56,MATCH(LARGE('Menu Pricing'!$AA$7:$AA$56,1),'Menu Pricing'!$AA$7:$AA$56,0))>0),INDEX('Menu Pricing'!$T$7:$T$56,MATCH(LARGE('Menu Pricing'!$AA$7:$AA$56,1),'Menu Pricing'!$AA$7:$AA$56,0)),""),"")
B36: =IFERROR(IF(AND(LARGE('Menu Pricing'!$Z$7:$Z$56,2)>=1,INDEX('Menu Pricing'!$V$7:$V$56,MATCH(LARGE('Menu Pricing'!$Z$7:$Z$56,2),'Menu Pricing'!$Z$7:$Z$56,0))>0),"2. "&INDEX('Menu Pricing'!$B$7:$B$56,MATCH(LARGE('Menu Pricing'!$Z$7:$Z$56,2),'Menu Pricing'!$Z$7:$Z$56,0)),IF(2=1,"No sales in this period yet","")),"") | F36: =IFERROR(IF(AND(LARGE('Menu Pricing'!$Z$7:$Z$56,2)>=1,INDEX('Menu Pricing'!$V$7:$V$56,MATCH(LARGE('Menu Pricing'!$Z$7:$Z$56,2),'Menu Pricing'!$Z$7:$Z$56,0))>0),INDEX('Menu Pricing'!$V$7:$V$56,MATCH(LARGE('Menu Pricing'!$Z$7:$Z$56,2),'Menu Pricing'!$Z$7:$Z$56,0)),""),"") | H36: =IFERROR(IF(AND(LARGE('Menu Pricing'!$Z$7:$Z$56,2)>=1,INDEX('Menu Pricing'!$V$7:$V$56,MATCH(LARGE('Menu Pricing'!$Z$7:$Z$56,2),'Menu Pricing'!$Z$7:$Z$56,0))>0),IF(N(INDEX('Menu Pricing'!$W$7:$W$56,MATCH(LARGE('Menu Pricing'!$Z$7:$Z$56,2),'Menu Pricing'!$Z$7:$Z$56,0)))<0,"-","")&cfg_Symbol&TEXT(ABS(N(INDEX('Menu Pricing'!$W$7:$W$56,MATCH(LARGE('Menu Pricing'!$Z$7:$Z$56,2),'Menu Pricing'!$Z$7:$Z$56,0)))),"#,##0"),""),"") | J36: =IFERROR(IF(AND(LARGE('Menu Pricing'!$AA$7:$AA$56,2)>-1E+14,INDEX('Menu Pricing'!$V$7:$V$56,MATCH(LARGE('Menu Pricing'!$AA$7:$AA$56,2),'Menu Pricing'!$AA$7:$AA$56,0))>0),"2. "&INDEX('Menu Pricing'!$B$7:$B$56,MATCH(LARGE('Menu Pricing'!$AA$7:$AA$56,2),'Menu Pricing'!$AA$7:$AA$56,0)),IF(2=1,"No sales in this period yet","")),"") | N36: =IFERROR(IF(AND(LARGE('Menu Pricing'!$AA$7:$AA$56,2)>-1E+14,INDEX('Menu Pricing'!$V$7:$V$56,MATCH(LARGE('Menu Pricing'!$AA$7:$AA$56,2),'Menu Pricing'!$AA$7:$AA$56,0))>0),INDEX('Menu Pricing'!$X$7:$X$56,MATCH(LARGE('Menu Pricing'!$AA$7:$AA$56,2),'Menu Pricing'!$AA$7:$AA$56,0)),""),"") | P36: =IFERROR(IF(AND(LARGE('Menu Pricing'!$AA$7:$AA$56,2)>-1E+14,INDEX('Menu Pricing'!$V$7:$V$56,MATCH(LARGE('Menu Pricing'!$AA$7:$AA$56,2),'Menu Pricing'!$AA$7:$AA$56,0))>0),INDEX('Menu Pricing'!$T$7:$T$56,MATCH(LARGE('Menu Pricing'!$AA$7:$AA$56,2),'Menu Pricing'!$AA$7:$AA$56,0)),""),"")
B37: =IFERROR(IF(AND(LARGE('Menu Pricing'!$Z$7:$Z$56,3)>=1,INDEX('Menu Pricing'!$V$7:$V$56,MATCH(LARGE('Menu Pricing'!$Z$7:$Z$56,3),'Menu Pricing'!$Z$7:$Z$56,0))>0),"3. "&INDEX('Menu Pricing'!$B$7:$B$56,MATCH(LARGE('Menu Pricing'!$Z$7:$Z$56,3),'Menu Pricing'!$Z$7:$Z$56,0)),IF(3=1,"No sales in this period yet","")),"") | F37: =IFERROR(IF(AND(LARGE('Menu Pricing'!$Z$7:$Z$56,3)>=1,INDEX('Menu Pricing'!$V$7:$V$56,MATCH(LARGE('Menu Pricing'!$Z$7:$Z$56,3),'Menu Pricing'!$Z$7:$Z$56,0))>0),INDEX('Menu Pricing'!$V$7:$V$56,MATCH(LARGE('Menu Pricing'!$Z$7:$Z$56,3),'Menu Pricing'!$Z$7:$Z$56,0)),""),"") | H37: =IFERROR(IF(AND(LARGE('Menu Pricing'!$Z$7:$Z$56,3)>=1,INDEX('Menu Pricing'!$V$7:$V$56,MATCH(LARGE('Menu Pricing'!$Z$7:$Z$56,3),'Menu Pricing'!$Z$7:$Z$56,0))>0),IF(N(INDEX('Menu Pricing'!$W$7:$W$56,MATCH(LARGE('Menu Pricing'!$Z$7:$Z$56,3),'Menu Pricing'!$Z$7:$Z$56,0)))<0,"-","")&cfg_Symbol&TEXT(ABS(N(INDEX('Menu Pricing'!$W$7:$W$56,MATCH(LARGE('Menu Pricing'!$Z$7:$Z$56,3),'Menu Pricing'!$Z$7:$Z$56,0)))),"#,##0"),""),"") | J37: =IFERROR(IF(AND(LARGE('Menu Pricing'!$AA$7:$AA$56,3)>-1E+14,INDEX('Menu Pricing'!$V$7:$V$56,MATCH(LARGE('Menu Pricing'!$AA$7:$AA$56,3),'Menu Pricing'!$AA$7:$AA$56,0))>0),"3. "&INDEX('Menu Pricing'!$B$7:$B$56,MATCH(LARGE('Menu Pricing'!$AA$7:$AA$56,3),'Menu Pricing'!$AA$7:$AA$56,0)),IF(3=1,"No sales in this period yet","")),"") | N37: =IFERROR(IF(AND(LARGE('Menu Pricing'!$AA$7:$AA$56,3)>-1E+14,INDEX('Menu Pricing'!$V$7:$V$56,MATCH(LARGE('Menu Pricing'!$AA$7:$AA$56,3),'Menu Pricing'!$AA$7:$AA$56,0))>0),INDEX('Menu Pricing'!$X$7:$X$56,MATCH(LARGE('Menu Pricing'!$AA$7:$AA$56,3),'Menu Pricing'!$AA$7:$AA$56,0)),""),"") | P37: =IFERROR(IF(AND(LARGE('Menu Pricing'!$AA$7:$AA$56,3)>-1E+14,INDEX('Menu Pricing'!$V$7:$V$56,MATCH(LARGE('Menu Pricing'!$AA$7:$AA$56,3),'Menu Pricing'!$AA$7:$AA$56,0))>0),INDEX('Menu Pricing'!$T$7:$T$56,MATCH(LARGE('Menu Pricing'!$AA$7:$AA$56,3),'Menu Pricing'!$AA$7:$AA$56,0)),""),"")
B38: =IFERROR(IF(AND(LARGE('Menu Pricing'!$Z$7:$Z$56,4)>=1,INDEX('Menu Pricing'!$V$7:$V$56,MATCH(LARGE('Menu Pricing'!$Z$7:$Z$56,4),'Menu Pricing'!$Z$7:$Z$56,0))>0),"4. "&INDEX('Menu Pricing'!$B$7:$B$56,MATCH(LARGE('Menu Pricing'!$Z$7:$Z$56,4),'Menu Pricing'!$Z$7:$Z$56,0)),IF(4=1,"No sales in this period yet","")),"") | F38: =IFERROR(IF(AND(LARGE('Menu Pricing'!$Z$7:$Z$56,4)>=1,INDEX('Menu Pricing'!$V$7:$V$56,MATCH(LARGE('Menu Pricing'!$Z$7:$Z$56,4),'Menu Pricing'!$Z$7:$Z$56,0))>0),INDEX('Menu Pricing'!$V$7:$V$56,MATCH(LARGE('Menu Pricing'!$Z$7:$Z$56,4),'Menu Pricing'!$Z$7:$Z$56,0)),""),"") | H38: =IFERROR(IF(AND(LARGE('Menu Pricing'!$Z$7:$Z$56,4)>=1,INDEX('Menu Pricing'!$V$7:$V$56,MATCH(LARGE('Menu Pricing'!$Z$7:$Z$56,4),'Menu Pricing'!$Z$7:$Z$56,0))>0),IF(N(INDEX('Menu Pricing'!$W$7:$W$56,MATCH(LARGE('Menu Pricing'!$Z$7:$Z$56,4),'Menu Pricing'!$Z$7:$Z$56,0)))<0,"-","")&cfg_Symbol&TEXT(ABS(N(INDEX('Menu Pricing'!$W$7:$W$56,MATCH(LARGE('Menu Pricing'!$Z$7:$Z$56,4),'Menu Pricing'!$Z$7:$Z$56,0)))),"#,##0"),""),"") | J38: =IFERROR(IF(AND(LARGE('Menu Pricing'!$AA$7:$AA$56,4)>-1E+14,INDEX('Menu Pricing'!$V$7:$V$56,MATCH(LARGE('Menu Pricing'!$AA$7:$AA$56,4),'Menu Pricing'!$AA$7:$AA$56,0))>0),"4. "&INDEX('Menu Pricing'!$B$7:$B$56,MATCH(LARGE('Menu Pricing'!$AA$7:$AA$56,4),'Menu Pricing'!$AA$7:$AA$56,0)),IF(4=1,"No sales in this period yet","")),"") | N38: =IFERROR(IF(AND(LARGE('Menu Pricing'!$AA$7:$AA$56,4)>-1E+14,INDEX('Menu Pricing'!$V$7:$V$56,MATCH(LARGE('Menu Pricing'!$AA$7:$AA$56,4),'Menu Pricing'!$AA$7:$AA$56,0))>0),INDEX('Menu Pricing'!$X$7:$X$56,MATCH(LARGE('Menu Pricing'!$AA$7:$AA$56,4),'Menu Pricing'!$AA$7:$AA$56,0)),""),"") | P38: =IFERROR(IF(AND(LARGE('Menu Pricing'!$AA$7:$AA$56,4)>-1E+14,INDEX('Menu Pricing'!$V$7:$V$56,MATCH(LARGE('Menu Pricing'!$AA$7:$AA$56,4),'Menu Pricing'!$AA$7:$AA$56,0))>0),INDEX('Menu Pricing'!$T$7:$T$56,MATCH(LARGE('Menu Pricing'!$AA$7:$AA$56,4),'Menu Pricing'!$AA$7:$AA$56,0)),""),"")
B39: =IFERROR(IF(AND(LARGE('Menu Pricing'!$Z$7:$Z$56,5)>=1,INDEX('Menu Pricing'!$V$7:$V$56,MATCH(LARGE('Menu Pricing'!$Z$7:$Z$56,5),'Menu Pricing'!$Z$7:$Z$56,0))>0),"5. "&INDEX('Menu Pricing'!$B$7:$B$56,MATCH(LARGE('Menu Pricing'!$Z$7:$Z$56,5),'Menu Pricing'!$Z$7:$Z$56,0)),IF(5=1,"No sales in this period yet","")),"") | F39: =IFERROR(IF(AND(LARGE('Menu Pricing'!$Z$7:$Z$56,5)>=1,INDEX('Menu Pricing'!$V$7:$V$56,MATCH(LARGE('Menu Pricing'!$Z$7:$Z$56,5),'Menu Pricing'!$Z$7:$Z$56,0))>0),INDEX('Menu Pricing'!$V$7:$V$56,MATCH(LARGE('Menu Pricing'!$Z$7:$Z$56,5),'Menu Pricing'!$Z$7:$Z$56,0)),""),"") | H39: =IFERROR(IF(AND(LARGE('Menu Pricing'!$Z$7:$Z$56,5)>=1,INDEX('Menu Pricing'!$V$7:$V$56,MATCH(LARGE('Menu Pricing'!$Z$7:$Z$56,5),'Menu Pricing'!$Z$7:$Z$56,0))>0),IF(N(INDEX('Menu Pricing'!$W$7:$W$56,MATCH(LARGE('Menu Pricing'!$Z$7:$Z$56,5),'Menu Pricing'!$Z$7:$Z$56,0)))<0,"-","")&cfg_Symbol&TEXT(ABS(N(INDEX('Menu Pricing'!$W$7:$W$56,MATCH(LARGE('Menu Pricing'!$Z$7:$Z$56,5),'Menu Pricing'!$Z$7:$Z$56,0)))),"#,##0"),""),"") | J39: =IFERROR(IF(AND(LARGE('Menu Pricing'!$AA$7:$AA$56,5)>-1E+14,INDEX('Menu Pricing'!$V$7:$V$56,MATCH(LARGE('Menu Pricing'!$AA$7:$AA$56,5),'Menu Pricing'!$AA$7:$AA$56,0))>0),"5. "&INDEX('Menu Pricing'!$B$7:$B$56,MATCH(LARGE('Menu Pricing'!$AA$7:$AA$56,5),'Menu Pricing'!$AA$7:$AA$56,0)),IF(5=1,"No sales in this period yet","")),"") | N39: =IFERROR(IF(AND(LARGE('Menu Pricing'!$AA$7:$AA$56,5)>-1E+14,INDEX('Menu Pricing'!$V$7:$V$56,MATCH(LARGE('Menu Pricing'!$AA$7:$AA$56,5),'Menu Pricing'!$AA$7:$AA$56,0))>0),INDEX('Menu Pricing'!$X$7:$X$56,MATCH(LARGE('Menu Pricing'!$AA$7:$AA$56,5),'Menu Pricing'!$AA$7:$AA$56,0)),""),"") | P39: =IFERROR(IF(AND(LARGE('Menu Pricing'!$AA$7:$AA$56,5)>-1E+14,INDEX('Menu Pricing'!$V$7:$V$56,MATCH(LARGE('Menu Pricing'!$AA$7:$AA$56,5),'Menu Pricing'!$AA$7:$AA$56,0))>0),INDEX('Menu Pricing'!$T$7:$T$56,MATCH(LARGE('Menu Pricing'!$AA$7:$AA$56,5),'Menu Pricing'!$AA$7:$AA$56,0)),""),"")
B41: ALERTS & DATA CHECKS
B42: =COUNTIF('Menu Pricing'!$T$7:$T$56,"LOSS") | C42: menu item(s) priced BELOW cost | H42: Open › | J42: =SUMPRODUCT(('Recipe Builder'!$G$7:$G$406<>"")*('Recipe Builder'!$G$7:$G$406<>"OK")) | K42: recipe line(s) with a unit or setup problem | P42: Open ›
B43: =COUNTIF('Menu Pricing'!$T$7:$T$56,"Below target") | C43: menu item(s) below your target margin | H43: Open › | J43: =SUMPRODUCT(('Sales Log'!$N$7:$N$3006<>"")*('Sales Log'!$N$7:$N$3006<>"OK")) | K43: sales row(s) that need fixing (not counted) | P43: Open ›
B44: =COUNTIF('Inventory'!$P$7:$P$106,"Reorder") | C44: ingredient(s) at or below reorder level | H44: Open › | J44: =ps_unclassified | K44: expense row(s) that need fixing (not counted) | P44: Open ›
B45: =COUNTIF('Inventory'!$P$7:$P$106,"Recount (negative)") | C45: ingredient(s) with negative stock - recount | H45: Open › | J45: =SUMPRODUCT(('Waste Log'!$H$7:$H$506<>"")*('Waste Log'!$H$7:$H$506<>"OK")) | K45: waste row(s) that need fixing (not counted) | P45: Open ›
B47: ="Profit model: Revenue - COGS (recipe cost x items sold) = Gross profit; minus waste and operating expenses = Net profit. Ingredient purchases and owner's draw are excluded so nothing is counted twice. · NoviraNest v1.0.0"

Sheet Settings
B2: Settings | F2: NoviraNest
B3: Set these once. Every sheet reads from here.
B4: › Start Here | C4: › Dashboard | D4: › Menu Pricing
B5: Setting | C5: Your value | E5: What it does
B6: Business name | C6: Your Food Truck Name | E6: Shown on the Dashboard title.
B7: Currency | C7: USD | E7: USD ($) or GBP (£). Changes symbols and formats only - amounts are NOT converted.
B8: Reporting year | C8: 2026 | E8: The year shown in the Monthly Report and Dashboard charts.
B9: Dashboard period | C9: Full Year | E9: Full Year or a single month of the reporting year. KPI cards and item rankings follow this.
B10: Labour cost per hour (incl. payroll taxes) | E10: Used only to price prep time on Menu Pricing. Real wages go in Expenses (no double counting).
B11: Default target profit margin | C11: 0.6 | E11: Margin = profit / price. Used for suggested prices unless an item has its own target.
B12: Target food cost % | C12: 0.32 | E12: Ingredient cost / price. Items above this are flagged 'High food cost'. Typical: 25-35%.
B13: Round suggested prices up to | C13: 0.25 | E13: Suggested prices are rounded UP to this step (0 = no rounding).
B14: Last stock count date | E14: Date you last counted stock. Inventory usage and waste are counted from this date.
B17: AUTOMATIC VALUES (used by formulas - do not edit)
B18: Currency symbol | C18: =IF($C$7="GBP","£","$")
B19: Active currency | C19: =IF($C$7="GBP","GBP","USD")
B20: Period month (0 = full year) | C20: =IFERROR(MATCH($C$9,lst_Period,0)-1,0)
B21: Reporting year used | C21: =IF(AND(ISNUMBER($C$8),$C$8>=2000,$C$8<=2100),INT($C$8),2026)
B22: Period start | C22: =IF($C$20=0,DATE($C$21,1,1),DATE($C$21,$C$20,1))
B23: Period end | C23: =IF($C$20=0,DATE($C$21,12,31),EOMONTH($C$22,0))
B24: Months in period | C24: =IF($C$20=0,12,1)
B25: Period label | C25: =IF($C$20=0,"Full Year "&$C$21,$C$9&" "&$C$21)
B26: Stock count date used | C26: =IF(ISNUMBER($C$14),$C$14,DATE(2000,1,1))
B27: Labour rate used | C27: =N($C$10)
B28: Target margin used | C28: =IF(AND(ISNUMBER($C$11),$C$11<0.95),MAX(0,$C$11),0.6)
B29: Food cost target used | C29: =IF(ISNUMBER($C$12),$C$12,0.32)
B30: Rounding step used | C30: =IF(AND(ISNUMBER($C$13),$C$13>0),$C$13,0)
B32: Tip: switch Dashboard period to a month (e.g. 'July') to see that month's KPIs and best sellers. Charts on the Dashboard always show all 12 months of the reporting year.

Sheet Menu Pricing
B2: Smart Menu Pricing | Y2: NoviraNest
B3: Cost per serving, suggested price, real margin vs markup, and what to fix. Sales columns follow the Dashboard period.
B4: › Start Here | C4: › Dashboard | E4: › Recipe Builder | G4: › Settings
B5: ITEM | D5: COST PER SERVING | L5: PRICING TARGET | O5: YOUR PRICE & RESULT | V5: SALES (DASHBOARD PERIOD)
B6: Menu item | C6: Category | D6: ="Recipe ingredients ("&cfg_Symbol&")" | E6: ="Ingredient override ("&cfg_Symbol&")" | F6: ="Ingredient cost used ("&cfg_Symbol&")" | G6: ="Packaging ("&cfg_Symbol&")" | H6: Prep minutes | I6: ="Prep labour ("&cfg_Symbol&")" | J6: ="Other variable ("&cfg_Symbol&")" | K6: ="TOTAL COST per serving ("&cfg_Symbol&")" | L6: Target margin | M6: Target used | N6: ="Suggested price ("&cfg_Symbol&")" | O6: ="YOUR MENU PRICE ("&cfg_Symbol&")" | P6: ="Profit per serving ("&cfg_Symbol&")" | Q6: Actual margin | R6: Markup on cost | S6: Food cost % | T6: Status | U6: Recommendation | V6: Items sold | W6: ="Revenue ("&cfg_Symbol&")" | X6: ="Gross profit ("&cfg_Symbol&")" | Y6: Sales mix
D7: =IF($B7="","",SUMIFS('Recipe Builder'!$J$7:$J$406,'Recipe Builder'!$B$7:$B$406,$B7)) | F7: =IF($B7="","",IF(ISNUMBER($E7),$E7,N($D7))) | I7: =IF($B7="","",N($H7)/60*cfg_LaborRate) | K7: =IF($B7="","",$F7+N($G7)+$I7+N($J7)) | M7: =IF($B7="","",IF(AND(ISNUMBER($L7),$L7<0.95),MAX(0,$L7),cfg_TargetMargin)) | N7: =IF($B7="","",IF(cfg_Round>0,CEILING($K7/(1-$M7),cfg_Round),ROUND($K7/(1-$M7),2))) | P7: =IF(OR($B7="",N($O7)<=0),"",$O7-$K7) | Q7: =IF(OR($B7="",N($O7)<=0),"",$P7/$O7) | R7: =IF(OR($B7="",N($O7)<=0,N($K7)<=0),"",$P7/$K7) | S7: =IF(OR($B7="",N($O7)<=0),"",$F7/$O7) | T7: =IF($B7="","",IF(COUNTIF($B$7:$B$56,$B7)>1,"Duplicate name",IF(N($O7)<=0,"Set a price",IF(N($K7)<=0,"Add costs",IF($P7<0,"LOSS",IF($Q7<$M7-0.00001,"Below target",IF($S7>cfg_FoodCostTarget,"High food cost","Healthy"))))))) | U7: =IF($T7="","",IF($T7="Duplicate name","Each menu item needs a unique name",IF($T7="Set a price","Suggested starting price: "&cfg_Symbol&TEXT($N7,"0.00"),IF($T7="Add costs","Build the recipe or type an ingredient cost override",IF($T7="LOSS","Losing "&cfg_Symbol&TEXT(-$P7,"0.00")&" per sale - raise to "&cfg_Symbol&TEXT($N7,"0.00"),IF($T7="Below target","Raise to "&cfg_Symbol&TEXT($N7,"0.00")&" for a "&TEXT($M7,"0%")&" margin",IF($T7="High food cost","Margin OK; food cost "&TEXT($S7,"0%")&" is above "&TEXT(cfg_FoodCostTarget,"0%")&" target","On target"))))))) | V7: =IF($B7="","",SUMIFS('Sales Log'!$D$7:$D$3006,'Sales Log'!$C$7:$C$3006,$B7,'Sales Log'!$B$7:$B$3006,">="&cfg_Start,'Sales Log'!$B$7:$B$3006,"<="&cfg_End,'Sales Log'!$N$7:$N$3006,"OK")) | W7: =IF($B7="","",SUMIFS('Sales Log'!$I$7:$I$3006,'Sales Log'!$C$7:$C$3006,$B7,'Sales Log'!$B$7:$B$3006,">="&cfg_Start,'Sales Log'!$B$7:$B$3006,"<="&cfg_End,'Sales Log'!$N$7:$N$3006,"OK")) | X7: =IF($B7="","",SUMIFS('Sales Log'!$L$7:$L$3006,'Sales Log'!$C$7:$C$3006,$B7,'Sales Log'!$B$7:$B$3006,">="&cfg_Start,'Sales Log'!$B$7:$B$3006,"<="&cfg_End,'Sales Log'!$N$7:$N$3006,"OK")) | Y7: =IF($B7="","",IF(SUM($V$7:$V$56)=0,0,$V7/SUM($V$7:$V$56))) | Z7: =IF($B7="",-1,N($V7)+ROW()/1000000) | AA7: =IF($B7="",-1E+15,N($X7)+ROW()/1000000)
D8: =IF($B8="","",SUMIFS('Recipe Builder'!$J$7:$J$406,'Recipe Builder'!$B$7:$B$406,$B8)) | F8: =IF($B8="","",IF(ISNUMBER($E8),$E8,N($D8))) | I8: =IF($B8="","",N($H8)/60*cfg_LaborRate) | K8: =IF($B8="","",$F8+N($G8)+$I8+N($J8)) | M8: =IF($B8="","",IF(AND(ISNUMBER($L8),$L8<0.95),MAX(0,$L8),cfg_TargetMargin)) | N8: =IF($B8="","",IF(cfg_Round>0,CEILING($K8/(1-$M8),cfg_Round),ROUND($K8/(1-$M8),2))) | P8: =IF(OR($B8="",N($O8)<=0),"",$O8-$K8) | Q8: =IF(OR($B8="",N($O8)<=0),"",$P8/$O8) | R8: =IF(OR($B8="",N($O8)<=0,N($K8)<=0),"",$P8/$K8) | S8: =IF(OR($B8="",N($O8)<=0),"",$F8/$O8) | T8: =IF($B8="","",IF(COUNTIF($B$7:$B$56,$B8)>1,"Duplicate name",IF(N($O8)<=0,"Set a price",IF(N($K8)<=0,"Add costs",IF($P8<0,"LOSS",IF($Q8<$M8-0.00001,"Below target",IF($S8>cfg_FoodCostTarget,"High food cost","Healthy"))))))) | U8: =IF($T8="","",IF($T8="Duplicate name","Each menu item needs a unique name",IF($T8="Set a price","Suggested starting price: "&cfg_Symbol&TEXT($N8,"0.00"),IF($T8="Add costs","Build the recipe or type an ingredient cost override",IF($T8="LOSS","Losing "&cfg_Symbol&TEXT(-$P8,"0.00")&" per sale - raise to "&cfg_Symbol&TEXT($N8,"0.00"),IF($T8="Below target","Raise to "&cfg_Symbol&TEXT($N8,"0.00")&" for a "&TEXT($M8,"0%")&" margin",IF($T8="High food cost","Margin OK; food cost "&TEXT($S8,"0%")&" is above "&TEXT(cfg_FoodCostTarget,"0%")&" target","On target"))))))) | V8: =IF($B8="","",SUMIFS('Sales Log'!$D$7:$D$3006,'Sales Log'!$C$7:$C$3006,$B8,'Sales Log'!$B$7:$B$3006,">="&cfg_Start,'Sales Log'!$B$7:$B$3006,"<="&cfg_End,'Sales Log'!$N$7:$N$3006,"OK")) | W8: =IF($B8="","",SUMIFS('Sales Log'!$I$7:$I$3006,'Sales Log'!$C$7:$C$3006,$B8,'Sales Log'!$B$7:$B$3006,">="&cfg_Start,'Sales Log'!$B$7:$B$3006,"<="&cfg_End,'Sales Log'!$N$7:$N$3006,"OK")) | X8: =IF($B8="","",SUMIFS('Sales Log'!$L$7:$L$3006,'Sales Log'!$C$7:$C$3006,$B8,'Sales Log'!$B$7:$B$3006,">="&cfg_Start,'Sales Log'!$B$7:$B$3006,"<="&cfg_End,'Sales Log'!$N$7:$N$3006,"OK")) | Y8: =IF($B8="","",IF(SUM($V$7:$V$56)=0,0,$V8/SUM($V$7:$V$56))) | Z8: =IF($B8="",-1,N($V8)+ROW()/1000000) | AA8: =IF($B8="",-1E+15,N($X8)+ROW()/1000000)
D9: =IF($B9="","",SUMIFS('Recipe Builder'!$J$7:$J$406,'Recipe Builder'!$B$7:$B$406,$B9)) | F9: =IF($B9="","",IF(ISNUMBER($E9),$E9,N($D9))) | I9: =IF($B9="","",N($H9)/60*cfg_LaborRate) | K9: =IF($B9="","",$F9+N($G9)+$I9+N($J9)) | M9: =IF($B9="","",IF(AND(ISNUMBER($L9),$L9<0.95),MAX(0,$L9),cfg_TargetMargin)) | N9: =IF($B9="","",IF(cfg_Round>0,CEILING($K9/(1-$M9),cfg_Round),ROUND($K9/(1-$M9),2))) | P9: =IF(OR($B9="",N($O9)<=0),"",$O9-$K9) | Q9: =IF(OR($B9="",N($O9)<=0),"",$P9/$O9) | R9: =IF(OR($B9="",N($O9)<=0,N($K9)<=0),"",$P9/$K9) | S9: =IF(OR($B9="",N($O9)<=0),"",$F9/$O9) | T9: =IF($B9="","",IF(COUNTIF($B$7:$B$56,$B9)>1,"Duplicate name",IF(N($O9)<=0,"Set a price",IF(N($K9)<=0,"Add costs",IF($P9<0,"LOSS",IF($Q9<$M9-0.00001,"Below target",IF($S9>cfg_FoodCostTarget,"High food cost","Healthy"))))))) | U9: =IF($T9="","",IF($T9="Duplicate name","Each menu item needs a unique name",IF($T9="Set a price","Suggested starting price: "&cfg_Symbol&TEXT($N9,"0.00"),IF($T9="Add costs","Build the recipe or type an ingredient cost override",IF($T9="LOSS","Losing "&cfg_Symbol&TEXT(-$P9,"0.00")&" per sale - raise to "&cfg_Symbol&TEXT($N9,"0.00"),IF($T9="Below target","Raise to "&cfg_Symbol&TEXT($N9,"0.00")&" for a "&TEXT($M9,"0%")&" margin",IF($T9="High food cost","Margin OK; food cost "&TEXT($S9,"0%")&" is above "&TEXT(cfg_FoodCostTarget,"0%")&" target","On target"))))))) | V9: =IF($B9="","",SUMIFS('Sales Log'!$D$7:$D$3006,'Sales Log'!$C$7:$C$3006,$B9,'Sales Log'!$B$7:$B$3006,">="&cfg_Start,'Sales Log'!$B$7:$B$3006,"<="&cfg_End,'Sales Log'!$N$7:$N$3006,"OK")) | W9: =IF($B9="","",SUMIFS('Sales Log'!$I$7:$I$3006,'Sales Log'!$C$7:$C$3006,$B9,'Sales Log'!$B$7:$B$3006,">="&cfg_Start,'Sales Log'!$B$7:$B$3006,"<="&cfg_End,'Sales Log'!$N$7:$N$3006,"OK")) | X9: =IF($B9="","",SUMIFS('Sales Log'!$L$7:$L$3006,'Sales Log'!$C$7:$C$3006,$B9,'Sales Log'!$B$7:$B$3006,">="&cfg_Start,'Sales Log'!$B$7:$B$3006,"<="&cfg_End,'Sales Log'!$N$7:$N$3006,"OK")) | Y9: =IF($B9="","",IF(SUM($V$7:$V$56)=0,0,$V9/SUM($V$7:$V$56))) | Z9: =IF($B9="",-1,N($V9)+ROW()/1000000) | AA9: =IF($B9="",-1E+15,N($X9)+ROW()/1000000)
D10: =IF($B10="","",SUMIFS('Recipe Builder'!$J$7:$J$406,'Recipe Builder'!$B$7:$B$406,$B10)) | F10: =IF($B10="","",IF(ISNUMBER($E10),$E10,N($D10))) | I10: =IF($B10="","",N($H10)/60*cfg_LaborRate) | K10: =IF($B10="","",$F10+N($G10)+$I10+N($J10)) | M10: =IF($B10="","",IF(AND(ISNUMBER($L10),$L10<0.95),MAX(0,$L10),cfg_TargetMargin)) | N10: =IF($B10="","",IF(cfg_Round>0,CEILING($K10/(1-$M10),cfg_Round),ROUND($K10/(1-$M10),2))) | P10: =IF(OR($B10="",N($O10)<=0),"",$O10-$K10) | Q10: =IF(OR($B10="",N($O10)<=0),"",$P10/$O10) | R10: =IF(OR($B10="",N($O10)<=0,N($K10)<=0),"",$P10/$K10) | S10: =IF(OR($B10="",N($O10)<=0),"",$F10/$O10) | T10: =IF($B10="","",IF(COUNTIF($B$7:$B$56,$B10)>1,"Duplicate name",IF(N($O10)<=0,"Set a price",IF(N($K10)<=0,"Add costs",IF($P10<0,"LOSS",IF($Q10<$M10-0.00001,"Below target",IF($S10>cfg_FoodCostTarget,"High food cost","Healthy"))))))) | U10: =IF($T10="","",IF($T10="Duplicate name","Each menu item needs a unique name",IF($T10="Set a price","Suggested starting price: "&cfg_Symbol&TEXT($N10,"0.00"),IF($T10="Add costs","Build the recipe or type an ingredient cost override",IF($T10="LOSS","Losing "&cfg_Symbol&TEXT(-$P10,"0.00")&" per sale - raise to "&cfg_Symbol&TEXT($N10,"0.00"),IF($T10="Below target","Raise to "&cfg_Symbol&TEXT($N10,"0.00")&" for a "&TEXT($M10,"0%")&" margin",IF($T10="High food cost","Margin OK; food cost "&TEXT($S10,"0%")&" is above "&TEXT(cfg_FoodCostTarget,"0%")&" target","On target"))))))) | V10: =IF($B10="","",SUMIFS('Sales Log'!$D$7:$D$3006,'Sales Log'!$C$7:$C$3006,$B10,'Sales Log'!$B$7:$B$3006,">="&cfg_Start,'Sales Log'!$B$7:$B$3006,"<="&cfg_End,'Sales Log'!$N$7:$N$3006,"OK")) | W10: =IF($B10="","",SUMIFS('Sales Log'!$I$7:$I$3006,'Sales Log'!$C$7:$C$3006,$B10,'Sales Log'!$B$7:$B$3006,">="&cfg_Start,'Sales Log'!$B$7:$B$3006,"<="&cfg_End,'Sales Log'!$N$7:$N$3006,"OK")) | X10: =IF($B10="","",SUMIFS('Sales Log'!$L$7:$L$3006,'Sales Log'!$C$7:$C$3006,$B10,'Sales Log'!$B$7:$B$3006,">="&cfg_Start,'Sales Log'!$B$7:$B$3006,"<="&cfg_End,'Sales Log'!$N$7:$N$3006,"OK")) | Y10: =IF($B10="","",IF(SUM($V$7:$V$56)=0,0,$V10/SUM($V$7:$V$56))) | Z10: =IF($B10="",-1,N($V10)+ROW()/1000000) | AA10: =IF($B10="",-1E+15,N($X10)+ROW()/1000000)
D11: =IF($B11="","",SUMIFS('Recipe Builder'!$J$7:$J$406,'Recipe Builder'!$B$7:$B$406,$B11)) | F11: =IF($B11="","",IF(ISNUMBER($E11),$E11,N($D11))) | I11: =IF($B11="","",N($H11)/60*cfg_LaborRate) | K11: =IF($B11="","",$F11+N($G11)+$I11+N($J11)) | M11: =IF($B11="","",IF(AND(ISNUMBER($L11),$L11<0.95),MAX(0,$L11),cfg_TargetMargin)) | N11: =IF($B11="","",IF(cfg_Round>0,CEILING($K11/(1-$M11),cfg_Round),ROUND($K11/(1-$M11),2))) | P11: =IF(OR($B11="",N($O11)<=0),"",$O11-$K11) | Q11: =IF(OR($B11="",N($O11)<=0),"",$P11/$O11) | R11: =IF(OR($B11="",N($O11)<=0,N($K11)<=0),"",$P11/$K11) | S11: =IF(OR($B11="",N($O11)<=0),"",$F11/$O11) | T11: =IF($B11="","",IF(COUNTIF($B$7:$B$56,$B11)>1,"Duplicate name",IF(N($O11)<=0,"Set a price",IF(N($K11)<=0,"Add costs",IF($P11<0,"LOSS",IF($Q11<$M11-0.00001,"Below target",IF($S11>cfg_FoodCostTarget,"High food cost","Healthy"))))))) | U11: =IF($T11="","",IF($T11="Duplicate name","Each menu item needs a unique name",IF($T11="Set a price","Suggested starting price: "&cfg_Symbol&TEXT($N11,"0.00"),IF($T11="Add costs","Build the recipe or type an ingredient cost override",IF($T11="LOSS","Losing "&cfg_Symbol&TEXT(-$P11,"0.00")&" per sale - raise to "&cfg_Symbol&TEXT($N11,"0.00"),IF($T11="Below target","Raise to "&cfg_Symbol&TEXT($N11,"0.00")&" for a "&TEXT($M11,"0%")&" margin",IF($T11="High food cost","Margin OK; food cost "&TEXT($S11,"0%")&" is above "&TEXT(cfg_FoodCostTarget,"0%")&" target","On target"))))))) | V11: =IF($B11="","",SUMIFS('Sales Log'!$D$7:$D$3006,'Sales Log'!$C$7:$C$3006,$B11,'Sales Log'!$B$7:$B$3006,">="&cfg_Start,'Sales Log'!$B$7:$B$3006,"<="&cfg_End,'Sales Log'!$N$7:$N$3006,"OK")) | W11: =IF($B11="","",SUMIFS('Sales Log'!$I$7:$I$3006,'Sales Log'!$C$7:$C$3006,$B11,'Sales Log'!$B$7:$B$3006,">="&cfg_Start,'Sales Log'!$B$7:$B$3006,"<="&cfg_End,'Sales Log'!$N$7:$N$3006,"OK")) | X11: =IF($B11="","",SUMIFS('Sales Log'!$L$7:$L$3006,'Sales Log'!$C$7:$C$3006,$B11,'Sales Log'!$B$7:$B$3006,">="&cfg_Start,'Sales Log'!$B$7:$B$3006,"<="&cfg_End,'Sales Log'!$N$7:$N$3006,"OK")) | Y11: =IF($B11="","",IF(SUM($V$7:$V$56)=0,0,$V11/SUM($V$7:$V$56))) | Z11: =IF($B11="",-1,N($V11)+ROW()/1000000) | AA11: =IF($B11="",-1E+15,N($X11)+ROW()/1000000)
D12: =IF($B12="","",SUMIFS('Recipe Builder'!$J$7:$J$406,'Recipe Builder'!$B$7:$B$406,$B12)) | F12: =IF($B12="","",IF(ISNUMBER($E12),$E12,N($D12))) | I12: =IF($B12="","",N($H12)/60*cfg_LaborRate) | K12: =IF($B12="","",$F12+N($G12)+$I12+N($J12)) | M12: =IF($B12="","",IF(AND(ISNUMBER($L12),$L12<0.95),MAX(0,$L12),cfg_TargetMargin)) | N12: =IF($B12="","",IF(cfg_Round>0,CEILING($K12/(1-$M12),cfg_Round),ROUND($K12/(1-$M12),2))) | P12: =IF(OR($B12="",N($O12)<=0),"",$O12-$K12) | Q12: =IF(OR($B12="",N($O12)<=0),"",$P12/$O12) | R12: =IF(OR($B12="",N($O12)<=0,N($K12)<=0),"",$P12/$K12) | S12: =IF(OR($B12="",N($O12)<=0),"",$F12/$O12) | T12: =IF($B12="","",IF(COUNTIF($B$7:$B$56,$B12)>1,"Duplicate name",IF(N($O12)<=0,"Set a price",IF(N($K12)<=0,"Add costs",IF($P12<0,"LOSS",IF($Q12<$M12-0.00001,"Below target",IF($S12>cfg_FoodCostTarget,"High food cost","Healthy"))))))) | U12: =IF($T12="","",IF($T12="Duplicate name","Each menu item needs a unique name",IF($T12="Set a price","Suggested starting price: "&cfg_Symbol&TEXT($N12,"0.00"),IF($T12="Add costs","Build the recipe or type an ingredient cost override",IF($T12="LOSS","Losing "&cfg_Symbol&TEXT(-$P12,"0.00")&" per sale - raise to "&cfg_Symbol&TEXT($N12,"0.00"),IF($T12="Below target","Raise to "&cfg_Symbol&TEXT($N12,"0.00")&" for a "&TEXT($M12,"0%")&" margin",IF($T12="High food cost","Margin OK; food cost "&TEXT($S12,"0%")&" is above "&TEXT(cfg_FoodCostTarget,"0%")&" target","On target"))))))) | V12: =IF($B12="","",SUMIFS('Sales Log'!$D$7:$D$3006,'Sales Log'!$C$7:$C$3006,$B12,'Sales Log'!$B$7:$B$3006,">="&cfg_Start,'Sales Log'!$B$7:$B$3006,"<="&cfg_End,'Sales Log'!$N$7:$N$3006,"OK")) | W12: =IF($B12="","",SUMIFS('Sales Log'!$I$7:$I$3006,'Sales Log'!$C$7:$C$3006,$B12,'Sales Log'!$B$7:$B$3006,">="&cfg_Start,'Sales Log'!$B$7:$B$3006,"<="&cfg_End,'Sales Log'!$N$7:$N$3006,"OK")) | X12: =IF($B12="","",SUMIFS('Sales Log'!$L$7:$L$3006,'Sales Log'!$C$7:$C$3006,$B12,'Sales Log'!$B$7:$B$3006,">="&cfg_Start,'Sales Log'!$B$7:$B$3006,"<="&cfg_End,'Sales Log'!$N$7:$N$3006,"OK")) | Y12: =IF($B12="","",IF(SUM($V$7:$V$56)=0,0,$V12/SUM($V$7:$V$56))) | Z12: =IF($B12="",-1,N($V12)+ROW()/1000000) | AA12: =IF($B12="",-1E+15,N($X12)+ROW()/1000000)
D13: =IF($B13="","",SUMIFS('Recipe Builder'!$J$7:$J$406,'Recipe Builder'!$B$7:$B$406,$B13)) | F13: =IF($B13="","",IF(ISNUMBER($E13),$E13,N($D13))) | I13: =IF($B13="","",N($H13)/60*cfg_LaborRate) | K13: =IF($B13="","",$F13+N($G13)+$I13+N($J13)) | M13: =IF($B13="","",IF(AND(ISNUMBER($L13),$L13<0.95),MAX(0,$L13),cfg_TargetMargin)) | N13: =IF($B13="","",IF(cfg_Round>0,CEILING($K13/(1-$M13),cfg_Round),ROUND($K13/(1-$M13),2))) | P13: =IF(OR($B13="",N($O13)<=0),"",$O13-$K13) | Q13: =IF(OR($B13="",N($O13)<=0),"",$P13/$O13) | R13: =IF(OR($B13="",N($O13)<=0,N($K13)<=0),"",$P13/$K13) | S13: =IF(OR($B13="",N($O13)<=0),"",$F13/$O13) | T13: =IF($B13="","",IF(COUNTIF($B$7:$B$56,$B13)>1,"Duplicate name",IF(N($O13)<=0,"Set a price",IF(N($K13)<=0,"Add costs",IF($P13<0,"LOSS",IF($Q13<$M13-0.00001,"Below target",IF($S13>cfg_FoodCostTarget,"High food cost","Healthy"))))))) | U13: =IF($T13="","",IF($T13="Duplicate name","Each menu item needs a unique name",IF($T13="Set a price","Suggested starting price: "&cfg_Symbol&TEXT($N13,"0.00"),IF($T13="Add costs","Build the recipe or type an ingredient cost override",IF($T13="LOSS","Losing "&cfg_Symbol&TEXT(-$P13,"0.00")&" per sale - raise to "&cfg_Symbol&TEXT($N13,"0.00"),IF($T13="Below target","Raise to "&cfg_Symbol&TEXT($N13,"0.00")&" for a "&TEXT($M13,"0%")&" margin",IF($T13="High food cost","Margin OK; food cost "&TEXT($S13,"0%")&" is above "&TEXT(cfg_FoodCostTarget,"0%")&" target","On target"))))))) | V13: =IF($B13="","",SUMIFS('Sales Log'!$D$7:$D$3006,'Sales Log'!$C$7:$C$3006,$B13,'Sales Log'!$B$7:$B$3006,">="&cfg_Start,'Sales Log'!$B$7:$B$3006,"<="&cfg_End,'Sales Log'!$N$7:$N$3006,"OK")) | W13: =IF($B13="","",SUMIFS('Sales Log'!$I$7:$I$3006,'Sales Log'!$C$7:$C$3006,$B13,'Sales Log'!$B$7:$B$3006,">="&cfg_Start,'Sales Log'!$B$7:$B$3006,"<="&cfg_End,'Sales Log'!$N$7:$N$3006,"OK")) | X13: =IF($B13="","",SUMIFS('Sales Log'!$L$7:$L$3006,'Sales Log'!$C$7:$C$3006,$B13,'Sales Log'!$B$7:$B$3006,">="&cfg_Start,'Sales Log'!$B$7:$B$3006,"<="&cfg_End,'Sales Log'!$N$7:$N$3006,"OK")) | Y13: =IF($B13="","",IF(SUM($V$7:$V$56)=0,0,$V13/SUM($V$7:$V$56))) | Z13: =IF($B13="",-1,N($V13)+ROW()/1000000) | AA13: =IF($B13="",-1E+15,N($X13)+ROW()/1000000)
D14: =IF($B14="","",SUMIFS('Recipe Builder'!$J$7:$J$406,'Recipe Builder'!$B$7:$B$406,$B14)) | F14: =IF($B14="","",IF(ISNUMBER($E14),$E14,N($D14))) | I14: =IF($B14="","",N($H14)/60*cfg_LaborRate) | K14: =IF($B14="","",$F14+N($G14)+$I14+N($J14)) | M14: =IF($B14="","",IF(AND(ISNUMBER($L14),$L14<0.95),MAX(0,$L14),cfg_TargetMargin)) | N14: =IF($B14="","",IF(cfg_Round>0,CEILING($K14/(1-$M14),cfg_Round),ROUND($K14/(1-$M14),2))) | P14: =IF(OR($B14="",N($O14)<=0),"",$O14-$K14) | Q14: =IF(OR($B14="",N($O14)<=0),"",$P14/$O14) | R14: =IF(OR($B14="",N($O14)<=0,N($K14)<=0),"",$P14/$K14) | S14: =IF(OR($B14="",N($O14)<=0),"",$F14/$O14) | T14: =IF($B14="","",IF(COUNTIF($B$7:$B$56,$B14)>1,"Duplicate name",IF(N($O14)<=0,"Set a price",IF(N($K14)<=0,"Add costs",IF($P14<0,"LOSS",IF($Q14<$M14-0.00001,"Below target",IF($S14>cfg_FoodCostTarget,"High food cost","Healthy"))))))) | U14: =IF($T14="","",IF($T14="Duplicate name","Each menu item needs a unique name",IF($T14="Set a price","Suggested starting price: "&cfg_Symbol&TEXT($N14,"0.00"),IF($T14="Add costs","Build the recipe or type an ingredient cost override",IF($T14="LOSS","Losing "&cfg_Symbol&TEXT(-$P14,"0.00")&" per sale - raise to "&cfg_Symbol&TEXT($N14,"0.00"),IF($T14="Below target","Raise to "&cfg_Symbol&TEXT($N14,"0.00")&" for a "&TEXT($M14,"0%")&" margin",IF($T14="High food cost","Margin OK; food cost "&TEXT($S14,"0%")&" is above "&TEXT(cfg_FoodCostTarget,"0%")&" target","On target"))))))) | V14: =IF($B14="","",SUMIFS('Sales Log'!$D$7:$D$3006,'Sales Log'!$C$7:$C$3006,$B14,'Sales Log'!$B$7:$B$3006,">="&cfg_Start,'Sales Log'!$B$7:$B$3006,"<="&cfg_End,'Sales Log'!$N$7:$N$3006,"OK")) | W14: =IF($B14="","",SUMIFS('Sales Log'!$I$7:$I$3006,'Sales Log'!$C$7:$C$3006,$B14,'Sales Log'!$B$7:$B$3006,">="&cfg_Start,'Sales Log'!$B$7:$B$3006,"<="&cfg_End,'Sales Log'!$N$7:$N$3006,"OK")) | X14: =IF($B14="","",SUMIFS('Sales Log'!$L$7:$L$3006,'Sales Log'!$C$7:$C$3006,$B14,'Sales Log'!$B$7:$B$3006,">="&cfg_Start,'Sales Log'!$B$7:$B$3006,"<="&cfg_End,'Sales Log'!$N$7:$N$3006,"OK")) | Y14: =IF($B14="","",IF(SUM($V$7:$V$56)=0,0,$V14/SUM($V$7:$V$56))) | Z14: =IF($B14="",-1,N($V14)+ROW()/1000000) | AA14: =IF($B14="",-1E+15,N($X14)+ROW()/1000000)
D15: =IF($B15="","",SUMIFS('Recipe Builder'!$J$7:$J$406,'Recipe Builder'!$B$7:$B$406,$B15)) | F15: =IF($B15="","",IF(ISNUMBER($E15),$E15,N($D15))) | I15: =IF($B15="","",N($H15)/60*cfg_LaborRate) | K15: =IF($B15="","",$F15+N($G15)+$I15+N($J15)) | M15: =IF($B15="","",IF(AND(ISNUMBER($L15),$L15<0.95),MAX(0,$L15),cfg_TargetMargin)) | N15: =IF($B15="","",IF(cfg_Round>0,CEILING($K15/(1-$M15),cfg_Round),ROUND($K15/(1-$M15),2))) | P15: =IF(OR($B15="",N($O15)<=0),"",$O15-$K15) | Q15: =IF(OR($B15="",N($O15)<=0),"",$P15/$O15) | R15: =IF(OR($B15="",N($O15)<=0,N($K15)<=0),"",$P15/$K15) | S15: =IF(OR($B15="",N($O15)<=0),"",$F15/$O15) | T15: =IF($B15="","",IF(COUNTIF($B$7:$B$56,$B15)>1,"Duplicate name",IF(N($O15)<=0,"Set a price",IF(N($K15)<=0,"Add costs",IF($P15<0,"LOSS",IF($Q15<$M15-0.00001,"Below target",IF($S15>cfg_FoodCostTarget,"High food cost","Healthy"))))))) | U15: =IF($T15="","",IF($T15="Duplicate name","Each menu item needs a unique name",IF($T15="Set a price","Suggested starting price: "&cfg_Symbol&TEXT($N15,"0.00"),IF($T15="Add costs","Build the recipe or type an ingredient cost override",IF($T15="LOSS","Losing "&cfg_Symbol&TEXT(-$P15,"0.00")&" per sale - raise to "&cfg_Symbol&TEXT($N15,"0.00"),IF($T15="Below target","Raise to "&cfg_Symbol&TEXT($N15,"0.00")&" for a "&TEXT($M15,"0%")&" margin",IF($T15="High food cost","Margin OK; food cost "&TEXT($S15,"0%")&" is above "&TEXT(cfg_FoodCostTarget,"0%")&" target","On target"))))))) | V15: =IF($B15="","",SUMIFS('Sales Log'!$D$7:$D$3006,'Sales Log'!$C$7:$C$3006,$B15,'Sales Log'!$B$7:$B$3006,">="&cfg_Start,'Sales Log'!$B$7:$B$3006,"<="&cfg_End,'Sales Log'!$N$7:$N$3006,"OK")) | W15: =IF($B15="","",SUMIFS('Sales Log'!$I$7:$I$3006,'Sales Log'!$C$7:$C$3006,$B15,'Sales Log'!$B$7:$B$3006,">="&cfg_Start,'Sales Log'!$B$7:$B$3006,"<="&cfg_End,'Sales Log'!$N$7:$N$3006,"OK")) | X15: =IF($B15="","",SUMIFS('Sales Log'!$L$7:$L$3006,'Sales Log'!$C$7:$C$3006,$B15,'Sales Log'!$B$7:$B$3006,">="&cfg_Start,'Sales Log'!$B$7:$B$3006,"<="&cfg_End,'Sales Log'!$N$7:$N$3006,"OK")) | Y15: =IF($B15="","",IF(SUM($V$7:$V$56)=0,0,$V15/SUM($V$7:$V$56))) | Z15: =IF($B15="",-1,N($V15)+ROW()/1000000) | AA15: =IF($B15="",-1E+15,N($X15)+ROW()/1000000)
D16: =IF($B16="","",SUMIFS('Recipe Builder'!$J$7:$J$406,'Recipe Builder'!$B$7:$B$406,$B16)) | F16: =IF($B16="","",IF(ISNUMBER($E16),$E16,N($D16))) | I16: =IF($B16="","",N($H16)/60*cfg_LaborRate) | K16: =IF($B16="","",$F16+N($G16)+$I16+N($J16)) | M16: =IF($B16="","",IF(AND(ISNUMBER($L16),$L16<0.95),MAX(0,$L16),cfg_TargetMargin)) | N16: =IF($B16="","",IF(cfg_Round>0,CEILING($K16/(1-$M16),cfg_Round),ROUND($K16/(1-$M16),2))) | P16: =IF(OR($B16="",N($O16)<=0),"",$O16-$K16) | Q16: =IF(OR($B16="",N($O16)<=0),"",$P16/$O16) | R16: =IF(OR($B16="",N($O16)<=0,N($K16)<=0),"",$P16/$K16) | S16: =IF(OR($B16="",N($O16)<=0),"",$F16/$O16) | T16: =IF($B16="","",IF(COUNTIF($B$7:$B$56,$B16)>1,"Duplicate name",IF(N($O16)<=0,"Set a price",IF(N($K16)<=0,"Add costs",IF($P16<0,"LOSS",IF($Q16<$M16-0.00001,"Below target",IF($S16>cfg_FoodCostTarget,"High food cost","Healthy"))))))) | U16: =IF($T16="","",IF($T16="Duplicate name","Each menu item needs a unique name",IF($T16="Set a price","Suggested starting price: "&cfg_Symbol&TEXT($N16,"0.00"),IF($T16="Add costs","Build the recipe or type an ingredient cost override",IF($T16="LOSS","Losing "&cfg_Symbol&TEXT(-$P16,"0.00")&" per sale - raise to "&cfg_Symbol&TEXT($N16,"0.00"),IF($T16="Below target","Raise to "&cfg_Symbol&TEXT($N16,"0.00")&" for a "&TEXT($M16,"0%")&" margin",IF($T16="High food cost","Margin OK; food cost "&TEXT($S16,"0%")&" is above "&TEXT(cfg_FoodCostTarget,"0%")&" target","On target"))))))) | V16: =IF($B16="","",SUMIFS('Sales Log'!$D$7:$D$3006,'Sales Log'!$C$7:$C$3006,$B16,'Sales Log'!$B$7:$B$3006,">="&cfg_Start,'Sales Log'!$B$7:$B$3006,"<="&cfg_End,'Sales Log'!$N$7:$N$3006,"OK")) | W16: =IF($B16="","",SUMIFS('Sales Log'!$I$7:$I$3006,'Sales Log'!$C$7:$C$3006,$B16,'Sales Log'!$B$7:$B$3006,">="&cfg_Start,'Sales Log'!$B$7:$B$3006,"<="&cfg_End,'Sales Log'!$N$7:$N$3006,"OK")) | X16: =IF($B16="","",SUMIFS('Sales Log'!$L$7:$L$3006,'Sales Log'!$C$7:$C$3006,$B16,'Sales Log'!$B$7:$B$3006,">="&cfg_Start,'Sales Log'!$B$7:$B$3006,"<="&cfg_End,'Sales Log'!$N$7:$N$3006,"OK")) | Y16: =IF($B16="","",IF(SUM($V$7:$V$56)=0,0,$V16/SUM($V$7:$V$56))) | Z16: =IF($B16="",-1,N($V16)+ROW()/1000000) | AA16: =IF($B16="",-1E+15,N($X16)+ROW()/1000000)
D17: =IF($B17="","",SUMIFS('Recipe Builder'!$J$7:$J$406,'Recipe Builder'!$B$7:$B$406,$B17)) | F17: =IF($B17="","",IF(ISNUMBER($E17),$E17,N($D17))) | I17: =IF($B17="","",N($H17)/60*cfg_LaborRate) | K17: =IF($B17="","",$F17+N($G17)+$I17+N($J17)) | M17: =IF($B17="","",IF(AND(ISNUMBER($L17),$L17<0.95),MAX(0,$L17),cfg_TargetMargin)) | N17: =IF($B17="","",IF(cfg_Round>0,CEILING($K17/(1-$M17),cfg_Round),ROUND($K17/(1-$M17),2))) | P17: =IF(OR($B17="",N($O17)<=0),"",$O17-$K17) | Q17: =IF(OR($B17="",N($O17)<=0),"",$P17/$O17) | R17: =IF(OR($B17="",N($O17)<=0,N($K17)<=0),"",$P17/$K17) | S17: =IF(OR($B17="",N($O17)<=0),"",$F17/$O17) | T17: =IF($B17="","",IF(COUNTIF($B$7:$B$56,$B17)>1,"Duplicate name",IF(N($O17)<=0,"Set a price",IF(N($K17)<=0,"Add costs",IF($P17<0,"LOSS",IF($Q17<$M17-0.00001,"Below target",IF($S17>cfg_FoodCostTarget,"High food cost","Healthy"))))))) | U17: =IF($T17="","",IF($T17="Duplicate name","Each menu item needs a unique name",IF($T17="Set a price","Suggested starting price: "&cfg_Symbol&TEXT($N17,"0.00"),IF($T17="Add costs","Build the recipe or type an ingredient cost override",IF($T17="LOSS","Losing "&cfg_Symbol&TEXT(-$P17,"0.00")&" per sale - raise to "&cfg_Symbol&TEXT($N17,"0.00"),IF($T17="Below target","Raise to "&cfg_Symbol&TEXT($N17,"0.00")&" for a "&TEXT($M17,"0%")&" margin",IF($T17="High food cost","Margin OK; food cost "&TEXT($S17,"0%")&" is above "&TEXT(cfg_FoodCostTarget,"0%")&" target","On target"))))))) | V17: =IF($B17="","",SUMIFS('Sales Log'!$D$7:$D$3006,'Sales Log'!$C$7:$C$3006,$B17,'Sales Log'!$B$7:$B$3006,">="&cfg_Start,'Sales Log'!$B$7:$B$3006,"<="&cfg_End,'Sales Log'!$N$7:$N$3006,"OK")) | W17: =IF($B17="","",SUMIFS('Sales Log'!$I$7:$I$3006,'Sales Log'!$C$7:$C$3006,$B17,'Sales Log'!$B$7:$B$3006,">="&cfg_Start,'Sales Log'!$B$7:$B$3006,"<="&cfg_End,'Sales Log'!$N$7:$N$3006,"OK")) | X17: =IF($B17="","",SUMIFS('Sales Log'!$L$7:$L$3006,'Sales Log'!$C$7:$C$3006,$B17,'Sales Log'!$B$7:$B$3006,">="&cfg_Start,'Sales Log'!$B$7:$B$3006,"<="&cfg_End,'Sales Log'!$N$7:$N$3006,"OK")) | Y17: =IF($B17="","",IF(SUM($V$7:$V$56)=0,0,$V17/SUM($V$7:$V$56))) | Z17: =IF($B17="",-1,N($V17)+ROW()/1000000) | AA17: =IF($B17="",-1E+15,N($X17)+ROW()/1000000)
D18: =IF($B18="","",SUMIFS('Recipe Builder'!$J$7:$J$406,'Recipe Builder'!$B$7:$B$406,$B18)) | F18: =IF($B18="","",IF(ISNUMBER($E18),$E18,N($D18))) | I18: =IF($B18="","",N($H18)/60*cfg_LaborRate) | K18: =IF($B18="","",$F18+N($G18)+$I18+N($J18)) | M18: =IF($B18="","",IF(AND(ISNUMBER($L18),$L18<0.95),MAX(0,$L18),cfg_TargetMargin)) | N18: =IF($B18="","",IF(cfg_Round>0,CEILING($K18/(1-$M18),cfg_Round),ROUND($K18/(1-$M18),2))) | P18: =IF(OR($B18="",N($O18)<=0),"",$O18-$K18) | Q18: =IF(OR($B18="",N($O18)<=0),"",$P18/$O18) | R18: =IF(OR($B18="",N($O18)<=0,N($K18)<=0),"",$P18/$K18) | S18: =IF(OR($B18="",N($O18)<=0),"",$F18/$O18) | T18: =IF($B18="","",IF(COUNTIF($B$7:$B$56,$B18)>1,"Duplicate name",IF(N($O18)<=0,"Set a price",IF(N($K18)<=0,"Add costs",IF($P18<0,"LOSS",IF($Q18<$M18-0.00001,"Below target",IF($S18>cfg_FoodCostTarget,"High food cost","Healthy"))))))) | U18: =IF($T18="","",IF($T18="Duplicate name","Each menu item needs a unique name",IF($T18="Set a price","Suggested starting price: "&cfg_Symbol&TEXT($N18,"0.00"),IF($T18="Add costs","Build the recipe or type an ingredient cost override",IF($T18="LOSS","Losing "&cfg_Symbol&TEXT(-$P18,"0.00")&" per sale - raise to "&cfg_Symbol&TEXT($N18,"0.00"),IF($T18="Below target","Raise to "&cfg_Symbol&TEXT($N18,"0.00")&" for a "&TEXT($M18,"0%")&" margin",IF($T18="High food cost","Margin OK; food cost "&TEXT($S18,"0%")&" is above "&TEXT(cfg_FoodCostTarget,"0%")&" target","On target"))))))) | V18: =IF($B18="","",SUMIFS('Sales Log'!$D$7:$D$3006,'Sales Log'!$C$7:$C$3006,$B18,'Sales Log'!$B$7:$B$3006,">="&cfg_Start,'Sales Log'!$B$7:$B$3006,"<="&cfg_End,'Sales Log'!$N$7:$N$3006,"OK")) | W18: =IF($B18="","",SUMIFS('Sales Log'!$I$7:$I$3006,'Sales Log'!$C$7:$C$3006,$B18,'Sales Log'!$B$7:$B$3006,">="&cfg_Start,'Sales Log'!$B$7:$B$3006,"<="&cfg_End,'Sales Log'!$N$7:$N$3006,"OK")) | X18: =IF($B18="","",SUMIFS('Sales Log'!$L$7:$L$3006,'Sales Log'!$C$7:$C$3006,$B18,'Sales Log'!$B$7:$B$3006,">="&cfg_Start,'Sales Log'!$B$7:$B$3006,"<="&cfg_End,'Sales Log'!$N$7:$N$3006,"OK")) | Y18: =IF($B18="","",IF(SUM($V$7:$V$56)=0,0,$V18/SUM($V$7:$V$56))) | Z18: =IF($B18="",-1,N($V18)+ROW()/1000000) | AA18: =IF($B18="",-1E+15,N($X18)+ROW()/1000000)
... D56: =IF($B56="","",SUMIFS('Recipe Builder'!$J$7:$J$406,'Recipe Builder'!$B$7:$B$406,$B56)) | F56: =IF($B56="","",IF(ISNUMBER($E56),$E56,N($D56))) | I56: =IF($B56="","",N($H56)/60*cfg_LaborRate) | K56: =IF($B56="","",$F56+N($G56)+$I56+N($J56)) | M56: =IF($B56="","",IF(AND(ISNUMBER($L56),$L56<0.95),MAX(0,$L56),cfg_TargetMargin)) | N56: =IF($B56="","",IF(cfg_Round>0,CEILING($K56/(1-$M56),cfg_Round),ROUND($K56/(1-$M56),2))) | P56: =IF(OR($B56="",N($O56)<=0),"",$O56-$K56) | Q56: =IF(OR($B56="",N($O56)<=0),"",$P56/$O56) | R56: =IF(OR($B56="",N($O56)<=0,N($K56)<=0),"",$P56/$K56) | S56: =IF(OR($B56="",N($O56)<=0),"",$F56/$O56) | T56: =IF($B56="","",IF(COUNTIF($B$7:$B$56,$B56)>1,"Duplicate name",IF(N($O56)<=0,"Set a price",IF(N($K56)<=0,"Add costs",IF($P56<0,"LOSS",IF($Q56<$M56-0.00001,"Below target",IF($S56>cfg_FoodCostTarget,"High food cost","Healthy"))))))) | U56: =IF($T56="","",IF($T56="Duplicate name","Each menu item needs a unique name",IF($T56="Set a price","Suggested starting price: "&cfg_Symbol&TEXT($N56,"0.00"),IF($T56="Add costs","Build the recipe or type an ingredient cost override",IF($T56="LOSS","Losing "&cfg_Symbol&TEXT(-$P56,"0.00")&" per sale - raise to "&cfg_Symbol&TEXT($N56,"0.00"),IF($T56="Below target","Raise to "&cfg_Symbol&TEXT($N56,"0.00")&" for a "&TEXT($M56,"0%")&" margin",IF($T56="High food cost","Margin OK; food cost "&TEXT($S56,"0%")&" is above "&TEXT(cfg_FoodCostTarget,"0%")&" target","On target"))))))) | V56: =IF($B56="","",SUMIFS('Sales Log'!$D$7:$D$3006,'Sales Log'!$C$7:$C$3006,$B56,'Sales Log'!$B$7:$B$3006,">="&cfg_Start,'Sales Log'!$B$7:$B$3006,"<="&cfg_End,'Sales Log'!$N$7:$N$3006,"OK")) | W56: =IF($B56="","",SUMIFS('Sales Log'!$I$7:$I$3006,'Sales Log'!$C$7:$C$3006,$B56,'Sales Log'!$B$7:$B$3006,">="&cfg_Start,'Sales Log'!$B$7:$B$3006,"<="&cfg_End,'Sales Log'!$N$7:$N$3006,"OK")) | X56: =IF($B56="","",SUMIFS('Sales Log'!$L$7:$L$3006,'Sales Log'!$C$7:$C$3006,$B56,'Sales Log'!$B$7:$B$3006,">="&cfg_Start,'Sales Log'!$B$7:$B$3006,"<="&cfg_End,'Sales Log'!$N$7:$N$3006,"OK")) | Y56: =IF($B56="","",IF(SUM($V$7:$V$56)=0,0,$V56/SUM($V$7:$V$56))) | Z56: =IF($B56="",-1,N($V56)+ROW()/1000000) | AA56: =IF($B56="",-1E+15,N($X56)+ROW()/1000000)
B57: TOTAL / ALERTS | T57: =COUNTIF(T7:T56,"LOSS")+COUNTIF(T7:T56,"Below target")&" need attention" | V57: =SUM(V7:V56) | W57: =SUM(W7:W56) | X57: =SUM(X7:X56)
B59: MARGIN = profit / price. MARKUP = profit / cost. Example: cost 4.00, price 10.00 -> margin 60%, markup 150%. Suggested price = total cost / (1 - target margin), rounded UP. Prep labour here is a pricing allowance only - real wages are recorded in Expenses. Gross profit in the sales columns uses ingredients + packaging + other variable cost (no labour), so labour is never counted twice.

Sheet Recipe Builder
B2: Recipe Builder | L2: NoviraNest
B3: One row per ingredient per menu item. Quantities convert automatically to each ingredient's stock unit. Incompatible units are flagged and never costed.
B4: › Start Here | C4: › Dashboard | D4: › Menu Pricing | F4: › Inventory
B5: WHAT GOES INTO ONE SERVING | F5: AUTOMATIC COSTING & USAGE
B6: Menu item | C6: Ingredient | D6: Qty per serving | E6: Unit | F6: Stock unit | G6: Unit check | H6: Qty in stock units | I6: ="Cost per stock unit ("&cfg_Symbol&")" | J6: ="Line cost ("&cfg_Symbol&")" | K6: Items sold since count | L6: Usage since count
F7: =IF($C7="","",IFERROR(INDEX('Inventory'!$D$7:$D$106,MATCH($C7,'Inventory'!$B$7:$B$106,0))&"","?")) | G7: =IF(AND($B7="",$C7=""),"",IF($B7="","Pick menu item",IF(ISNA(MATCH($B7,'Menu Pricing'!$B$7:$B$56,0)),"Not on Menu Pricing",IF($C7="","Pick ingredient",IF($F7="?","Not in Inventory",IF($F7="","Set stock unit in Inventory",IF(N($D7)<=0,"Enter quantity",IF($E7="","Pick unit",IF(IFERROR(INDEX('Lists'!$C$6:$C$30,MATCH($E7,'Lists'!$B$6:$B$30,0)),"?")<>IFERROR(INDEX('Lists'!$C$6:$C$30,MATCH($F7,'Lists'!$B$6:$B$30,0)),"?"),"Unit mismatch",IF(ISNUMBER(INDEX('Inventory'!$G$7:$G$106,MATCH($C7,'Inventory'!$B$7:$B$106,0))),"OK","Add price in Inventory")))))))))) | H7: =IF($G7<>"OK","",$D7*INDEX('Lists'!$D$6:$D$30,MATCH($E7,'Lists'!$B$6:$B$30,0))/INDEX('Lists'!$D$6:$D$30,MATCH($F7,'Lists'!$B$6:$B$30,0))) | I7: =IF($G7<>"OK","",INDEX('Inventory'!$G$7:$G$106,MATCH($C7,'Inventory'!$B$7:$B$106,0))) | J7: =IF($G7<>"OK","",$H7*$I7) | K7: =IF($G7<>"OK","",SUMIFS('Sales Log'!$D$7:$D$3006,'Sales Log'!$C$7:$C$3006,$B7,'Sales Log'!$B$7:$B$3006,">="&cfg_CountDate,'Sales Log'!$N$7:$N$3006,"OK")) | L7: =IF($G7<>"OK","",$H7*$K7)
F8: =IF($C8="","",IFERROR(INDEX('Inventory'!$D$7:$D$106,MATCH($C8,'Inventory'!$B$7:$B$106,0))&"","?")) | G8: =IF(AND($B8="",$C8=""),"",IF($B8="","Pick menu item",IF(ISNA(MATCH($B8,'Menu Pricing'!$B$7:$B$56,0)),"Not on Menu Pricing",IF($C8="","Pick ingredient",IF($F8="?","Not in Inventory",IF($F8="","Set stock unit in Inventory",IF(N($D8)<=0,"Enter quantity",IF($E8="","Pick unit",IF(IFERROR(INDEX('Lists'!$C$6:$C$30,MATCH($E8,'Lists'!$B$6:$B$30,0)),"?")<>IFERROR(INDEX('Lists'!$C$6:$C$30,MATCH($F8,'Lists'!$B$6:$B$30,0)),"?"),"Unit mismatch",IF(ISNUMBER(INDEX('Inventory'!$G$7:$G$106,MATCH($C8,'Inventory'!$B$7:$B$106,0))),"OK","Add price in Inventory")))))))))) | H8: =IF($G8<>"OK","",$D8*INDEX('Lists'!$D$6:$D$30,MATCH($E8,'Lists'!$B$6:$B$30,0))/INDEX('Lists'!$D$6:$D$30,MATCH($F8,'Lists'!$B$6:$B$30,0))) | I8: =IF($G8<>"OK","",INDEX('Inventory'!$G$7:$G$106,MATCH($C8,'Inventory'!$B$7:$B$106,0))) | J8: =IF($G8<>"OK","",$H8*$I8) | K8: =IF($G8<>"OK","",SUMIFS('Sales Log'!$D$7:$D$3006,'Sales Log'!$C$7:$C$3006,$B8,'Sales Log'!$B$7:$B$3006,">="&cfg_CountDate,'Sales Log'!$N$7:$N$3006,"OK")) | L8: =IF($G8<>"OK","",$H8*$K8)
F9: =IF($C9="","",IFERROR(INDEX('Inventory'!$D$7:$D$106,MATCH($C9,'Inventory'!$B$7:$B$106,0))&"","?")) | G9: =IF(AND($B9="",$C9=""),"",IF($B9="","Pick menu item",IF(ISNA(MATCH($B9,'Menu Pricing'!$B$7:$B$56,0)),"Not on Menu Pricing",IF($C9="","Pick ingredient",IF($F9="?","Not in Inventory",IF($F9="","Set stock unit in Inventory",IF(N($D9)<=0,"Enter quantity",IF($E9="","Pick unit",IF(IFERROR(INDEX('Lists'!$C$6:$C$30,MATCH($E9,'Lists'!$B$6:$B$30,0)),"?")<>IFERROR(INDEX('Lists'!$C$6:$C$30,MATCH($F9,'Lists'!$B$6:$B$30,0)),"?"),"Unit mismatch",IF(ISNUMBER(INDEX('Inventory'!$G$7:$G$106,MATCH($C9,'Inventory'!$B$7:$B$106,0))),"OK","Add price in Inventory")))))))))) | H9: =IF($G9<>"OK","",$D9*INDEX('Lists'!$D$6:$D$30,MATCH($E9,'Lists'!$B$6:$B$30,0))/INDEX('Lists'!$D$6:$D$30,MATCH($F9,'Lists'!$B$6:$B$30,0))) | I9: =IF($G9<>"OK","",INDEX('Inventory'!$G$7:$G$106,MATCH($C9,'Inventory'!$B$7:$B$106,0))) | J9: =IF($G9<>"OK","",$H9*$I9) | K9: =IF($G9<>"OK","",SUMIFS('Sales Log'!$D$7:$D$3006,'Sales Log'!$C$7:$C$3006,$B9,'Sales Log'!$B$7:$B$3006,">="&cfg_CountDate,'Sales Log'!$N$7:$N$3006,"OK")) | L9: =IF($G9<>"OK","",$H9*$K9)
F10: =IF($C10="","",IFERROR(INDEX('Inventory'!$D$7:$D$106,MATCH($C10,'Inventory'!$B$7:$B$106,0))&"","?")) | G10: =IF(AND($B10="",$C10=""),"",IF($B10="","Pick menu item",IF(ISNA(MATCH($B10,'Menu Pricing'!$B$7:$B$56,0)),"Not on Menu Pricing",IF($C10="","Pick ingredient",IF($F10="?","Not in Inventory",IF($F10="","Set stock unit in Inventory",IF(N($D10)<=0,"Enter quantity",IF($E10="","Pick unit",IF(IFERROR(INDEX('Lists'!$C$6:$C$30,MATCH($E10,'Lists'!$B$6:$B$30,0)),"?")<>IFERROR(INDEX('Lists'!$C$6:$C$30,MATCH($F10,'Lists'!$B$6:$B$30,0)),"?"),"Unit mismatch",IF(ISNUMBER(INDEX('Inventory'!$G$7:$G$106,MATCH($C10,'Inventory'!$B$7:$B$106,0))),"OK","Add price in Inventory")))))))))) | H10: =IF($G10<>"OK","",$D10*INDEX('Lists'!$D$6:$D$30,MATCH($E10,'Lists'!$B$6:$B$30,0))/INDEX('Lists'!$D$6:$D$30,MATCH($F10,'Lists'!$B$6:$B$30,0))) | I10: =IF($G10<>"OK","",INDEX('Inventory'!$G$7:$G$106,MATCH($C10,'Inventory'!$B$7:$B$106,0))) | J10: =IF($G10<>"OK","",$H10*$I10) | K10: =IF($G10<>"OK","",SUMIFS('Sales Log'!$D$7:$D$3006,'Sales Log'!$C$7:$C$3006,$B10,'Sales Log'!$B$7:$B$3006,">="&cfg_CountDate,'Sales Log'!$N$7:$N$3006,"OK")) | L10: =IF($G10<>"OK","",$H10*$K10)
F11: =IF($C11="","",IFERROR(INDEX('Inventory'!$D$7:$D$106,MATCH($C11,'Inventory'!$B$7:$B$106,0))&"","?")) | G11: =IF(AND($B11="",$C11=""),"",IF($B11="","Pick menu item",IF(ISNA(MATCH($B11,'Menu Pricing'!$B$7:$B$56,0)),"Not on Menu Pricing",IF($C11="","Pick ingredient",IF($F11="?","Not in Inventory",IF($F11="","Set stock unit in Inventory",IF(N($D11)<=0,"Enter quantity",IF($E11="","Pick unit",IF(IFERROR(INDEX('Lists'!$C$6:$C$30,MATCH($E11,'Lists'!$B$6:$B$30,0)),"?")<>IFERROR(INDEX('Lists'!$C$6:$C$30,MATCH($F11,'Lists'!$B$6:$B$30,0)),"?"),"Unit mismatch",IF(ISNUMBER(INDEX('Inventory'!$G$7:$G$106,MATCH($C11,'Inventory'!$B$7:$B$106,0))),"OK","Add price in Inventory")))))))))) | H11: =IF($G11<>"OK","",$D11*INDEX('Lists'!$D$6:$D$30,MATCH($E11,'Lists'!$B$6:$B$30,0))/INDEX('Lists'!$D$6:$D$30,MATCH($F11,'Lists'!$B$6:$B$30,0))) | I11: =IF($G11<>"OK","",INDEX('Inventory'!$G$7:$G$106,MATCH($C11,'Inventory'!$B$7:$B$106,0))) | J11: =IF($G11<>"OK","",$H11*$I11) | K11: =IF($G11<>"OK","",SUMIFS('Sales Log'!$D$7:$D$3006,'Sales Log'!$C$7:$C$3006,$B11,'Sales Log'!$B$7:$B$3006,">="&cfg_CountDate,'Sales Log'!$N$7:$N$3006,"OK")) | L11: =IF($G11<>"OK","",$H11*$K11)
F12: =IF($C12="","",IFERROR(INDEX('Inventory'!$D$7:$D$106,MATCH($C12,'Inventory'!$B$7:$B$106,0))&"","?")) | G12: =IF(AND($B12="",$C12=""),"",IF($B12="","Pick menu item",IF(ISNA(MATCH($B12,'Menu Pricing'!$B$7:$B$56,0)),"Not on Menu Pricing",IF($C12="","Pick ingredient",IF($F12="?","Not in Inventory",IF($F12="","Set stock unit in Inventory",IF(N($D12)<=0,"Enter quantity",IF($E12="","Pick unit",IF(IFERROR(INDEX('Lists'!$C$6:$C$30,MATCH($E12,'Lists'!$B$6:$B$30,0)),"?")<>IFERROR(INDEX('Lists'!$C$6:$C$30,MATCH($F12,'Lists'!$B$6:$B$30,0)),"?"),"Unit mismatch",IF(ISNUMBER(INDEX('Inventory'!$G$7:$G$106,MATCH($C12,'Inventory'!$B$7:$B$106,0))),"OK","Add price in Inventory")))))))))) | H12: =IF($G12<>"OK","",$D12*INDEX('Lists'!$D$6:$D$30,MATCH($E12,'Lists'!$B$6:$B$30,0))/INDEX('Lists'!$D$6:$D$30,MATCH($F12,'Lists'!$B$6:$B$30,0))) | I12: =IF($G12<>"OK","",INDEX('Inventory'!$G$7:$G$106,MATCH($C12,'Inventory'!$B$7:$B$106,0))) | J12: =IF($G12<>"OK","",$H12*$I12) | K12: =IF($G12<>"OK","",SUMIFS('Sales Log'!$D$7:$D$3006,'Sales Log'!$C$7:$C$3006,$B12,'Sales Log'!$B$7:$B$3006,">="&cfg_CountDate,'Sales Log'!$N$7:$N$3006,"OK")) | L12: =IF($G12<>"OK","",$H12*$K12)
F13: =IF($C13="","",IFERROR(INDEX('Inventory'!$D$7:$D$106,MATCH($C13,'Inventory'!$B$7:$B$106,0))&"","?")) | G13: =IF(AND($B13="",$C13=""),"",IF($B13="","Pick menu item",IF(ISNA(MATCH($B13,'Menu Pricing'!$B$7:$B$56,0)),"Not on Menu Pricing",IF($C13="","Pick ingredient",IF($F13="?","Not in Inventory",IF($F13="","Set stock unit in Inventory",IF(N($D13)<=0,"Enter quantity",IF($E13="","Pick unit",IF(IFERROR(INDEX('Lists'!$C$6:$C$30,MATCH($E13,'Lists'!$B$6:$B$30,0)),"?")<>IFERROR(INDEX('Lists'!$C$6:$C$30,MATCH($F13,'Lists'!$B$6:$B$30,0)),"?"),"Unit mismatch",IF(ISNUMBER(INDEX('Inventory'!$G$7:$G$106,MATCH($C13,'Inventory'!$B$7:$B$106,0))),"OK","Add price in Inventory")))))))))) | H13: =IF($G13<>"OK","",$D13*INDEX('Lists'!$D$6:$D$30,MATCH($E13,'Lists'!$B$6:$B$30,0))/INDEX('Lists'!$D$6:$D$30,MATCH($F13,'Lists'!$B$6:$B$30,0))) | I13: =IF($G13<>"OK","",INDEX('Inventory'!$G$7:$G$106,MATCH($C13,'Inventory'!$B$7:$B$106,0))) | J13: =IF($G13<>"OK","",$H13*$I13) | K13: =IF($G13<>"OK","",SUMIFS('Sales Log'!$D$7:$D$3006,'Sales Log'!$C$7:$C$3006,$B13,'Sales Log'!$B$7:$B$3006,">="&cfg_CountDate,'Sales Log'!$N$7:$N$3006,"OK")) | L13: =IF($G13<>"OK","",$H13*$K13)
F14: =IF($C14="","",IFERROR(INDEX('Inventory'!$D$7:$D$106,MATCH($C14,'Inventory'!$B$7:$B$106,0))&"","?")) | G14: =IF(AND($B14="",$C14=""),"",IF($B14="","Pick menu item",IF(ISNA(MATCH($B14,'Menu Pricing'!$B$7:$B$56,0)),"Not on Menu Pricing",IF($C14="","Pick ingredient",IF($F14="?","Not in Inventory",IF($F14="","Set stock unit in Inventory",IF(N($D14)<=0,"Enter quantity",IF($E14="","Pick unit",IF(IFERROR(INDEX('Lists'!$C$6:$C$30,MATCH($E14,'Lists'!$B$6:$B$30,0)),"?")<>IFERROR(INDEX('Lists'!$C$6:$C$30,MATCH($F14,'Lists'!$B$6:$B$30,0)),"?"),"Unit mismatch",IF(ISNUMBER(INDEX('Inventory'!$G$7:$G$106,MATCH($C14,'Inventory'!$B$7:$B$106,0))),"OK","Add price in Inventory")))))))))) | H14: =IF($G14<>"OK","",$D14*INDEX('Lists'!$D$6:$D$30,MATCH($E14,'Lists'!$B$6:$B$30,0))/INDEX('Lists'!$D$6:$D$30,MATCH($F14,'Lists'!$B$6:$B$30,0))) | I14: =IF($G14<>"OK","",INDEX('Inventory'!$G$7:$G$106,MATCH($C14,'Inventory'!$B$7:$B$106,0))) | J14: =IF($G14<>"OK","",$H14*$I14) | K14: =IF($G14<>"OK","",SUMIFS('Sales Log'!$D$7:$D$3006,'Sales Log'!$C$7:$C$3006,$B14,'Sales Log'!$B$7:$B$3006,">="&cfg_CountDate,'Sales Log'!$N$7:$N$3006,"OK")) | L14: =IF($G14<>"OK","",$H14*$K14)
F15: =IF($C15="","",IFERROR(INDEX('Inventory'!$D$7:$D$106,MATCH($C15,'Inventory'!$B$7:$B$106,0))&"","?")) | G15: =IF(AND($B15="",$C15=""),"",IF($B15="","Pick menu item",IF(ISNA(MATCH($B15,'Menu Pricing'!$B$7:$B$56,0)),"Not on Menu Pricing",IF($C15="","Pick ingredient",IF($F15="?","Not in Inventory",IF($F15="","Set stock unit in Inventory",IF(N($D15)<=0,"Enter quantity",IF($E15="","Pick unit",IF(IFERROR(INDEX('Lists'!$C$6:$C$30,MATCH($E15,'Lists'!$B$6:$B$30,0)),"?")<>IFERROR(INDEX('Lists'!$C$6:$C$30,MATCH($F15,'Lists'!$B$6:$B$30,0)),"?"),"Unit mismatch",IF(ISNUMBER(INDEX('Inventory'!$G$7:$G$106,MATCH($C15,'Inventory'!$B$7:$B$106,0))),"OK","Add price in Inventory")))))))))) | H15: =IF($G15<>"OK","",$D15*INDEX('Lists'!$D$6:$D$30,MATCH($E15,'Lists'!$B$6:$B$30,0))/INDEX('Lists'!$D$6:$D$30,MATCH($F15,'Lists'!$B$6:$B$30,0))) | I15: =IF($G15<>"OK","",INDEX('Inventory'!$G$7:$G$106,MATCH($C15,'Inventory'!$B$7:$B$106,0))) | J15: =IF($G15<>"OK","",$H15*$I15) | K15: =IF($G15<>"OK","",SUMIFS('Sales Log'!$D$7:$D$3006,'Sales Log'!$C$7:$C$3006,$B15,'Sales Log'!$B$7:$B$3006,">="&cfg_CountDate,'Sales Log'!$N$7:$N$3006,"OK")) | L15: =IF($G15<>"OK","",$H15*$K15)
F16: =IF($C16="","",IFERROR(INDEX('Inventory'!$D$7:$D$106,MATCH($C16,'Inventory'!$B$7:$B$106,0))&"","?")) | G16: =IF(AND($B16="",$C16=""),"",IF($B16="","Pick menu item",IF(ISNA(MATCH($B16,'Menu Pricing'!$B$7:$B$56,0)),"Not on Menu Pricing",IF($C16="","Pick ingredient",IF($F16="?","Not in Inventory",IF($F16="","Set stock unit in Inventory",IF(N($D16)<=0,"Enter quantity",IF($E16="","Pick unit",IF(IFERROR(INDEX('Lists'!$C$6:$C$30,MATCH($E16,'Lists'!$B$6:$B$30,0)),"?")<>IFERROR(INDEX('Lists'!$C$6:$C$30,MATCH($F16,'Lists'!$B$6:$B$30,0)),"?"),"Unit mismatch",IF(ISNUMBER(INDEX('Inventory'!$G$7:$G$106,MATCH($C16,'Inventory'!$B$7:$B$106,0))),"OK","Add price in Inventory")))))))))) | H16: =IF($G16<>"OK","",$D16*INDEX('Lists'!$D$6:$D$30,MATCH($E16,'Lists'!$B$6:$B$30,0))/INDEX('Lists'!$D$6:$D$30,MATCH($F16,'Lists'!$B$6:$B$30,0))) | I16: =IF($G16<>"OK","",INDEX('Inventory'!$G$7:$G$106,MATCH($C16,'Inventory'!$B$7:$B$106,0))) | J16: =IF($G16<>"OK","",$H16*$I16) | K16: =IF($G16<>"OK","",SUMIFS('Sales Log'!$D$7:$D$3006,'Sales Log'!$C$7:$C$3006,$B16,'Sales Log'!$B$7:$B$3006,">="&cfg_CountDate,'Sales Log'!$N$7:$N$3006,"OK")) | L16: =IF($G16<>"OK","",$H16*$K16)
F17: =IF($C17="","",IFERROR(INDEX('Inventory'!$D$7:$D$106,MATCH($C17,'Inventory'!$B$7:$B$106,0))&"","?")) | G17: =IF(AND($B17="",$C17=""),"",IF($B17="","Pick menu item",IF(ISNA(MATCH($B17,'Menu Pricing'!$B$7:$B$56,0)),"Not on Menu Pricing",IF($C17="","Pick ingredient",IF($F17="?","Not in Inventory",IF($F17="","Set stock unit in Inventory",IF(N($D17)<=0,"Enter quantity",IF($E17="","Pick unit",IF(IFERROR(INDEX('Lists'!$C$6:$C$30,MATCH($E17,'Lists'!$B$6:$B$30,0)),"?")<>IFERROR(INDEX('Lists'!$C$6:$C$30,MATCH($F17,'Lists'!$B$6:$B$30,0)),"?"),"Unit mismatch",IF(ISNUMBER(INDEX('Inventory'!$G$7:$G$106,MATCH($C17,'Inventory'!$B$7:$B$106,0))),"OK","Add price in Inventory")))))))))) | H17: =IF($G17<>"OK","",$D17*INDEX('Lists'!$D$6:$D$30,MATCH($E17,'Lists'!$B$6:$B$30,0))/INDEX('Lists'!$D$6:$D$30,MATCH($F17,'Lists'!$B$6:$B$30,0))) | I17: =IF($G17<>"OK","",INDEX('Inventory'!$G$7:$G$106,MATCH($C17,'Inventory'!$B$7:$B$106,0))) | J17: =IF($G17<>"OK","",$H17*$I17) | K17: =IF($G17<>"OK","",SUMIFS('Sales Log'!$D$7:$D$3006,'Sales Log'!$C$7:$C$3006,$B17,'Sales Log'!$B$7:$B$3006,">="&cfg_CountDate,'Sales Log'!$N$7:$N$3006,"OK")) | L17: =IF($G17<>"OK","",$H17*$K17)
F18: =IF($C18="","",IFERROR(INDEX('Inventory'!$D$7:$D$106,MATCH($C18,'Inventory'!$B$7:$B$106,0))&"","?")) | G18: =IF(AND($B18="",$C18=""),"",IF($B18="","Pick menu item",IF(ISNA(MATCH($B18,'Menu Pricing'!$B$7:$B$56,0)),"Not on Menu Pricing",IF($C18="","Pick ingredient",IF($F18="?","Not in Inventory",IF($F18="","Set stock unit in Inventory",IF(N($D18)<=0,"Enter quantity",IF($E18="","Pick unit",IF(IFERROR(INDEX('Lists'!$C$6:$C$30,MATCH($E18,'Lists'!$B$6:$B$30,0)),"?")<>IFERROR(INDEX('Lists'!$C$6:$C$30,MATCH($F18,'Lists'!$B$6:$B$30,0)),"?"),"Unit mismatch",IF(ISNUMBER(INDEX('Inventory'!$G$7:$G$106,MATCH($C18,'Inventory'!$B$7:$B$106,0))),"OK","Add price in Inventory")))))))))) | H18: =IF($G18<>"OK","",$D18*INDEX('Lists'!$D$6:$D$30,MATCH($E18,'Lists'!$B$6:$B$30,0))/INDEX('Lists'!$D$6:$D$30,MATCH($F18,'Lists'!$B$6:$B$30,0))) | I18: =IF($G18<>"OK","",INDEX('Inventory'!$G$7:$G$106,MATCH($C18,'Inventory'!$B$7:$B$106,0))) | J18: =IF($G18<>"OK","",$H18*$I18) | K18: =IF($G18<>"OK","",SUMIFS('Sales Log'!$D$7:$D$3006,'Sales Log'!$C$7:$C$3006,$B18,'Sales Log'!$B$7:$B$3006,">="&cfg_CountDate,'Sales Log'!$N$7:$N$3006,"OK")) | L18: =IF($G18<>"OK","",$H18*$K18)
... F406: =IF($C406="","",IFERROR(INDEX('Inventory'!$D$7:$D$106,MATCH($C406,'Inventory'!$B$7:$B$106,0))&"","?")) | G406: =IF(AND($B406="",$C406=""),"",IF($B406="","Pick menu item",IF(ISNA(MATCH($B406,'Menu Pricing'!$B$7:$B$56,0)),"Not on Menu Pricing",IF($C406="","Pick ingredient",IF($F406="?","Not in Inventory",IF($F406="","Set stock unit in Inventory",IF(N($D406)<=0,"Enter quantity",IF($E406="","Pick unit",IF(IFERROR(INDEX('Lists'!$C$6:$C$30,MATCH($E406,'Lists'!$B$6:$B$30,0)),"?")<>IFERROR(INDEX('Lists'!$C$6:$C$30,MATCH($F406,'Lists'!$B$6:$B$30,0)),"?"),"Unit mismatch",IF(ISNUMBER(INDEX('Inventory'!$G$7:$G$106,MATCH($C406,'Inventory'!$B$7:$B$106,0))),"OK","Add price in Inventory")))))))))) | H406: =IF($G406<>"OK","",$D406*INDEX('Lists'!$D$6:$D$30,MATCH($E406,'Lists'!$B$6:$B$30,0))/INDEX('Lists'!$D$6:$D$30,MATCH($F406,'Lists'!$B$6:$B$30,0))) | I406: =IF($G406<>"OK","",INDEX('Inventory'!$G$7:$G$106,MATCH($C406,'Inventory'!$B$7:$B$106,0))) | J406: =IF($G406<>"OK","",$H406*$I406) | K406: =IF($G406<>"OK","",SUMIFS('Sales Log'!$D$7:$D$3006,'Sales Log'!$C$7:$C$3006,$B406,'Sales Log'!$B$7:$B$3006,">="&cfg_CountDate,'Sales Log'!$N$7:$N$3006,"OK")) | L406: =IF($G406<>"OK","",$H406*$K406)

Sheet Inventory
B2: Inventory | Q2: NoviraNest
B3: Ingredient prices, estimated stock on hand and reorder alerts. Stock falls automatically as items sell (via Recipe Builder) and as waste is logged.
B4: › Start Here | C4: › Dashboard | D4: › Recipe Builder | F4: › Waste Log
B5: INGREDIENT & PRICE | H5: STOCK SINCE LAST COUNT (in stock units) | N5: VALUE & ALERTS
B6: Ingredient | C6: Supplier | D6: Stock unit | E6: Pack size (stock units) | F6: ="Pack price ("&cfg_Symbol&")" | G6: ="Cost per unit ("&cfg_Symbol&")" | H6: Opening stock at count | I6: Purchased since count | J6: Used by sales (auto) | K6: Other usage (staff meals...) | L6: Wasted (auto) | M6: Est. on hand | N6: ="Stock value ("&cfg_Symbol&")" | O6: Reorder level | P6: Status | Q6: ="Waste value ("&cfg_Symbol&")"
G7: =IF($B7="","",IF(N($E7)<=0,"",N($F7)/$E7)) | J7: =IF($B7="","",SUMIFS('Recipe Builder'!$L$7:$L$406,'Recipe Builder'!$C$7:$C$406,$B7)) | L7: =IF($B7="","",SUMIFS('Waste Log'!$I$7:$I$506,'Waste Log'!$C$7:$C$506,$B7,'Waste Log'!$B$7:$B$506,">="&cfg_CountDate)) | M7: =IF($B7="","",N($H7)+N($I7)-N($J7)-N($K7)-N($L7)) | N7: =IF($B7="","",IF($G7="",0,MAX(0,$M7)*$G7)) | P7: =IF($B7="","",IF($D7="","Set stock unit",IF($G7="","Add pack size & price",IF($M7<0,"Recount (negative)",IF(AND(ISNUMBER($O7),$M7<=$O7),"Reorder","OK"))))) | Q7: =IF(OR($B7="",$G7=""),"",N($L7)*$G7)
G8: =IF($B8="","",IF(N($E8)<=0,"",N($F8)/$E8)) | J8: =IF($B8="","",SUMIFS('Recipe Builder'!$L$7:$L$406,'Recipe Builder'!$C$7:$C$406,$B8)) | L8: =IF($B8="","",SUMIFS('Waste Log'!$I$7:$I$506,'Waste Log'!$C$7:$C$506,$B8,'Waste Log'!$B$7:$B$506,">="&cfg_CountDate)) | M8: =IF($B8="","",N($H8)+N($I8)-N($J8)-N($K8)-N($L8)) | N8: =IF($B8="","",IF($G8="",0,MAX(0,$M8)*$G8)) | P8: =IF($B8="","",IF($D8="","Set stock unit",IF($G8="","Add pack size & price",IF($M8<0,"Recount (negative)",IF(AND(ISNUMBER($O8),$M8<=$O8),"Reorder","OK"))))) | Q8: =IF(OR($B8="",$G8=""),"",N($L8)*$G8)
G9: =IF($B9="","",IF(N($E9)<=0,"",N($F9)/$E9)) | J9: =IF($B9="","",SUMIFS('Recipe Builder'!$L$7:$L$406,'Recipe Builder'!$C$7:$C$406,$B9)) | L9: =IF($B9="","",SUMIFS('Waste Log'!$I$7:$I$506,'Waste Log'!$C$7:$C$506,$B9,'Waste Log'!$B$7:$B$506,">="&cfg_CountDate)) | M9: =IF($B9="","",N($H9)+N($I9)-N($J9)-N($K9)-N($L9)) | N9: =IF($B9="","",IF($G9="",0,MAX(0,$M9)*$G9)) | P9: =IF($B9="","",IF($D9="","Set stock unit",IF($G9="","Add pack size & price",IF($M9<0,"Recount (negative)",IF(AND(ISNUMBER($O9),$M9<=$O9),"Reorder","OK"))))) | Q9: =IF(OR($B9="",$G9=""),"",N($L9)*$G9)
G10: =IF($B10="","",IF(N($E10)<=0,"",N($F10)/$E10)) | J10: =IF($B10="","",SUMIFS('Recipe Builder'!$L$7:$L$406,'Recipe Builder'!$C$7:$C$406,$B10)) | L10: =IF($B10="","",SUMIFS('Waste Log'!$I$7:$I$506,'Waste Log'!$C$7:$C$506,$B10,'Waste Log'!$B$7:$B$506,">="&cfg_CountDate)) | M10: =IF($B10="","",N($H10)+N($I10)-N($J10)-N($K10)-N($L10)) | N10: =IF($B10="","",IF($G10="",0,MAX(0,$M10)*$G10)) | P10: =IF($B10="","",IF($D10="","Set stock unit",IF($G10="","Add pack size & price",IF($M10<0,"Recount (negative)",IF(AND(ISNUMBER($O10),$M10<=$O10),"Reorder","OK"))))) | Q10: =IF(OR($B10="",$G10=""),"",N($L10)*$G10)
G11: =IF($B11="","",IF(N($E11)<=0,"",N($F11)/$E11)) | J11: =IF($B11="","",SUMIFS('Recipe Builder'!$L$7:$L$406,'Recipe Builder'!$C$7:$C$406,$B11)) | L11: =IF($B11="","",SUMIFS('Waste Log'!$I$7:$I$506,'Waste Log'!$C$7:$C$506,$B11,'Waste Log'!$B$7:$B$506,">="&cfg_CountDate)) | M11: =IF($B11="","",N($H11)+N($I11)-N($J11)-N($K11)-N($L11)) | N11: =IF($B11="","",IF($G11="",0,MAX(0,$M11)*$G11)) | P11: =IF($B11="","",IF($D11="","Set stock unit",IF($G11="","Add pack size & price",IF($M11<0,"Recount (negative)",IF(AND(ISNUMBER($O11),$M11<=$O11),"Reorder","OK"))))) | Q11: =IF(OR($B11="",$G11=""),"",N($L11)*$G11)
G12: =IF($B12="","",IF(N($E12)<=0,"",N($F12)/$E12)) | J12: =IF($B12="","",SUMIFS('Recipe Builder'!$L$7:$L$406,'Recipe Builder'!$C$7:$C$406,$B12)) | L12: =IF($B12="","",SUMIFS('Waste Log'!$I$7:$I$506,'Waste Log'!$C$7:$C$506,$B12,'Waste Log'!$B$7:$B$506,">="&cfg_CountDate)) | M12: =IF($B12="","",N($H12)+N($I12)-N($J12)-N($K12)-N($L12)) | N12: =IF($B12="","",IF($G12="",0,MAX(0,$M12)*$G12)) | P12: =IF($B12="","",IF($D12="","Set stock unit",IF($G12="","Add pack size & price",IF($M12<0,"Recount (negative)",IF(AND(ISNUMBER($O12),$M12<=$O12),"Reorder","OK"))))) | Q12: =IF(OR($B12="",$G12=""),"",N($L12)*$G12)
G13: =IF($B13="","",IF(N($E13)<=0,"",N($F13)/$E13)) | J13: =IF($B13="","",SUMIFS('Recipe Builder'!$L$7:$L$406,'Recipe Builder'!$C$7:$C$406,$B13)) | L13: =IF($B13="","",SUMIFS('Waste Log'!$I$7:$I$506,'Waste Log'!$C$7:$C$506,$B13,'Waste Log'!$B$7:$B$506,">="&cfg_CountDate)) | M13: =IF($B13="","",N($H13)+N($I13)-N($J13)-N($K13)-N($L13)) | N13: =IF($B13="","",IF($G13="",0,MAX(0,$M13)*$G13)) | P13: =IF($B13="","",IF($D13="","Set stock unit",IF($G13="","Add pack size & price",IF($M13<0,"Recount (negative)",IF(AND(ISNUMBER($O13),$M13<=$O13),"Reorder","OK"))))) | Q13: =IF(OR($B13="",$G13=""),"",N($L13)*$G13)
G14: =IF($B14="","",IF(N($E14)<=0,"",N($F14)/$E14)) | J14: =IF($B14="","",SUMIFS('Recipe Builder'!$L$7:$L$406,'Recipe Builder'!$C$7:$C$406,$B14)) | L14: =IF($B14="","",SUMIFS('Waste Log'!$I$7:$I$506,'Waste Log'!$C$7:$C$506,$B14,'Waste Log'!$B$7:$B$506,">="&cfg_CountDate)) | M14: =IF($B14="","",N($H14)+N($I14)-N($J14)-N($K14)-N($L14)) | N14: =IF($B14="","",IF($G14="",0,MAX(0,$M14)*$G14)) | P14: =IF($B14="","",IF($D14="","Set stock unit",IF($G14="","Add pack size & price",IF($M14<0,"Recount (negative)",IF(AND(ISNUMBER($O14),$M14<=$O14),"Reorder","OK"))))) | Q14: =IF(OR($B14="",$G14=""),"",N($L14)*$G14)
G15: =IF($B15="","",IF(N($E15)<=0,"",N($F15)/$E15)) | J15: =IF($B15="","",SUMIFS('Recipe Builder'!$L$7:$L$406,'Recipe Builder'!$C$7:$C$406,$B15)) | L15: =IF($B15="","",SUMIFS('Waste Log'!$I$7:$I$506,'Waste Log'!$C$7:$C$506,$B15,'Waste Log'!$B$7:$B$506,">="&cfg_CountDate)) | M15: =IF($B15="","",N($H15)+N($I15)-N($J15)-N($K15)-N($L15)) | N15: =IF($B15="","",IF($G15="",0,MAX(0,$M15)*$G15)) | P15: =IF($B15="","",IF($D15="","Set stock unit",IF($G15="","Add pack size & price",IF($M15<0,"Recount (negative)",IF(AND(ISNUMBER($O15),$M15<=$O15),"Reorder","OK"))))) | Q15: =IF(OR($B15="",$G15=""),"",N($L15)*$G15)
G16: =IF($B16="","",IF(N($E16)<=0,"",N($F16)/$E16)) | J16: =IF($B16="","",SUMIFS('Recipe Builder'!$L$7:$L$406,'Recipe Builder'!$C$7:$C$406,$B16)) | L16: =IF($B16="","",SUMIFS('Waste Log'!$I$7:$I$506,'Waste Log'!$C$7:$C$506,$B16,'Waste Log'!$B$7:$B$506,">="&cfg_CountDate)) | M16: =IF($B16="","",N($H16)+N($I16)-N($J16)-N($K16)-N($L16)) | N16: =IF($B16="","",IF($G16="",0,MAX(0,$M16)*$G16)) | P16: =IF($B16="","",IF($D16="","Set stock unit",IF($G16="","Add pack size & price",IF($M16<0,"Recount (negative)",IF(AND(ISNUMBER($O16),$M16<=$O16),"Reorder","OK"))))) | Q16: =IF(OR($B16="",$G16=""),"",N($L16)*$G16)
G17: =IF($B17="","",IF(N($E17)<=0,"",N($F17)/$E17)) | J17: =IF($B17="","",SUMIFS('Recipe Builder'!$L$7:$L$406,'Recipe Builder'!$C$7:$C$406,$B17)) | L17: =IF($B17="","",SUMIFS('Waste Log'!$I$7:$I$506,'Waste Log'!$C$7:$C$506,$B17,'Waste Log'!$B$7:$B$506,">="&cfg_CountDate)) | M17: =IF($B17="","",N($H17)+N($I17)-N($J17)-N($K17)-N($L17)) | N17: =IF($B17="","",IF($G17="",0,MAX(0,$M17)*$G17)) | P17: =IF($B17="","",IF($D17="","Set stock unit",IF($G17="","Add pack size & price",IF($M17<0,"Recount (negative)",IF(AND(ISNUMBER($O17),$M17<=$O17),"Reorder","OK"))))) | Q17: =IF(OR($B17="",$G17=""),"",N($L17)*$G17)
G18: =IF($B18="","",IF(N($E18)<=0,"",N($F18)/$E18)) | J18: =IF($B18="","",SUMIFS('Recipe Builder'!$L$7:$L$406,'Recipe Builder'!$C$7:$C$406,$B18)) | L18: =IF($B18="","",SUMIFS('Waste Log'!$I$7:$I$506,'Waste Log'!$C$7:$C$506,$B18,'Waste Log'!$B$7:$B$506,">="&cfg_CountDate)) | M18: =IF($B18="","",N($H18)+N($I18)-N($J18)-N($K18)-N($L18)) | N18: =IF($B18="","",IF($G18="",0,MAX(0,$M18)*$G18)) | P18: =IF($B18="","",IF($D18="","Set stock unit",IF($G18="","Add pack size & price",IF($M18<0,"Recount (negative)",IF(AND(ISNUMBER($O18),$M18<=$O18),"Reorder","OK"))))) | Q18: =IF(OR($B18="",$G18=""),"",N($L18)*$G18)
... G106: =IF($B106="","",IF(N($E106)<=0,"",N($F106)/$E106)) | J106: =IF($B106="","",SUMIFS('Recipe Builder'!$L$7:$L$406,'Recipe Builder'!$C$7:$C$406,$B106)) | L106: =IF($B106="","",SUMIFS('Waste Log'!$I$7:$I$506,'Waste Log'!$C$7:$C$506,$B106,'Waste Log'!$B$7:$B$506,">="&cfg_CountDate)) | M106: =IF($B106="","",N($H106)+N($I106)-N($J106)-N($K106)-N($L106)) | N106: =IF($B106="","",IF($G106="",0,MAX(0,$M106)*$G106)) | P106: =IF($B106="","",IF($D106="","Set stock unit",IF($G106="","Add pack size & price",IF($M106<0,"Recount (negative)",IF(AND(ISNUMBER($O106),$M106<=$O106),"Reorder","OK"))))) | Q106: =IF(OR($B106="",$G106=""),"",N($L106)*$G106)
B107: TOTAL STOCK VALUE | N107: =SUM(N7:N106) | P107: =COUNTIF(P7:P106,"Reorder")&" to reorder" | Q107: =SUM(Q7:Q106)
B109: Duplicate ingredient names turn red - each name must be unique. 'Used by sales' = recipe quantity x items sold since the stock count date.

Sheet Waste Log
B2: Waste Log | K2: NoviraNest
B3: Record food you throw away. Any unit of the same type as the stock unit works (e.g. stock in kg, waste in g).
B4: › Start Here | D4: › Dashboard | F4: › Inventory
B5: YOU TYPE | G5: AUTOMATIC
B6: Date | C6: Ingredient | D6: Qty | E6: Unit | F6: Reason | G6: Stock unit | H6: Check | I6: Qty in stock units | J6: ="Waste value ("&cfg_Symbol&")"
G7: =IF($C7="","",IFERROR(INDEX('Inventory'!$D$7:$D$106,MATCH($C7,'Inventory'!$B$7:$B$106,0))&"","?")) | H7: =IF(AND($B7="",$C7="",$D7=""),"",IF(NOT(ISNUMBER($B7)),"Enter a valid date",IF($C7="","Pick ingredient",IF($G7="?","Not in Inventory",IF($G7="","Set stock unit in Inventory",IF(N($D7)<=0,"Enter quantity",IF($E7="","Pick unit",IF(IFERROR(INDEX('Lists'!$C$6:$C$30,MATCH($E7,'Lists'!$B$6:$B$30,0)),"?")<>IFERROR(INDEX('Lists'!$C$6:$C$30,MATCH($G7,'Lists'!$B$6:$B$30,0)),"?"),"Unit mismatch",IF(ISNUMBER(INDEX('Inventory'!$G$7:$G$106,MATCH($C7,'Inventory'!$B$7:$B$106,0))),"OK","Add price in Inventory"))))))))) | I7: =IF($H7<>"OK","",$D7*INDEX('Lists'!$D$6:$D$30,MATCH($E7,'Lists'!$B$6:$B$30,0))/INDEX('Lists'!$D$6:$D$30,MATCH($G7,'Lists'!$B$6:$B$30,0))) | J7: =IF($H7<>"OK","",$I7*INDEX('Inventory'!$G$7:$G$106,MATCH($C7,'Inventory'!$B$7:$B$106,0)))
G8: =IF($C8="","",IFERROR(INDEX('Inventory'!$D$7:$D$106,MATCH($C8,'Inventory'!$B$7:$B$106,0))&"","?")) | H8: =IF(AND($B8="",$C8="",$D8=""),"",IF(NOT(ISNUMBER($B8)),"Enter a valid date",IF($C8="","Pick ingredient",IF($G8="?","Not in Inventory",IF($G8="","Set stock unit in Inventory",IF(N($D8)<=0,"Enter quantity",IF($E8="","Pick unit",IF(IFERROR(INDEX('Lists'!$C$6:$C$30,MATCH($E8,'Lists'!$B$6:$B$30,0)),"?")<>IFERROR(INDEX('Lists'!$C$6:$C$30,MATCH($G8,'Lists'!$B$6:$B$30,0)),"?"),"Unit mismatch",IF(ISNUMBER(INDEX('Inventory'!$G$7:$G$106,MATCH($C8,'Inventory'!$B$7:$B$106,0))),"OK","Add price in Inventory"))))))))) | I8: =IF($H8<>"OK","",$D8*INDEX('Lists'!$D$6:$D$30,MATCH($E8,'Lists'!$B$6:$B$30,0))/INDEX('Lists'!$D$6:$D$30,MATCH($G8,'Lists'!$B$6:$B$30,0))) | J8: =IF($H8<>"OK","",$I8*INDEX('Inventory'!$G$7:$G$106,MATCH($C8,'Inventory'!$B$7:$B$106,0)))
G9: =IF($C9="","",IFERROR(INDEX('Inventory'!$D$7:$D$106,MATCH($C9,'Inventory'!$B$7:$B$106,0))&"","?")) | H9: =IF(AND($B9="",$C9="",$D9=""),"",IF(NOT(ISNUMBER($B9)),"Enter a valid date",IF($C9="","Pick ingredient",IF($G9="?","Not in Inventory",IF($G9="","Set stock unit in Inventory",IF(N($D9)<=0,"Enter quantity",IF($E9="","Pick unit",IF(IFERROR(INDEX('Lists'!$C$6:$C$30,MATCH($E9,'Lists'!$B$6:$B$30,0)),"?")<>IFERROR(INDEX('Lists'!$C$6:$C$30,MATCH($G9,'Lists'!$B$6:$B$30,0)),"?"),"Unit mismatch",IF(ISNUMBER(INDEX('Inventory'!$G$7:$G$106,MATCH($C9,'Inventory'!$B$7:$B$106,0))),"OK","Add price in Inventory"))))))))) | I9: =IF($H9<>"OK","",$D9*INDEX('Lists'!$D$6:$D$30,MATCH($E9,'Lists'!$B$6:$B$30,0))/INDEX('Lists'!$D$6:$D$30,MATCH($G9,'Lists'!$B$6:$B$30,0))) | J9: =IF($H9<>"OK","",$I9*INDEX('Inventory'!$G$7:$G$106,MATCH($C9,'Inventory'!$B$7:$B$106,0)))
G10: =IF($C10="","",IFERROR(INDEX('Inventory'!$D$7:$D$106,MATCH($C10,'Inventory'!$B$7:$B$106,0))&"","?")) | H10: =IF(AND($B10="",$C10="",$D10=""),"",IF(NOT(ISNUMBER($B10)),"Enter a valid date",IF($C10="","Pick ingredient",IF($G10="?","Not in Inventory",IF($G10="","Set stock unit in Inventory",IF(N($D10)<=0,"Enter quantity",IF($E10="","Pick unit",IF(IFERROR(INDEX('Lists'!$C$6:$C$30,MATCH($E10,'Lists'!$B$6:$B$30,0)),"?")<>IFERROR(INDEX('Lists'!$C$6:$C$30,MATCH($G10,'Lists'!$B$6:$B$30,0)),"?"),"Unit mismatch",IF(ISNUMBER(INDEX('Inventory'!$G$7:$G$106,MATCH($C10,'Inventory'!$B$7:$B$106,0))),"OK","Add price in Inventory"))))))))) | I10: =IF($H10<>"OK","",$D10*INDEX('Lists'!$D$6:$D$30,MATCH($E10,'Lists'!$B$6:$B$30,0))/INDEX('Lists'!$D$6:$D$30,MATCH($G10,'Lists'!$B$6:$B$30,0))) | J10: =IF($H10<>"OK","",$I10*INDEX('Inventory'!$G$7:$G$106,MATCH($C10,'Inventory'!$B$7:$B$106,0)))
G11: =IF($C11="","",IFERROR(INDEX('Inventory'!$D$7:$D$106,MATCH($C11,'Inventory'!$B$7:$B$106,0))&"","?")) | H11: =IF(AND($B11="",$C11="",$D11=""),"",IF(NOT(ISNUMBER($B11)),"Enter a valid date",IF($C11="","Pick ingredient",IF($G11="?","Not in Inventory",IF($G11="","Set stock unit in Inventory",IF(N($D11)<=0,"Enter quantity",IF($E11="","Pick unit",IF(IFERROR(INDEX('Lists'!$C$6:$C$30,MATCH($E11,'Lists'!$B$6:$B$30,0)),"?")<>IFERROR(INDEX('Lists'!$C$6:$C$30,MATCH($G11,'Lists'!$B$6:$B$30,0)),"?"),"Unit mismatch",IF(ISNUMBER(INDEX('Inventory'!$G$7:$G$106,MATCH($C11,'Inventory'!$B$7:$B$106,0))),"OK","Add price in Inventory"))))))))) | I11: =IF($H11<>"OK","",$D11*INDEX('Lists'!$D$6:$D$30,MATCH($E11,'Lists'!$B$6:$B$30,0))/INDEX('Lists'!$D$6:$D$30,MATCH($G11,'Lists'!$B$6:$B$30,0))) | J11: =IF($H11<>"OK","",$I11*INDEX('Inventory'!$G$7:$G$106,MATCH($C11,'Inventory'!$B$7:$B$106,0)))
G12: =IF($C12="","",IFERROR(INDEX('Inventory'!$D$7:$D$106,MATCH($C12,'Inventory'!$B$7:$B$106,0))&"","?")) | H12: =IF(AND($B12="",$C12="",$D12=""),"",IF(NOT(ISNUMBER($B12)),"Enter a valid date",IF($C12="","Pick ingredient",IF($G12="?","Not in Inventory",IF($G12="","Set stock unit in Inventory",IF(N($D12)<=0,"Enter quantity",IF($E12="","Pick unit",IF(IFERROR(INDEX('Lists'!$C$6:$C$30,MATCH($E12,'Lists'!$B$6:$B$30,0)),"?")<>IFERROR(INDEX('Lists'!$C$6:$C$30,MATCH($G12,'Lists'!$B$6:$B$30,0)),"?"),"Unit mismatch",IF(ISNUMBER(INDEX('Inventory'!$G$7:$G$106,MATCH($C12,'Inventory'!$B$7:$B$106,0))),"OK","Add price in Inventory"))))))))) | I12: =IF($H12<>"OK","",$D12*INDEX('Lists'!$D$6:$D$30,MATCH($E12,'Lists'!$B$6:$B$30,0))/INDEX('Lists'!$D$6:$D$30,MATCH($G12,'Lists'!$B$6:$B$30,0))) | J12: =IF($H12<>"OK","",$I12*INDEX('Inventory'!$G$7:$G$106,MATCH($C12,'Inventory'!$B$7:$B$106,0)))
G13: =IF($C13="","",IFERROR(INDEX('Inventory'!$D$7:$D$106,MATCH($C13,'Inventory'!$B$7:$B$106,0))&"","?")) | H13: =IF(AND($B13="",$C13="",$D13=""),"",IF(NOT(ISNUMBER($B13)),"Enter a valid date",IF($C13="","Pick ingredient",IF($G13="?","Not in Inventory",IF($G13="","Set stock unit in Inventory",IF(N($D13)<=0,"Enter quantity",IF($E13="","Pick unit",IF(IFERROR(INDEX('Lists'!$C$6:$C$30,MATCH($E13,'Lists'!$B$6:$B$30,0)),"?")<>IFERROR(INDEX('Lists'!$C$6:$C$30,MATCH($G13,'Lists'!$B$6:$B$30,0)),"?"),"Unit mismatch",IF(ISNUMBER(INDEX('Inventory'!$G$7:$G$106,MATCH($C13,'Inventory'!$B$7:$B$106,0))),"OK","Add price in Inventory"))))))))) | I13: =IF($H13<>"OK","",$D13*INDEX('Lists'!$D$6:$D$30,MATCH($E13,'Lists'!$B$6:$B$30,0))/INDEX('Lists'!$D$6:$D$30,MATCH($G13,'Lists'!$B$6:$B$30,0))) | J13: =IF($H13<>"OK","",$I13*INDEX('Inventory'!$G$7:$G$106,MATCH($C13,'Inventory'!$B$7:$B$106,0)))
G14: =IF($C14="","",IFERROR(INDEX('Inventory'!$D$7:$D$106,MATCH($C14,'Inventory'!$B$7:$B$106,0))&"","?")) | H14: =IF(AND($B14="",$C14="",$D14=""),"",IF(NOT(ISNUMBER($B14)),"Enter a valid date",IF($C14="","Pick ingredient",IF($G14="?","Not in Inventory",IF($G14="","Set stock unit in Inventory",IF(N($D14)<=0,"Enter quantity",IF($E14="","Pick unit",IF(IFERROR(INDEX('Lists'!$C$6:$C$30,MATCH($E14,'Lists'!$B$6:$B$30,0)),"?")<>IFERROR(INDEX('Lists'!$C$6:$C$30,MATCH($G14,'Lists'!$B$6:$B$30,0)),"?"),"Unit mismatch",IF(ISNUMBER(INDEX('Inventory'!$G$7:$G$106,MATCH($C14,'Inventory'!$B$7:$B$106,0))),"OK","Add price in Inventory"))))))))) | I14: =IF($H14<>"OK","",$D14*INDEX('Lists'!$D$6:$D$30,MATCH($E14,'Lists'!$B$6:$B$30,0))/INDEX('Lists'!$D$6:$D$30,MATCH($G14,'Lists'!$B$6:$B$30,0))) | J14: =IF($H14<>"OK","",$I14*INDEX('Inventory'!$G$7:$G$106,MATCH($C14,'Inventory'!$B$7:$B$106,0)))
G15: =IF($C15="","",IFERROR(INDEX('Inventory'!$D$7:$D$106,MATCH($C15,'Inventory'!$B$7:$B$106,0))&"","?")) | H15: =IF(AND($B15="",$C15="",$D15=""),"",IF(NOT(ISNUMBER($B15)),"Enter a valid date",IF($C15="","Pick ingredient",IF($G15="?","Not in Inventory",IF($G15="","Set stock unit in Inventory",IF(N($D15)<=0,"Enter quantity",IF($E15="","Pick unit",IF(IFERROR(INDEX('Lists'!$C$6:$C$30,MATCH($E15,'Lists'!$B$6:$B$30,0)),"?")<>IFERROR(INDEX('Lists'!$C$6:$C$30,MATCH($G15,'Lists'!$B$6:$B$30,0)),"?"),"Unit mismatch",IF(ISNUMBER(INDEX('Inventory'!$G$7:$G$106,MATCH($C15,'Inventory'!$B$7:$B$106,0))),"OK","Add price in Inventory"))))))))) | I15: =IF($H15<>"OK","",$D15*INDEX('Lists'!$D$6:$D$30,MATCH($E15,'Lists'!$B$6:$B$30,0))/INDEX('Lists'!$D$6:$D$30,MATCH($G15,'Lists'!$B$6:$B$30,0))) | J15: =IF($H15<>"OK","",$I15*INDEX('Inventory'!$G$7:$G$106,MATCH($C15,'Inventory'!$B$7:$B$106,0)))
G16: =IF($C16="","",IFERROR(INDEX('Inventory'!$D$7:$D$106,MATCH($C16,'Inventory'!$B$7:$B$106,0))&"","?")) | H16: =IF(AND($B16="",$C16="",$D16=""),"",IF(NOT(ISNUMBER($B16)),"Enter a valid date",IF($C16="","Pick ingredient",IF($G16="?","Not in Inventory",IF($G16="","Set stock unit in Inventory",IF(N($D16)<=0,"Enter quantity",IF($E16="","Pick unit",IF(IFERROR(INDEX('Lists'!$C$6:$C$30,MATCH($E16,'Lists'!$B$6:$B$30,0)),"?")<>IFERROR(INDEX('Lists'!$C$6:$C$30,MATCH($G16,'Lists'!$B$6:$B$30,0)),"?"),"Unit mismatch",IF(ISNUMBER(INDEX('Inventory'!$G$7:$G$106,MATCH($C16,'Inventory'!$B$7:$B$106,0))),"OK","Add price in Inventory"))))))))) | I16: =IF($H16<>"OK","",$D16*INDEX('Lists'!$D$6:$D$30,MATCH($E16,'Lists'!$B$6:$B$30,0))/INDEX('Lists'!$D$6:$D$30,MATCH($G16,'Lists'!$B$6:$B$30,0))) | J16: =IF($H16<>"OK","",$I16*INDEX('Inventory'!$G$7:$G$106,MATCH($C16,'Inventory'!$B$7:$B$106,0)))
G17: =IF($C17="","",IFERROR(INDEX('Inventory'!$D$7:$D$106,MATCH($C17,'Inventory'!$B$7:$B$106,0))&"","?")) | H17: =IF(AND($B17="",$C17="",$D17=""),"",IF(NOT(ISNUMBER($B17)),"Enter a valid date",IF($C17="","Pick ingredient",IF($G17="?","Not in Inventory",IF($G17="","Set stock unit in Inventory",IF(N($D17)<=0,"Enter quantity",IF($E17="","Pick unit",IF(IFERROR(INDEX('Lists'!$C$6:$C$30,MATCH($E17,'Lists'!$B$6:$B$30,0)),"?")<>IFERROR(INDEX('Lists'!$C$6:$C$30,MATCH($G17,'Lists'!$B$6:$B$30,0)),"?"),"Unit mismatch",IF(ISNUMBER(INDEX('Inventory'!$G$7:$G$106,MATCH($C17,'Inventory'!$B$7:$B$106,0))),"OK","Add price in Inventory"))))))))) | I17: =IF($H17<>"OK","",$D17*INDEX('Lists'!$D$6:$D$30,MATCH($E17,'Lists'!$B$6:$B$30,0))/INDEX('Lists'!$D$6:$D$30,MATCH($G17,'Lists'!$B$6:$B$30,0))) | J17: =IF($H17<>"OK","",$I17*INDEX('Inventory'!$G$7:$G$106,MATCH($C17,'Inventory'!$B$7:$B$106,0)))
G18: =IF($C18="","",IFERROR(INDEX('Inventory'!$D$7:$D$106,MATCH($C18,'Inventory'!$B$7:$B$106,0))&"","?")) | H18: =IF(AND($B18="",$C18="",$D18=""),"",IF(NOT(ISNUMBER($B18)),"Enter a valid date",IF($C18="","Pick ingredient",IF($G18="?","Not in Inventory",IF($G18="","Set stock unit in Inventory",IF(N($D18)<=0,"Enter quantity",IF($E18="","Pick unit",IF(IFERROR(INDEX('Lists'!$C$6:$C$30,MATCH($E18,'Lists'!$B$6:$B$30,0)),"?")<>IFERROR(INDEX('Lists'!$C$6:$C$30,MATCH($G18,'Lists'!$B$6:$B$30,0)),"?"),"Unit mismatch",IF(ISNUMBER(INDEX('Inventory'!$G$7:$G$106,MATCH($C18,'Inventory'!$B$7:$B$106,0))),"OK","Add price in Inventory"))))))))) | I18: =IF($H18<>"OK","",$D18*INDEX('Lists'!$D$6:$D$30,MATCH($E18,'Lists'!$B$6:$B$30,0))/INDEX('Lists'!$D$6:$D$30,MATCH($G18,'Lists'!$B$6:$B$30,0))) | J18: =IF($H18<>"OK","",$I18*INDEX('Inventory'!$G$7:$G$106,MATCH($C18,'Inventory'!$B$7:$B$106,0)))
... G506: =IF($C506="","",IFERROR(INDEX('Inventory'!$D$7:$D$106,MATCH($C506,'Inventory'!$B$7:$B$106,0))&"","?")) | H506: =IF(AND($B506="",$C506="",$D506=""),"",IF(NOT(ISNUMBER($B506)),"Enter a valid date",IF($C506="","Pick ingredient",IF($G506="?","Not in Inventory",IF($G506="","Set stock unit in Inventory",IF(N($D506)<=0,"Enter quantity",IF($E506="","Pick unit",IF(IFERROR(INDEX('Lists'!$C$6:$C$30,MATCH($E506,'Lists'!$B$6:$B$30,0)),"?")<>IFERROR(INDEX('Lists'!$C$6:$C$30,MATCH($G506,'Lists'!$B$6:$B$30,0)),"?"),"Unit mismatch",IF(ISNUMBER(INDEX('Inventory'!$G$7:$G$106,MATCH($C506,'Inventory'!$B$7:$B$106,0))),"OK","Add price in Inventory"))))))))) | I506: =IF($H506<>"OK","",$D506*INDEX('Lists'!$D$6:$D$30,MATCH($E506,'Lists'!$B$6:$B$30,0))/INDEX('Lists'!$D$6:$D$30,MATCH($G506,'Lists'!$B$6:$B$30,0))) | J506: =IF($H506<>"OK","",$I506*INDEX('Inventory'!$G$7:$G$106,MATCH($C506,'Inventory'!$B$7:$B$106,0)))

Sheet Sales Log
B2: Sales Log | O2: NoviraNest
B3: Record what you sold: one row per item per day (or per order). Leave 'Price charged' blank to use your menu price.
B4: › Start Here | D4: › Dashboard | F4: › Menu Pricing
B5: YOU TYPE | H5: AUTOMATIC
B6: Date | C6: Menu item | D6: Qty | E6: ="Price charged (optional) ("&cfg_Symbol&")" | F6: Payment method | G6: Location / event | H6: ="Unit price used ("&cfg_Symbol&")" | I6: ="Revenue ("&cfg_Symbol&")" | J6: ="Unit cost (COGS) ("&cfg_Symbol&")" | K6: ="COGS ("&cfg_Symbol&")" | L6: ="Gross profit ("&cfg_Symbol&")" | M6: ="Ingredient cost ("&cfg_Symbol&")" | N6: Check | O6: Menu row
H7: =IF(OR($C7="",$D7=""),"",IF(ISNUMBER($E7),$E7,IF($O7="","",IF(N(INDEX('Menu Pricing'!$O$7:$O$56,$O7))>0,INDEX('Menu Pricing'!$O$7:$O$56,$O7),"")))) | I7: =IF($N7<>"OK","",$D7*$H7) | J7: =IF($N7<>"OK","",N(INDEX('Menu Pricing'!$F$7:$F$56,$O7))+N(INDEX('Menu Pricing'!$G$7:$G$56,$O7))+N(INDEX('Menu Pricing'!$J$7:$J$56,$O7))) | K7: =IF($N7<>"OK","",$D7*$J7) | L7: =IF($N7<>"OK","",$I7-$K7) | M7: =IF($N7<>"OK","",$D7*N(INDEX('Menu Pricing'!$F$7:$F$56,$O7))) | N7: =IF(AND($B7="",$C7="",$D7=""),"",IF(NOT(ISNUMBER($B7)),"Enter a valid date",IF($C7="","Pick a menu item",IF($O7="","Item not on Menu Pricing",IF(N($D7)<=0,"Qty must be above 0",IF($H7="","No price on menu","OK")))))) | O7: =IF($C7="","",IFERROR(MATCH($C7,'Menu Pricing'!$B$7:$B$56,0),""))
H8: =IF(OR($C8="",$D8=""),"",IF(ISNUMBER($E8),$E8,IF($O8="","",IF(N(INDEX('Menu Pricing'!$O$7:$O$56,$O8))>0,INDEX('Menu Pricing'!$O$7:$O$56,$O8),"")))) | I8: =IF($N8<>"OK","",$D8*$H8) | J8: =IF($N8<>"OK","",N(INDEX('Menu Pricing'!$F$7:$F$56,$O8))+N(INDEX('Menu Pricing'!$G$7:$G$56,$O8))+N(INDEX('Menu Pricing'!$J$7:$J$56,$O8))) | K8: =IF($N8<>"OK","",$D8*$J8) | L8: =IF($N8<>"OK","",$I8-$K8) | M8: =IF($N8<>"OK","",$D8*N(INDEX('Menu Pricing'!$F$7:$F$56,$O8))) | N8: =IF(AND($B8="",$C8="",$D8=""),"",IF(NOT(ISNUMBER($B8)),"Enter a valid date",IF($C8="","Pick a menu item",IF($O8="","Item not on Menu Pricing",IF(N($D8)<=0,"Qty must be above 0",IF($H8="","No price on menu","OK")))))) | O8: =IF($C8="","",IFERROR(MATCH($C8,'Menu Pricing'!$B$7:$B$56,0),""))
H9: =IF(OR($C9="",$D9=""),"",IF(ISNUMBER($E9),$E9,IF($O9="","",IF(N(INDEX('Menu Pricing'!$O$7:$O$56,$O9))>0,INDEX('Menu Pricing'!$O$7:$O$56,$O9),"")))) | I9: =IF($N9<>"OK","",$D9*$H9) | J9: =IF($N9<>"OK","",N(INDEX('Menu Pricing'!$F$7:$F$56,$O9))+N(INDEX('Menu Pricing'!$G$7:$G$56,$O9))+N(INDEX('Menu Pricing'!$J$7:$J$56,$O9))) | K9: =IF($N9<>"OK","",$D9*$J9) | L9: =IF($N9<>"OK","",$I9-$K9) | M9: =IF($N9<>"OK","",$D9*N(INDEX('Menu Pricing'!$F$7:$F$56,$O9))) | N9: =IF(AND($B9="",$C9="",$D9=""),"",IF(NOT(ISNUMBER($B9)),"Enter a valid date",IF($C9="","Pick a menu item",IF($O9="","Item not on Menu Pricing",IF(N($D9)<=0,"Qty must be above 0",IF($H9="","No price on menu","OK")))))) | O9: =IF($C9="","",IFERROR(MATCH($C9,'Menu Pricing'!$B$7:$B$56,0),""))
H10: =IF(OR($C10="",$D10=""),"",IF(ISNUMBER($E10),$E10,IF($O10="","",IF(N(INDEX('Menu Pricing'!$O$7:$O$56,$O10))>0,INDEX('Menu Pricing'!$O$7:$O$56,$O10),"")))) | I10: =IF($N10<>"OK","",$D10*$H10) | J10: =IF($N10<>"OK","",N(INDEX('Menu Pricing'!$F$7:$F$56,$O10))+N(INDEX('Menu Pricing'!$G$7:$G$56,$O10))+N(INDEX('Menu Pricing'!$J$7:$J$56,$O10))) | K10: =IF($N10<>"OK","",$D10*$J10) | L10: =IF($N10<>"OK","",$I10-$K10) | M10: =IF($N10<>"OK","",$D10*N(INDEX('Menu Pricing'!$F$7:$F$56,$O10))) | N10: =IF(AND($B10="",$C10="",$D10=""),"",IF(NOT(ISNUMBER($B10)),"Enter a valid date",IF($C10="","Pick a menu item",IF($O10="","Item not on Menu Pricing",IF(N($D10)<=0,"Qty must be above 0",IF($H10="","No price on menu","OK")))))) | O10: =IF($C10="","",IFERROR(MATCH($C10,'Menu Pricing'!$B$7:$B$56,0),""))
H11: =IF(OR($C11="",$D11=""),"",IF(ISNUMBER($E11),$E11,IF($O11="","",IF(N(INDEX('Menu Pricing'!$O$7:$O$56,$O11))>0,INDEX('Menu Pricing'!$O$7:$O$56,$O11),"")))) | I11: =IF($N11<>"OK","",$D11*$H11) | J11: =IF($N11<>"OK","",N(INDEX('Menu Pricing'!$F$7:$F$56,$O11))+N(INDEX('Menu Pricing'!$G$7:$G$56,$O11))+N(INDEX('Menu Pricing'!$J$7:$J$56,$O11))) | K11: =IF($N11<>"OK","",$D11*$J11) | L11: =IF($N11<>"OK","",$I11-$K11) | M11: =IF($N11<>"OK","",$D11*N(INDEX('Menu Pricing'!$F$7:$F$56,$O11))) | N11: =IF(AND($B11="",$C11="",$D11=""),"",IF(NOT(ISNUMBER($B11)),"Enter a valid date",IF($C11="","Pick a menu item",IF($O11="","Item not on Menu Pricing",IF(N($D11)<=0,"Qty must be above 0",IF($H11="","No price on menu","OK")))))) | O11: =IF($C11="","",IFERROR(MATCH($C11,'Menu Pricing'!$B$7:$B$56,0),""))
H12: =IF(OR($C12="",$D12=""),"",IF(ISNUMBER($E12),$E12,IF($O12="","",IF(N(INDEX('Menu Pricing'!$O$7:$O$56,$O12))>0,INDEX('Menu Pricing'!$O$7:$O$56,$O12),"")))) | I12: =IF($N12<>"OK","",$D12*$H12) | J12: =IF($N12<>"OK","",N(INDEX('Menu Pricing'!$F$7:$F$56,$O12))+N(INDEX('Menu Pricing'!$G$7:$G$56,$O12))+N(INDEX('Menu Pricing'!$J$7:$J$56,$O12))) | K12: =IF($N12<>"OK","",$D12*$J12) | L12: =IF($N12<>"OK","",$I12-$K12) | M12: =IF($N12<>"OK","",$D12*N(INDEX('Menu Pricing'!$F$7:$F$56,$O12))) | N12: =IF(AND($B12="",$C12="",$D12=""),"",IF(NOT(ISNUMBER($B12)),"Enter a valid date",IF($C12="","Pick a menu item",IF($O12="","Item not on Menu Pricing",IF(N($D12)<=0,"Qty must be above 0",IF($H12="","No price on menu","OK")))))) | O12: =IF($C12="","",IFERROR(MATCH($C12,'Menu Pricing'!$B$7:$B$56,0),""))
H13: =IF(OR($C13="",$D13=""),"",IF(ISNUMBER($E13),$E13,IF($O13="","",IF(N(INDEX('Menu Pricing'!$O$7:$O$56,$O13))>0,INDEX('Menu Pricing'!$O$7:$O$56,$O13),"")))) | I13: =IF($N13<>"OK","",$D13*$H13) | J13: =IF($N13<>"OK","",N(INDEX('Menu Pricing'!$F$7:$F$56,$O13))+N(INDEX('Menu Pricing'!$G$7:$G$56,$O13))+N(INDEX('Menu Pricing'!$J$7:$J$56,$O13))) | K13: =IF($N13<>"OK","",$D13*$J13) | L13: =IF($N13<>"OK","",$I13-$K13) | M13: =IF($N13<>"OK","",$D13*N(INDEX('Menu Pricing'!$F$7:$F$56,$O13))) | N13: =IF(AND($B13="",$C13="",$D13=""),"",IF(NOT(ISNUMBER($B13)),"Enter a valid date",IF($C13="","Pick a menu item",IF($O13="","Item not on Menu Pricing",IF(N($D13)<=0,"Qty must be above 0",IF($H13="","No price on menu","OK")))))) | O13: =IF($C13="","",IFERROR(MATCH($C13,'Menu Pricing'!$B$7:$B$56,0),""))
H14: =IF(OR($C14="",$D14=""),"",IF(ISNUMBER($E14),$E14,IF($O14="","",IF(N(INDEX('Menu Pricing'!$O$7:$O$56,$O14))>0,INDEX('Menu Pricing'!$O$7:$O$56,$O14),"")))) | I14: =IF($N14<>"OK","",$D14*$H14) | J14: =IF($N14<>"OK","",N(INDEX('Menu Pricing'!$F$7:$F$56,$O14))+N(INDEX('Menu Pricing'!$G$7:$G$56,$O14))+N(INDEX('Menu Pricing'!$J$7:$J$56,$O14))) | K14: =IF($N14<>"OK","",$D14*$J14) | L14: =IF($N14<>"OK","",$I14-$K14) | M14: =IF($N14<>"OK","",$D14*N(INDEX('Menu Pricing'!$F$7:$F$56,$O14))) | N14: =IF(AND($B14="",$C14="",$D14=""),"",IF(NOT(ISNUMBER($B14)),"Enter a valid date",IF($C14="","Pick a menu item",IF($O14="","Item not on Menu Pricing",IF(N($D14)<=0,"Qty must be above 0",IF($H14="","No price on menu","OK")))))) | O14: =IF($C14="","",IFERROR(MATCH($C14,'Menu Pricing'!$B$7:$B$56,0),""))
H15: =IF(OR($C15="",$D15=""),"",IF(ISNUMBER($E15),$E15,IF($O15="","",IF(N(INDEX('Menu Pricing'!$O$7:$O$56,$O15))>0,INDEX('Menu Pricing'!$O$7:$O$56,$O15),"")))) | I15: =IF($N15<>"OK","",$D15*$H15) | J15: =IF($N15<>"OK","",N(INDEX('Menu Pricing'!$F$7:$F$56,$O15))+N(INDEX('Menu Pricing'!$G$7:$G$56,$O15))+N(INDEX('Menu Pricing'!$J$7:$J$56,$O15))) | K15: =IF($N15<>"OK","",$D15*$J15) | L15: =IF($N15<>"OK","",$I15-$K15) | M15: =IF($N15<>"OK","",$D15*N(INDEX('Menu Pricing'!$F$7:$F$56,$O15))) | N15: =IF(AND($B15="",$C15="",$D15=""),"",IF(NOT(ISNUMBER($B15)),"Enter a valid date",IF($C15="","Pick a menu item",IF($O15="","Item not on Menu Pricing",IF(N($D15)<=0,"Qty must be above 0",IF($H15="","No price on menu","OK")))))) | O15: =IF($C15="","",IFERROR(MATCH($C15,'Menu Pricing'!$B$7:$B$56,0),""))
H16: =IF(OR($C16="",$D16=""),"",IF(ISNUMBER($E16),$E16,IF($O16="","",IF(N(INDEX('Menu Pricing'!$O$7:$O$56,$O16))>0,INDEX('Menu Pricing'!$O$7:$O$56,$O16),"")))) | I16: =IF($N16<>"OK","",$D16*$H16) | J16: =IF($N16<>"OK","",N(INDEX('Menu Pricing'!$F$7:$F$56,$O16))+N(INDEX('Menu Pricing'!$G$7:$G$56,$O16))+N(INDEX('Menu Pricing'!$J$7:$J$56,$O16))) | K16: =IF($N16<>"OK","",$D16*$J16) | L16: =IF($N16<>"OK","",$I16-$K16) | M16: =IF($N16<>"OK","",$D16*N(INDEX('Menu Pricing'!$F$7:$F$56,$O16))) | N16: =IF(AND($B16="",$C16="",$D16=""),"",IF(NOT(ISNUMBER($B16)),"Enter a valid date",IF($C16="","Pick a menu item",IF($O16="","Item not on Menu Pricing",IF(N($D16)<=0,"Qty must be above 0",IF($H16="","No price on menu","OK")))))) | O16: =IF($C16="","",IFERROR(MATCH($C16,'Menu Pricing'!$B$7:$B$56,0),""))
H17: =IF(OR($C17="",$D17=""),"",IF(ISNUMBER($E17),$E17,IF($O17="","",IF(N(INDEX('Menu Pricing'!$O$7:$O$56,$O17))>0,INDEX('Menu Pricing'!$O$7:$O$56,$O17),"")))) | I17: =IF($N17<>"OK","",$D17*$H17) | J17: =IF($N17<>"OK","",N(INDEX('Menu Pricing'!$F$7:$F$56,$O17))+N(INDEX('Menu Pricing'!$G$7:$G$56,$O17))+N(INDEX('Menu Pricing'!$J$7:$J$56,$O17))) | K17: =IF($N17<>"OK","",$D17*$J17) | L17: =IF($N17<>"OK","",$I17-$K17) | M17: =IF($N17<>"OK","",$D17*N(INDEX('Menu Pricing'!$F$7:$F$56,$O17))) | N17: =IF(AND($B17="",$C17="",$D17=""),"",IF(NOT(ISNUMBER($B17)),"Enter a valid date",IF($C17="","Pick a menu item",IF($O17="","Item not on Menu Pricing",IF(N($D17)<=0,"Qty must be above 0",IF($H17="","No price on menu","OK")))))) | O17: =IF($C17="","",IFERROR(MATCH($C17,'Menu Pricing'!$B$7:$B$56,0),""))
H18: =IF(OR($C18="",$D18=""),"",IF(ISNUMBER($E18),$E18,IF($O18="","",IF(N(INDEX('Menu Pricing'!$O$7:$O$56,$O18))>0,INDEX('Menu Pricing'!$O$7:$O$56,$O18),"")))) | I18: =IF($N18<>"OK","",$D18*$H18) | J18: =IF($N18<>"OK","",N(INDEX('Menu Pricing'!$F$7:$F$56,$O18))+N(INDEX('Menu Pricing'!$G$7:$G$56,$O18))+N(INDEX('Menu Pricing'!$J$7:$J$56,$O18))) | K18: =IF($N18<>"OK","",$D18*$J18) | L18: =IF($N18<>"OK","",$I18-$K18) | M18: =IF($N18<>"OK","",$D18*N(INDEX('Menu Pricing'!$F$7:$F$56,$O18))) | N18: =IF(AND($B18="",$C18="",$D18=""),"",IF(NOT(ISNUMBER($B18)),"Enter a valid date",IF($C18="","Pick a menu item",IF($O18="","Item not on Menu Pricing",IF(N($D18)<=0,"Qty must be above 0",IF($H18="","No price on menu","OK")))))) | O18: =IF($C18="","",IFERROR(MATCH($C18,'Menu Pricing'!$B$7:$B$56,0),""))
... H3006: =IF(OR($C3006="",$D3006=""),"",IF(ISNUMBER($E3006),$E3006,IF($O3006="","",IF(N(INDEX('Menu Pricing'!$O$7:$O$56,$O3006))>0,INDEX('Menu Pricing'!$O$7:$O$56,$O3006),"")))) | I3006: =IF($N3006<>"OK","",$D3006*$H3006) | J3006: =IF($N3006<>"OK","",N(INDEX('Menu Pricing'!$F$7:$F$56,$O3006))+N(INDEX('Menu Pricing'!$G$7:$G$56,$O3006))+N(INDEX('Menu Pricing'!$J$7:$J$56,$O3006))) | K3006: =IF($N3006<>"OK","",$D3006*$J3006) | L3006: =IF($N3006<>"OK","",$I3006-$K3006) | M3006: =IF($N3006<>"OK","",$D3006*N(INDEX('Menu Pricing'!$F$7:$F$56,$O3006))) | N3006: =IF(AND($B3006="",$C3006="",$D3006=""),"",IF(NOT(ISNUMBER($B3006)),"Enter a valid date",IF($C3006="","Pick a menu item",IF($O3006="","Item not on Menu Pricing",IF(N($D3006)<=0,"Qty must be above 0",IF($H3006="","No price on menu","OK")))))) | O3006: =IF($C3006="","",IFERROR(MATCH($C3006,'Menu Pricing'!$B$7:$B$56,0),""))

Sheet Expenses
B2: Expenses | J2: NoviraNest
B3: Every business cost with a date and category. Ingredient purchases and owner's draw are kept for your records but excluded from profit (see Lists).
B4: › Start Here | D4: › Dashboard | E4: › Lists
B5: YOU TYPE | H5: AUTOMATIC
B6: Date | C6: Category | D6: Description | E6: ="Amount ("&cfg_Symbol&")" | F6: Payment method | G6: Paid to | H6: Cost type | I6: Check
H7: =IF($C7="","",IFERROR(INDEX('Lists'!$G$6:$G$35,MATCH($C7,'Lists'!$F$6:$F$35,0))&"","Unknown category")) | I7: =IF(AND($B7="",$C7="",$E7=""),"",IF(NOT(ISNUMBER($B7)),"Enter a valid date",IF($C7="","Pick a category",IF(OR($H7="Unknown category",$H7=""),"Category has no cost type",IF(NOT(ISNUMBER($E7)),"Enter an amount","OK")))))
H8: =IF($C8="","",IFERROR(INDEX('Lists'!$G$6:$G$35,MATCH($C8,'Lists'!$F$6:$F$35,0))&"","Unknown category")) | I8: =IF(AND($B8="",$C8="",$E8=""),"",IF(NOT(ISNUMBER($B8)),"Enter a valid date",IF($C8="","Pick a category",IF(OR($H8="Unknown category",$H8=""),"Category has no cost type",IF(NOT(ISNUMBER($E8)),"Enter an amount","OK")))))
H9: =IF($C9="","",IFERROR(INDEX('Lists'!$G$6:$G$35,MATCH($C9,'Lists'!$F$6:$F$35,0))&"","Unknown category")) | I9: =IF(AND($B9="",$C9="",$E9=""),"",IF(NOT(ISNUMBER($B9)),"Enter a valid date",IF($C9="","Pick a category",IF(OR($H9="Unknown category",$H9=""),"Category has no cost type",IF(NOT(ISNUMBER($E9)),"Enter an amount","OK")))))
H10: =IF($C10="","",IFERROR(INDEX('Lists'!$G$6:$G$35,MATCH($C10,'Lists'!$F$6:$F$35,0))&"","Unknown category")) | I10: =IF(AND($B10="",$C10="",$E10=""),"",IF(NOT(ISNUMBER($B10)),"Enter a valid date",IF($C10="","Pick a category",IF(OR($H10="Unknown category",$H10=""),"Category has no cost type",IF(NOT(ISNUMBER($E10)),"Enter an amount","OK")))))
H11: =IF($C11="","",IFERROR(INDEX('Lists'!$G$6:$G$35,MATCH($C11,'Lists'!$F$6:$F$35,0))&"","Unknown category")) | I11: =IF(AND($B11="",$C11="",$E11=""),"",IF(NOT(ISNUMBER($B11)),"Enter a valid date",IF($C11="","Pick a category",IF(OR($H11="Unknown category",$H11=""),"Category has no cost type",IF(NOT(ISNUMBER($E11)),"Enter an amount","OK")))))
H12: =IF($C12="","",IFERROR(INDEX('Lists'!$G$6:$G$35,MATCH($C12,'Lists'!$F$6:$F$35,0))&"","Unknown category")) | I12: =IF(AND($B12="",$C12="",$E12=""),"",IF(NOT(ISNUMBER($B12)),"Enter a valid date",IF($C12="","Pick a category",IF(OR($H12="Unknown category",$H12=""),"Category has no cost type",IF(NOT(ISNUMBER($E12)),"Enter an amount","OK")))))
H13: =IF($C13="","",IFERROR(INDEX('Lists'!$G$6:$G$35,MATCH($C13,'Lists'!$F$6:$F$35,0))&"","Unknown category")) | I13: =IF(AND($B13="",$C13="",$E13=""),"",IF(NOT(ISNUMBER($B13)),"Enter a valid date",IF($C13="","Pick a category",IF(OR($H13="Unknown category",$H13=""),"Category has no cost type",IF(NOT(ISNUMBER($E13)),"Enter an amount","OK")))))
H14: =IF($C14="","",IFERROR(INDEX('Lists'!$G$6:$G$35,MATCH($C14,'Lists'!$F$6:$F$35,0))&"","Unknown category")) | I14: =IF(AND($B14="",$C14="",$E14=""),"",IF(NOT(ISNUMBER($B14)),"Enter a valid date",IF($C14="","Pick a category",IF(OR($H14="Unknown category",$H14=""),"Category has no cost type",IF(NOT(ISNUMBER($E14)),"Enter an amount","OK")))))
H15: =IF($C15="","",IFERROR(INDEX('Lists'!$G$6:$G$35,MATCH($C15,'Lists'!$F$6:$F$35,0))&"","Unknown category")) | I15: =IF(AND($B15="",$C15="",$E15=""),"",IF(NOT(ISNUMBER($B15)),"Enter a valid date",IF($C15="","Pick a category",IF(OR($H15="Unknown category",$H15=""),"Category has no cost type",IF(NOT(ISNUMBER($E15)),"Enter an amount","OK")))))
H16: =IF($C16="","",IFERROR(INDEX('Lists'!$G$6:$G$35,MATCH($C16,'Lists'!$F$6:$F$35,0))&"","Unknown category")) | I16: =IF(AND($B16="",$C16="",$E16=""),"",IF(NOT(ISNUMBER($B16)),"Enter a valid date",IF($C16="","Pick a category",IF(OR($H16="Unknown category",$H16=""),"Category has no cost type",IF(NOT(ISNUMBER($E16)),"Enter an amount","OK")))))
H17: =IF($C17="","",IFERROR(INDEX('Lists'!$G$6:$G$35,MATCH($C17,'Lists'!$F$6:$F$35,0))&"","Unknown category")) | I17: =IF(AND($B17="",$C17="",$E17=""),"",IF(NOT(ISNUMBER($B17)),"Enter a valid date",IF($C17="","Pick a category",IF(OR($H17="Unknown category",$H17=""),"Category has no cost type",IF(NOT(ISNUMBER($E17)),"Enter an amount","OK")))))
H18: =IF($C18="","",IFERROR(INDEX('Lists'!$G$6:$G$35,MATCH($C18,'Lists'!$F$6:$F$35,0))&"","Unknown category")) | I18: =IF(AND($B18="",$C18="",$E18=""),"",IF(NOT(ISNUMBER($B18)),"Enter a valid date",IF($C18="","Pick a category",IF(OR($H18="Unknown category",$H18=""),"Category has no cost type",IF(NOT(ISNUMBER($E18)),"Enter an amount","OK")))))
... H1506: =IF($C1506="","",IFERROR(INDEX('Lists'!$G$6:$G$35,MATCH($C1506,'Lists'!$F$6:$F$35,0))&"","Unknown category")) | I1506: =IF(AND($B1506="",$C1506="",$E1506=""),"",IF(NOT(ISNUMBER($B1506)),"Enter a valid date",IF($C1506="","Pick a category",IF(OR($H1506="Unknown category",$H1506=""),"Category has no cost type",IF(NOT(ISNUMBER($E1506)),"Enter an amount","OK")))))

Sheet Monthly Report
B2: Monthly Report | S2: NoviraNest
B3: Profit & loss by month for the reporting year, plus the selected-period summary that feeds the Dashboard. Everything here is automatic.
B4: › Start Here | D4: › Dashboard | F4: › Settings
B6: ="Year "&cfg_Year | E6: SALES & GROSS PROFIT | J6: WASTE & OPERATING EXPENSES | P6: BOTTOM LINE | R6: INFO ONLY
B7: Month | C7: Start | D7: End | E7: ="Revenue ("&cfg_Symbol&")" | F7: Items sold | G7: ="COGS ("&cfg_Symbol&")" | H7: ="Gross profit ("&cfg_Symbol&")" | I7: Gross margin | J7: ="Waste ("&cfg_Symbol&")" | K7: ="Fixed costs ("&cfg_Symbol&")" | L7: ="Labour ("&cfg_Symbol&")" | M7: ="Event fees ("&cfg_Symbol&")" | N7: ="Other variable ("&cfg_Symbol&")" | O7: ="Total opex ("&cfg_Symbol&")" | P7: ="NET PROFIT ("&cfg_Symbol&")" | Q7: Net margin | R7: ="Stock purchases ("&cfg_Symbol&")" | S7: ="Ingredient part of COGS ("&cfg_Symbol&")"
B8: =TEXT(C8,"mmm") | C8: =DATE(cfg_Year,1,1) | D8: =EOMONTH(C8,0) | E8: =SUMIFS('Sales Log'!$I$7:$I$3006,'Sales Log'!$B$7:$B$3006,">="&$C8,'Sales Log'!$B$7:$B$3006,"<="&$D8,'Sales Log'!$N$7:$N$3006,"OK") | F8: =SUMIFS('Sales Log'!$D$7:$D$3006,'Sales Log'!$B$7:$B$3006,">="&$C8,'Sales Log'!$B$7:$B$3006,"<="&$D8,'Sales Log'!$N$7:$N$3006,"OK") | G8: =SUMIFS('Sales Log'!$K$7:$K$3006,'Sales Log'!$B$7:$B$3006,">="&$C8,'Sales Log'!$B$7:$B$3006,"<="&$D8,'Sales Log'!$N$7:$N$3006,"OK") | H8: =E8-G8 | I8: =IF(E8=0,"",H8/E8) | J8: =SUMIFS('Waste Log'!$J$7:$J$506,'Waste Log'!$B$7:$B$506,">="&$C8,'Waste Log'!$B$7:$B$506,"<="&$D8) | K8: =SUMIFS('Expenses'!$E$7:$E$1506,'Expenses'!$B$7:$B$1506,">="&$C8,'Expenses'!$B$7:$B$1506,"<="&$D8,'Expenses'!$H$7:$H$1506,"Fixed") | L8: =SUMIFS('Expenses'!$E$7:$E$1506,'Expenses'!$B$7:$B$1506,">="&$C8,'Expenses'!$B$7:$B$1506,"<="&$D8,'Expenses'!$H$7:$H$1506,"Labor") | M8: =SUMIFS('Expenses'!$E$7:$E$1506,'Expenses'!$B$7:$B$1506,">="&$C8,'Expenses'!$B$7:$B$1506,"<="&$D8,'Expenses'!$H$7:$H$1506,"Event Fees") | N8: =SUMIFS('Expenses'!$E$7:$E$1506,'Expenses'!$B$7:$B$1506,">="&$C8,'Expenses'!$B$7:$B$1506,"<="&$D8,'Expenses'!$H$7:$H$1506,"Variable") | O8: =SUM(K8:N8) | P8: =H8-J8-O8 | Q8: =IF(E8=0,"",P8/E8) | R8: =SUMIFS('Expenses'!$E$7:$E$1506,'Expenses'!$B$7:$B$1506,">="&$C8,'Expenses'!$B$7:$B$1506,"<="&$D8,'Expenses'!$H$7:$H$1506,"Excluded - Stock Purchase") | S8: =SUMIFS('Sales Log'!$M$7:$M$3006,'Sales Log'!$B$7:$B$3006,">="&$C8,'Sales Log'!$B$7:$B$3006,"<="&$D8,'Sales Log'!$N$7:$N$3006,"OK")
B9: =TEXT(C9,"mmm") | C9: =DATE(cfg_Year,2,1) | D9: =EOMONTH(C9,0) | E9: =SUMIFS('Sales Log'!$I$7:$I$3006,'Sales Log'!$B$7:$B$3006,">="&$C9,'Sales Log'!$B$7:$B$3006,"<="&$D9,'Sales Log'!$N$7:$N$3006,"OK") | F9: =SUMIFS('Sales Log'!$D$7:$D$3006,'Sales Log'!$B$7:$B$3006,">="&$C9,'Sales Log'!$B$7:$B$3006,"<="&$D9,'Sales Log'!$N$7:$N$3006,"OK") | G9: =SUMIFS('Sales Log'!$K$7:$K$3006,'Sales Log'!$B$7:$B$3006,">="&$C9,'Sales Log'!$B$7:$B$3006,"<="&$D9,'Sales Log'!$N$7:$N$3006,"OK") | H9: =E9-G9 | I9: =IF(E9=0,"",H9/E9) | J9: =SUMIFS('Waste Log'!$J$7:$J$506,'Waste Log'!$B$7:$B$506,">="&$C9,'Waste Log'!$B$7:$B$506,"<="&$D9) | K9: =SUMIFS('Expenses'!$E$7:$E$1506,'Expenses'!$B$7:$B$1506,">="&$C9,'Expenses'!$B$7:$B$1506,"<="&$D9,'Expenses'!$H$7:$H$1506,"Fixed") | L9: =SUMIFS('Expenses'!$E$7:$E$1506,'Expenses'!$B$7:$B$1506,">="&$C9,'Expenses'!$B$7:$B$1506,"<="&$D9,'Expenses'!$H$7:$H$1506,"Labor") | M9: =SUMIFS('Expenses'!$E$7:$E$1506,'Expenses'!$B$7:$B$1506,">="&$C9,'Expenses'!$B$7:$B$1506,"<="&$D9,'Expenses'!$H$7:$H$1506,"Event Fees") | N9: =SUMIFS('Expenses'!$E$7:$E$1506,'Expenses'!$B$7:$B$1506,">="&$C9,'Expenses'!$B$7:$B$1506,"<="&$D9,'Expenses'!$H$7:$H$1506,"Variable") | O9: =SUM(K9:N9) | P9: =H9-J9-O9 | Q9: =IF(E9=0,"",P9/E9) | R9: =SUMIFS('Expenses'!$E$7:$E$1506,'Expenses'!$B$7:$B$1506,">="&$C9,'Expenses'!$B$7:$B$1506,"<="&$D9,'Expenses'!$H$7:$H$1506,"Excluded - Stock Purchase") | S9: =SUMIFS('Sales Log'!$M$7:$M$3006,'Sales Log'!$B$7:$B$3006,">="&$C9,'Sales Log'!$B$7:$B$3006,"<="&$D9,'Sales Log'!$N$7:$N$3006,"OK")
B10: =TEXT(C10,"mmm") | C10: =DATE(cfg_Year,3,1) | D10: =EOMONTH(C10,0) | E10: =SUMIFS('Sales Log'!$I$7:$I$3006,'Sales Log'!$B$7:$B$3006,">="&$C10,'Sales Log'!$B$7:$B$3006,"<="&$D10,'Sales Log'!$N$7:$N$3006,"OK") | F10: =SUMIFS('Sales Log'!$D$7:$D$3006,'Sales Log'!$B$7:$B$3006,">="&$C10,'Sales Log'!$B$7:$B$3006,"<="&$D10,'Sales Log'!$N$7:$N$3006,"OK") | G10: =SUMIFS('Sales Log'!$K$7:$K$3006,'Sales Log'!$B$7:$B$3006,">="&$C10,'Sales Log'!$B$7:$B$3006,"<="&$D10,'Sales Log'!$N$7:$N$3006,"OK") | H10: =E10-G10 | I10: =IF(E10=0,"",H10/E10) | J10: =SUMIFS('Waste Log'!$J$7:$J$506,'Waste Log'!$B$7:$B$506,">="&$C10,'Waste Log'!$B$7:$B$506,"<="&$D10) | K10: =SUMIFS('Expenses'!$E$7:$E$1506,'Expenses'!$B$7:$B$1506,">="&$C10,'Expenses'!$B$7:$B$1506,"<="&$D10,'Expenses'!$H$7:$H$1506,"Fixed") | L10: =SUMIFS('Expenses'!$E$7:$E$1506,'Expenses'!$B$7:$B$1506,">="&$C10,'Expenses'!$B$7:$B$1506,"<="&$D10,'Expenses'!$H$7:$H$1506,"Labor") | M10: =SUMIFS('Expenses'!$E$7:$E$1506,'Expenses'!$B$7:$B$1506,">="&$C10,'Expenses'!$B$7:$B$1506,"<="&$D10,'Expenses'!$H$7:$H$1506,"Event Fees") | N10: =SUMIFS('Expenses'!$E$7:$E$1506,'Expenses'!$B$7:$B$1506,">="&$C10,'Expenses'!$B$7:$B$1506,"<="&$D10,'Expenses'!$H$7:$H$1506,"Variable") | O10: =SUM(K10:N10) | P10: =H10-J10-O10 | Q10: =IF(E10=0,"",P10/E10) | R10: =SUMIFS('Expenses'!$E$7:$E$1506,'Expenses'!$B$7:$B$1506,">="&$C10,'Expenses'!$B$7:$B$1506,"<="&$D10,'Expenses'!$H$7:$H$1506,"Excluded - Stock Purchase") | S10: =SUMIFS('Sales Log'!$M$7:$M$3006,'Sales Log'!$B$7:$B$3006,">="&$C10,'Sales Log'!$B$7:$B$3006,"<="&$D10,'Sales Log'!$N$7:$N$3006,"OK")
B11: =TEXT(C11,"mmm") | C11: =DATE(cfg_Year,4,1) | D11: =EOMONTH(C11,0) | E11: =SUMIFS('Sales Log'!$I$7:$I$3006,'Sales Log'!$B$7:$B$3006,">="&$C11,'Sales Log'!$B$7:$B$3006,"<="&$D11,'Sales Log'!$N$7:$N$3006,"OK") | F11: =SUMIFS('Sales Log'!$D$7:$D$3006,'Sales Log'!$B$7:$B$3006,">="&$C11,'Sales Log'!$B$7:$B$3006,"<="&$D11,'Sales Log'!$N$7:$N$3006,"OK") | G11: =SUMIFS('Sales Log'!$K$7:$K$3006,'Sales Log'!$B$7:$B$3006,">="&$C11,'Sales Log'!$B$7:$B$3006,"<="&$D11,'Sales Log'!$N$7:$N$3006,"OK") | H11: =E11-G11 | I11: =IF(E11=0,"",H11/E11) | J11: =SUMIFS('Waste Log'!$J$7:$J$506,'Waste Log'!$B$7:$B$506,">="&$C11,'Waste Log'!$B$7:$B$506,"<="&$D11) | K11: =SUMIFS('Expenses'!$E$7:$E$1506,'Expenses'!$B$7:$B$1506,">="&$C11,'Expenses'!$B$7:$B$1506,"<="&$D11,'Expenses'!$H$7:$H$1506,"Fixed") | L11: =SUMIFS('Expenses'!$E$7:$E$1506,'Expenses'!$B$7:$B$1506,">="&$C11,'Expenses'!$B$7:$B$1506,"<="&$D11,'Expenses'!$H$7:$H$1506,"Labor") | M11: =SUMIFS('Expenses'!$E$7:$E$1506,'Expenses'!$B$7:$B$1506,">="&$C11,'Expenses'!$B$7:$B$1506,"<="&$D11,'Expenses'!$H$7:$H$1506,"Event Fees") | N11: =SUMIFS('Expenses'!$E$7:$E$1506,'Expenses'!$B$7:$B$1506,">="&$C11,'Expenses'!$B$7:$B$1506,"<="&$D11,'Expenses'!$H$7:$H$1506,"Variable") | O11: =SUM(K11:N11) | P11: =H11-J11-O11 | Q11: =IF(E11=0,"",P11/E11) | R11: =SUMIFS('Expenses'!$E$7:$E$1506,'Expenses'!$B$7:$B$1506,">="&$C11,'Expenses'!$B$7:$B$1506,"<="&$D11,'Expenses'!$H$7:$H$1506,"Excluded - Stock Purchase") | S11: =SUMIFS('Sales Log'!$M$7:$M$3006,'Sales Log'!$B$7:$B$3006,">="&$C11,'Sales Log'!$B$7:$B$3006,"<="&$D11,'Sales Log'!$N$7:$N$3006,"OK")
B12: =TEXT(C12,"mmm") | C12: =DATE(cfg_Year,5,1) | D12: =EOMONTH(C12,0) | E12: =SUMIFS('Sales Log'!$I$7:$I$3006,'Sales Log'!$B$7:$B$3006,">="&$C12,'Sales Log'!$B$7:$B$3006,"<="&$D12,'Sales Log'!$N$7:$N$3006,"OK") | F12: =SUMIFS('Sales Log'!$D$7:$D$3006,'Sales Log'!$B$7:$B$3006,">="&$C12,'Sales Log'!$B$7:$B$3006,"<="&$D12,'Sales Log'!$N$7:$N$3006,"OK") | G12: =SUMIFS('Sales Log'!$K$7:$K$3006,'Sales Log'!$B$7:$B$3006,">="&$C12,'Sales Log'!$B$7:$B$3006,"<="&$D12,'Sales Log'!$N$7:$N$3006,"OK") | H12: =E12-G12 | I12: =IF(E12=0,"",H12/E12) | J12: =SUMIFS('Waste Log'!$J$7:$J$506,'Waste Log'!$B$7:$B$506,">="&$C12,'Waste Log'!$B$7:$B$506,"<="&$D12) | K12: =SUMIFS('Expenses'!$E$7:$E$1506,'Expenses'!$B$7:$B$1506,">="&$C12,'Expenses'!$B$7:$B$1506,"<="&$D12,'Expenses'!$H$7:$H$1506,"Fixed") | L12: =SUMIFS('Expenses'!$E$7:$E$1506,'Expenses'!$B$7:$B$1506,">="&$C12,'Expenses'!$B$7:$B$1506,"<="&$D12,'Expenses'!$H$7:$H$1506,"Labor") | M12: =SUMIFS('Expenses'!$E$7:$E$1506,'Expenses'!$B$7:$B$1506,">="&$C12,'Expenses'!$B$7:$B$1506,"<="&$D12,'Expenses'!$H$7:$H$1506,"Event Fees") | N12: =SUMIFS('Expenses'!$E$7:$E$1506,'Expenses'!$B$7:$B$1506,">="&$C12,'Expenses'!$B$7:$B$1506,"<="&$D12,'Expenses'!$H$7:$H$1506,"Variable") | O12: =SUM(K12:N12) | P12: =H12-J12-O12 | Q12: =IF(E12=0,"",P12/E12) | R12: =SUMIFS('Expenses'!$E$7:$E$1506,'Expenses'!$B$7:$B$1506,">="&$C12,'Expenses'!$B$7:$B$1506,"<="&$D12,'Expenses'!$H$7:$H$1506,"Excluded - Stock Purchase") | S12: =SUMIFS('Sales Log'!$M$7:$M$3006,'Sales Log'!$B$7:$B$3006,">="&$C12,'Sales Log'!$B$7:$B$3006,"<="&$D12,'Sales Log'!$N$7:$N$3006,"OK")
B13: =TEXT(C13,"mmm") | C13: =DATE(cfg_Year,6,1) | D13: =EOMONTH(C13,0) | E13: =SUMIFS('Sales Log'!$I$7:$I$3006,'Sales Log'!$B$7:$B$3006,">="&$C13,'Sales Log'!$B$7:$B$3006,"<="&$D13,'Sales Log'!$N$7:$N$3006,"OK") | F13: =SUMIFS('Sales Log'!$D$7:$D$3006,'Sales Log'!$B$7:$B$3006,">="&$C13,'Sales Log'!$B$7:$B$3006,"<="&$D13,'Sales Log'!$N$7:$N$3006,"OK") | G13: =SUMIFS('Sales Log'!$K$7:$K$3006,'Sales Log'!$B$7:$B$3006,">="&$C13,'Sales Log'!$B$7:$B$3006,"<="&$D13,'Sales Log'!$N$7:$N$3006,"OK") | H13: =E13-G13 | I13: =IF(E13=0,"",H13/E13) | J13: =SUMIFS('Waste Log'!$J$7:$J$506,'Waste Log'!$B$7:$B$506,">="&$C13,'Waste Log'!$B$7:$B$506,"<="&$D13) | K13: =SUMIFS('Expenses'!$E$7:$E$1506,'Expenses'!$B$7:$B$1506,">="&$C13,'Expenses'!$B$7:$B$1506,"<="&$D13,'Expenses'!$H$7:$H$1506,"Fixed") | L13: =SUMIFS('Expenses'!$E$7:$E$1506,'Expenses'!$B$7:$B$1506,">="&$C13,'Expenses'!$B$7:$B$1506,"<="&$D13,'Expenses'!$H$7:$H$1506,"Labor") | M13: =SUMIFS('Expenses'!$E$7:$E$1506,'Expenses'!$B$7:$B$1506,">="&$C13,'Expenses'!$B$7:$B$1506,"<="&$D13,'Expenses'!$H$7:$H$1506,"Event Fees") | N13: =SUMIFS('Expenses'!$E$7:$E$1506,'Expenses'!$B$7:$B$1506,">="&$C13,'Expenses'!$B$7:$B$1506,"<="&$D13,'Expenses'!$H$7:$H$1506,"Variable") | O13: =SUM(K13:N13) | P13: =H13-J13-O13 | Q13: =IF(E13=0,"",P13/E13) | R13: =SUMIFS('Expenses'!$E$7:$E$1506,'Expenses'!$B$7:$B$1506,">="&$C13,'Expenses'!$B$7:$B$1506,"<="&$D13,'Expenses'!$H$7:$H$1506,"Excluded - Stock Purchase") | S13: =SUMIFS('Sales Log'!$M$7:$M$3006,'Sales Log'!$B$7:$B$3006,">="&$C13,'Sales Log'!$B$7:$B$3006,"<="&$D13,'Sales Log'!$N$7:$N$3006,"OK")
B14: =TEXT(C14,"mmm") | C14: =DATE(cfg_Year,7,1) | D14: =EOMONTH(C14,0) | E14: =SUMIFS('Sales Log'!$I$7:$I$3006,'Sales Log'!$B$7:$B$3006,">="&$C14,'Sales Log'!$B$7:$B$3006,"<="&$D14,'Sales Log'!$N$7:$N$3006,"OK") | F14: =SUMIFS('Sales Log'!$D$7:$D$3006,'Sales Log'!$B$7:$B$3006,">="&$C14,'Sales Log'!$B$7:$B$3006,"<="&$D14,'Sales Log'!$N$7:$N$3006,"OK") | G14: =SUMIFS('Sales Log'!$K$7:$K$3006,'Sales Log'!$B$7:$B$3006,">="&$C14,'Sales Log'!$B$7:$B$3006,"<="&$D14,'Sales Log'!$N$7:$N$3006,"OK") | H14: =E14-G14 | I14: =IF(E14=0,"",H14/E14) | J14: =SUMIFS('Waste Log'!$J$7:$J$506,'Waste Log'!$B$7:$B$506,">="&$C14,'Waste Log'!$B$7:$B$506,"<="&$D14) | K14: =SUMIFS('Expenses'!$E$7:$E$1506,'Expenses'!$B$7:$B$1506,">="&$C14,'Expenses'!$B$7:$B$1506,"<="&$D14,'Expenses'!$H$7:$H$1506,"Fixed") | L14: =SUMIFS('Expenses'!$E$7:$E$1506,'Expenses'!$B$7:$B$1506,">="&$C14,'Expenses'!$B$7:$B$1506,"<="&$D14,'Expenses'!$H$7:$H$1506,"Labor") | M14: =SUMIFS('Expenses'!$E$7:$E$1506,'Expenses'!$B$7:$B$1506,">="&$C14,'Expenses'!$B$7:$B$1506,"<="&$D14,'Expenses'!$H$7:$H$1506,"Event Fees") | N14: =SUMIFS('Expenses'!$E$7:$E$1506,'Expenses'!$B$7:$B$1506,">="&$C14,'Expenses'!$B$7:$B$1506,"<="&$D14,'Expenses'!$H$7:$H$1506,"Variable") | O14: =SUM(K14:N14) | P14: =H14-J14-O14 | Q14: =IF(E14=0,"",P14/E14) | R14: =SUMIFS('Expenses'!$E$7:$E$1506,'Expenses'!$B$7:$B$1506,">="&$C14,'Expenses'!$B$7:$B$1506,"<="&$D14,'Expenses'!$H$7:$H$1506,"Excluded - Stock Purchase") | S14: =SUMIFS('Sales Log'!$M$7:$M$3006,'Sales Log'!$B$7:$B$3006,">="&$C14,'Sales Log'!$B$7:$B$3006,"<="&$D14,'Sales Log'!$N$7:$N$3006,"OK")
B15: =TEXT(C15,"mmm") | C15: =DATE(cfg_Year,8,1) | D15: =EOMONTH(C15,0) | E15: =SUMIFS('Sales Log'!$I$7:$I$3006,'Sales Log'!$B$7:$B$3006,">="&$C15,'Sales Log'!$B$7:$B$3006,"<="&$D15,'Sales Log'!$N$7:$N$3006,"OK") | F15: =SUMIFS('Sales Log'!$D$7:$D$3006,'Sales Log'!$B$7:$B$3006,">="&$C15,'Sales Log'!$B$7:$B$3006,"<="&$D15,'Sales Log'!$N$7:$N$3006,"OK") | G15: =SUMIFS('Sales Log'!$K$7:$K$3006,'Sales Log'!$B$7:$B$3006,">="&$C15,'Sales Log'!$B$7:$B$3006,"<="&$D15,'Sales Log'!$N$7:$N$3006,"OK") | H15: =E15-G15 | I15: =IF(E15=0,"",H15/E15) | J15: =SUMIFS('Waste Log'!$J$7:$J$506,'Waste Log'!$B$7:$B$506,">="&$C15,'Waste Log'!$B$7:$B$506,"<="&$D15) | K15: =SUMIFS('Expenses'!$E$7:$E$1506,'Expenses'!$B$7:$B$1506,">="&$C15,'Expenses'!$B$7:$B$1506,"<="&$D15,'Expenses'!$H$7:$H$1506,"Fixed") | L15: =SUMIFS('Expenses'!$E$7:$E$1506,'Expenses'!$B$7:$B$1506,">="&$C15,'Expenses'!$B$7:$B$1506,"<="&$D15,'Expenses'!$H$7:$H$1506,"Labor") | M15: =SUMIFS('Expenses'!$E$7:$E$1506,'Expenses'!$B$7:$B$1506,">="&$C15,'Expenses'!$B$7:$B$1506,"<="&$D15,'Expenses'!$H$7:$H$1506,"Event Fees") | N15: =SUMIFS('Expenses'!$E$7:$E$1506,'Expenses'!$B$7:$B$1506,">="&$C15,'Expenses'!$B$7:$B$1506,"<="&$D15,'Expenses'!$H$7:$H$1506,"Variable") | O15: =SUM(K15:N15) | P15: =H15-J15-O15 | Q15: =IF(E15=0,"",P15/E15) | R15: =SUMIFS('Expenses'!$E$7:$E$1506,'Expenses'!$B$7:$B$1506,">="&$C15,'Expenses'!$B$7:$B$1506,"<="&$D15,'Expenses'!$H$7:$H$1506,"Excluded - Stock Purchase") | S15: =SUMIFS('Sales Log'!$M$7:$M$3006,'Sales Log'!$B$7:$B$3006,">="&$C15,'Sales Log'!$B$7:$B$3006,"<="&$D15,'Sales Log'!$N$7:$N$3006,"OK")
B16: =TEXT(C16,"mmm") | C16: =DATE(cfg_Year,9,1) | D16: =EOMONTH(C16,0) | E16: =SUMIFS('Sales Log'!$I$7:$I$3006,'Sales Log'!$B$7:$B$3006,">="&$C16,'Sales Log'!$B$7:$B$3006,"<="&$D16,'Sales Log'!$N$7:$N$3006,"OK") | F16: =SUMIFS('Sales Log'!$D$7:$D$3006,'Sales Log'!$B$7:$B$3006,">="&$C16,'Sales Log'!$B$7:$B$3006,"<="&$D16,'Sales Log'!$N$7:$N$3006,"OK") | G16: =SUMIFS('Sales Log'!$K$7:$K$3006,'Sales Log'!$B$7:$B$3006,">="&$C16,'Sales Log'!$B$7:$B$3006,"<="&$D16,'Sales Log'!$N$7:$N$3006,"OK") | H16: =E16-G16 | I16: =IF(E16=0,"",H16/E16) | J16: =SUMIFS('Waste Log'!$J$7:$J$506,'Waste Log'!$B$7:$B$506,">="&$C16,'Waste Log'!$B$7:$B$506,"<="&$D16) | K16: =SUMIFS('Expenses'!$E$7:$E$1506,'Expenses'!$B$7:$B$1506,">="&$C16,'Expenses'!$B$7:$B$1506,"<="&$D16,'Expenses'!$H$7:$H$1506,"Fixed") | L16: =SUMIFS('Expenses'!$E$7:$E$1506,'Expenses'!$B$7:$B$1506,">="&$C16,'Expenses'!$B$7:$B$1506,"<="&$D16,'Expenses'!$H$7:$H$1506,"Labor") | M16: =SUMIFS('Expenses'!$E$7:$E$1506,'Expenses'!$B$7:$B$1506,">="&$C16,'Expenses'!$B$7:$B$1506,"<="&$D16,'Expenses'!$H$7:$H$1506,"Event Fees") | N16: =SUMIFS('Expenses'!$E$7:$E$1506,'Expenses'!$B$7:$B$1506,">="&$C16,'Expenses'!$B$7:$B$1506,"<="&$D16,'Expenses'!$H$7:$H$1506,"Variable") | O16: =SUM(K16:N16) | P16: =H16-J16-O16 | Q16: =IF(E16=0,"",P16/E16) | R16: =SUMIFS('Expenses'!$E$7:$E$1506,'Expenses'!$B$7:$B$1506,">="&$C16,'Expenses'!$B$7:$B$1506,"<="&$D16,'Expenses'!$H$7:$H$1506,"Excluded - Stock Purchase") | S16: =SUMIFS('Sales Log'!$M$7:$M$3006,'Sales Log'!$B$7:$B$3006,">="&$C16,'Sales Log'!$B$7:$B$3006,"<="&$D16,'Sales Log'!$N$7:$N$3006,"OK")
B17: =TEXT(C17,"mmm") | C17: =DATE(cfg_Year,10,1) | D17: =EOMONTH(C17,0) | E17: =SUMIFS('Sales Log'!$I$7:$I$3006,'Sales Log'!$B$7:$B$3006,">="&$C17,'Sales Log'!$B$7:$B$3006,"<="&$D17,'Sales Log'!$N$7:$N$3006,"OK") | F17: =SUMIFS('Sales Log'!$D$7:$D$3006,'Sales Log'!$B$7:$B$3006,">="&$C17,'Sales Log'!$B$7:$B$3006,"<="&$D17,'Sales Log'!$N$7:$N$3006,"OK") | G17: =SUMIFS('Sales Log'!$K$7:$K$3006,'Sales Log'!$B$7:$B$3006,">="&$C17,'Sales Log'!$B$7:$B$3006,"<="&$D17,'Sales Log'!$N$7:$N$3006,"OK") | H17: =E17-G17 | I17: =IF(E17=0,"",H17/E17) | J17: =SUMIFS('Waste Log'!$J$7:$J$506,'Waste Log'!$B$7:$B$506,">="&$C17,'Waste Log'!$B$7:$B$506,"<="&$D17) | K17: =SUMIFS('Expenses'!$E$7:$E$1506,'Expenses'!$B$7:$B$1506,">="&$C17,'Expenses'!$B$7:$B$1506,"<="&$D17,'Expenses'!$H$7:$H$1506,"Fixed") | L17: =SUMIFS('Expenses'!$E$7:$E$1506,'Expenses'!$B$7:$B$1506,">="&$C17,'Expenses'!$B$7:$B$1506,"<="&$D17,'Expenses'!$H$7:$H$1506,"Labor") | M17: =SUMIFS('Expenses'!$E$7:$E$1506,'Expenses'!$B$7:$B$1506,">="&$C17,'Expenses'!$B$7:$B$1506,"<="&$D17,'Expenses'!$H$7:$H$1506,"Event Fees") | N17: =SUMIFS('Expenses'!$E$7:$E$1506,'Expenses'!$B$7:$B$1506,">="&$C17,'Expenses'!$B$7:$B$1506,"<="&$D17,'Expenses'!$H$7:$H$1506,"Variable") | O17: =SUM(K17:N17) | P17: =H17-J17-O17 | Q17: =IF(E17=0,"",P17/E17) | R17: =SUMIFS('Expenses'!$E$7:$E$1506,'Expenses'!$B$7:$B$1506,">="&$C17,'Expenses'!$B$7:$B$1506,"<="&$D17,'Expenses'!$H$7:$H$1506,"Excluded - Stock Purchase") | S17: =SUMIFS('Sales Log'!$M$7:$M$3006,'Sales Log'!$B$7:$B$3006,">="&$C17,'Sales Log'!$B$7:$B$3006,"<="&$D17,'Sales Log'!$N$7:$N$3006,"OK")
B18: =TEXT(C18,"mmm") | C18: =DATE(cfg_Year,11,1) | D18: =EOMONTH(C18,0) | E18: =SUMIFS('Sales Log'!$I$7:$I$3006,'Sales Log'!$B$7:$B$3006,">="&$C18,'Sales Log'!$B$7:$B$3006,"<="&$D18,'Sales Log'!$N$7:$N$3006,"OK") | F18: =SUMIFS('Sales Log'!$D$7:$D$3006,'Sales Log'!$B$7:$B$3006,">="&$C18,'Sales Log'!$B$7:$B$3006,"<="&$D18,'Sales Log'!$N$7:$N$3006,"OK") | G18: =SUMIFS('Sales Log'!$K$7:$K$3006,'Sales Log'!$B$7:$B$3006,">="&$C18,'Sales Log'!$B$7:$B$3006,"<="&$D18,'Sales Log'!$N$7:$N$3006,"OK") | H18: =E18-G18 | I18: =IF(E18=0,"",H18/E18) | J18: =SUMIFS('Waste Log'!$J$7:$J$506,'Waste Log'!$B$7:$B$506,">="&$C18,'Waste Log'!$B$7:$B$506,"<="&$D18) | K18: =SUMIFS('Expenses'!$E$7:$E$1506,'Expenses'!$B$7:$B$1506,">="&$C18,'Expenses'!$B$7:$B$1506,"<="&$D18,'Expenses'!$H$7:$H$1506,"Fixed") | L18: =SUMIFS('Expenses'!$E$7:$E$1506,'Expenses'!$B$7:$B$1506,">="&$C18,'Expenses'!$B$7:$B$1506,"<="&$D18,'Expenses'!$H$7:$H$1506,"Labor") | M18: =SUMIFS('Expenses'!$E$7:$E$1506,'Expenses'!$B$7:$B$1506,">="&$C18,'Expenses'!$B$7:$B$1506,"<="&$D18,'Expenses'!$H$7:$H$1506,"Event Fees") | N18: =SUMIFS('Expenses'!$E$7:$E$1506,'Expenses'!$B$7:$B$1506,">="&$C18,'Expenses'!$B$7:$B$1506,"<="&$D18,'Expenses'!$H$7:$H$1506,"Variable") | O18: =SUM(K18:N18) | P18: =H18-J18-O18 | Q18: =IF(E18=0,"",P18/E18) | R18: =SUMIFS('Expenses'!$E$7:$E$1506,'Expenses'!$B$7:$B$1506,">="&$C18,'Expenses'!$B$7:$B$1506,"<="&$D18,'Expenses'!$H$7:$H$1506,"Excluded - Stock Purchase") | S18: =SUMIFS('Sales Log'!$M$7:$M$3006,'Sales Log'!$B$7:$B$3006,">="&$C18,'Sales Log'!$B$7:$B$3006,"<="&$D18,'Sales Log'!$N$7:$N$3006,"OK")
B19: =TEXT(C19,"mmm") | C19: =DATE(cfg_Year,12,1) | D19: =EOMONTH(C19,0) | E19: =SUMIFS('Sales Log'!$I$7:$I$3006,'Sales Log'!$B$7:$B$3006,">="&$C19,'Sales Log'!$B$7:$B$3006,"<="&$D19,'Sales Log'!$N$7:$N$3006,"OK") | F19: =SUMIFS('Sales Log'!$D$7:$D$3006,'Sales Log'!$B$7:$B$3006,">="&$C19,'Sales Log'!$B$7:$B$3006,"<="&$D19,'Sales Log'!$N$7:$N$3006,"OK") | G19: =SUMIFS('Sales Log'!$K$7:$K$3006,'Sales Log'!$B$7:$B$3006,">="&$C19,'Sales Log'!$B$7:$B$3006,"<="&$D19,'Sales Log'!$N$7:$N$3006,"OK") | H19: =E19-G19 | I19: =IF(E19=0,"",H19/E19) | J19: =SUMIFS('Waste Log'!$J$7:$J$506,'Waste Log'!$B$7:$B$506,">="&$C19,'Waste Log'!$B$7:$B$506,"<="&$D19) | K19: =SUMIFS('Expenses'!$E$7:$E$1506,'Expenses'!$B$7:$B$1506,">="&$C19,'Expenses'!$B$7:$B$1506,"<="&$D19,'Expenses'!$H$7:$H$1506,"Fixed") | L19: =SUMIFS('Expenses'!$E$7:$E$1506,'Expenses'!$B$7:$B$1506,">="&$C19,'Expenses'!$B$7:$B$1506,"<="&$D19,'Expenses'!$H$7:$H$1506,"Labor") | M19: =SUMIFS('Expenses'!$E$7:$E$1506,'Expenses'!$B$7:$B$1506,">="&$C19,'Expenses'!$B$7:$B$1506,"<="&$D19,'Expenses'!$H$7:$H$1506,"Event Fees") | N19: =SUMIFS('Expenses'!$E$7:$E$1506,'Expenses'!$B$7:$B$1506,">="&$C19,'Expenses'!$B$7:$B$1506,"<="&$D19,'Expenses'!$H$7:$H$1506,"Variable") | O19: =SUM(K19:N19) | P19: =H19-J19-O19 | Q19: =IF(E19=0,"",P19/E19) | R19: =SUMIFS('Expenses'!$E$7:$E$1506,'Expenses'!$B$7:$B$1506,">="&$C19,'Expenses'!$B$7:$B$1506,"<="&$D19,'Expenses'!$H$7:$H$1506,"Excluded - Stock Purchase") | S19: =SUMIFS('Sales Log'!$M$7:$M$3006,'Sales Log'!$B$7:$B$3006,">="&$C19,'Sales Log'!$B$7:$B$3006,"<="&$D19,'Sales Log'!$N$7:$N$3006,"OK")
B20: ="Total "&cfg_Year | E20: =SUM(E8:E19) | F20: =SUM(F8:F19) | G20: =SUM(G8:G19) | H20: =SUM(H8:H19) | I20: =IF(E20=0,"",H20/E20) | J20: =SUM(J8:J19) | K20: =SUM(K8:K19) | L20: =SUM(L8:L19) | M20: =SUM(M8:M19) | N20: =SUM(N8:N19) | O20: =SUM(O8:O19) | P20: =SUM(P8:P19) | Q20: =IF(E20=0,"",P20/E20) | R20: =SUM(R8:R19) | S20: =SUM(S8:S19)
B21: =IF(E20=0,"No sales recorded for "&cfg_Year&" yet - add rows on the Sales Log.","")
B23: SELECTED PERIOD SUMMARY (feeds the Dashboard) | J23: OPERATING EXPENSES BY CATEGORY (selected period)
B24: =cfg_PeriodLabel | J24: Category | M24: Cost type | N24: ="Amount ("&cfg_Symbol&")" | O24: % of opex
B25: Revenue | G25: =SUMIFS('Sales Log'!$I$7:$I$3006,'Sales Log'!$B$7:$B$3006,">="&cfg_Start,'Sales Log'!$B$7:$B$3006,"<="&cfg_End,'Sales Log'!$N$7:$N$3006,"OK") | J25: =IF(OR('Lists'!$F$6="",LEFT('Lists'!$G$6,8)="Excluded"),"",'Lists'!$F$6) | M25: =IF($J25="","",'Lists'!$G$6) | N25: =IF($J25="","",SUMIFS('Expenses'!$E$7:$E$1506,'Expenses'!$C$7:$C$1506,$J25,'Expenses'!$B$7:$B$1506,">="&cfg_Start,'Expenses'!$B$7:$B$1506,"<="&cfg_End)) | O25: =IF(OR($J25="",$G$35=0),"",$N25/$G$35)
B26: Items sold | G26: =SUMIFS('Sales Log'!$D$7:$D$3006,'Sales Log'!$B$7:$B$3006,">="&cfg_Start,'Sales Log'!$B$7:$B$3006,"<="&cfg_End,'Sales Log'!$N$7:$N$3006,"OK") | J26: =IF(OR('Lists'!$F$7="",LEFT('Lists'!$G$7,8)="Excluded"),"",'Lists'!$F$7) | M26: =IF($J26="","",'Lists'!$G$7) | N26: =IF($J26="","",SUMIFS('Expenses'!$E$7:$E$1506,'Expenses'!$C$7:$C$1506,$J26,'Expenses'!$B$7:$B$1506,">="&cfg_Start,'Expenses'!$B$7:$B$1506,"<="&cfg_End)) | O26: =IF(OR($J26="",$G$35=0),"",$N26/$G$35)
B27: Cost of goods sold (COGS) | G27: =SUMIFS('Sales Log'!$K$7:$K$3006,'Sales Log'!$B$7:$B$3006,">="&cfg_Start,'Sales Log'!$B$7:$B$3006,"<="&cfg_End,'Sales Log'!$N$7:$N$3006,"OK") | J27: =IF(OR('Lists'!$F$8="",LEFT('Lists'!$G$8,8)="Excluded"),"",'Lists'!$F$8) | M27: =IF($J27="","",'Lists'!$G$8) | N27: =IF($J27="","",SUMIFS('Expenses'!$E$7:$E$1506,'Expenses'!$C$7:$C$1506,$J27,'Expenses'!$B$7:$B$1506,">="&cfg_Start,'Expenses'!$B$7:$B$1506,"<="&cfg_End)) | O27: =IF(OR($J27="",$G$35=0),"",$N27/$G$35)
B28: Gross profit | G28: =$G$25-$G$27 | J28: =IF(OR('Lists'!$F$9="",LEFT('Lists'!$G$9,8)="Excluded"),"",'Lists'!$F$9) | M28: =IF($J28="","",'Lists'!$G$9) | N28: =IF($J28="","",SUMIFS('Expenses'!$E$7:$E$1506,'Expenses'!$C$7:$C$1506,$J28,'Expenses'!$B$7:$B$1506,">="&cfg_Start,'Expenses'!$B$7:$B$1506,"<="&cfg_End)) | O28: =IF(OR($J28="",$G$35=0),"",$N28/$G$35)
B29: Gross margin | G29: =IF($G$25=0,"",$G$28/$G$25) | J29: =IF(OR('Lists'!$F$10="",LEFT('Lists'!$G$10,8)="Excluded"),"",'Lists'!$F$10) | M29: =IF($J29="","",'Lists'!$G$10) | N29: =IF($J29="","",SUMIFS('Expenses'!$E$7:$E$1506,'Expenses'!$C$7:$C$1506,$J29,'Expenses'!$B$7:$B$1506,">="&cfg_Start,'Expenses'!$B$7:$B$1506,"<="&cfg_End)) | O29: =IF(OR($J29="",$G$35=0),"",$N29/$G$35)
B30: Waste | G30: =SUMIFS('Waste Log'!$J$7:$J$506,'Waste Log'!$B$7:$B$506,">="&cfg_Start,'Waste Log'!$B$7:$B$506,"<="&cfg_End) | J30: =IF(OR('Lists'!$F$11="",LEFT('Lists'!$G$11,8)="Excluded"),"",'Lists'!$F$11) | M30: =IF($J30="","",'Lists'!$G$11) | N30: =IF($J30="","",SUMIFS('Expenses'!$E$7:$E$1506,'Expenses'!$C$7:$C$1506,$J30,'Expenses'!$B$7:$B$1506,">="&cfg_Start,'Expenses'!$B$7:$B$1506,"<="&cfg_End)) | O30: =IF(OR($J30="",$G$35=0),"",$N30/$G$35)
B31: Fixed costs | G31: =SUMIFS('Expenses'!$E$7:$E$1506,'Expenses'!$B$7:$B$1506,">="&cfg_Start,'Expenses'!$B$7:$B$1506,"<="&cfg_End,'Expenses'!$H$7:$H$1506,"Fixed") | J31: =IF(OR('Lists'!$F$12="",LEFT('Lists'!$G$12,8)="Excluded"),"",'Lists'!$F$12) | M31: =IF($J31="","",'Lists'!$G$12) | N31: =IF($J31="","",SUMIFS('Expenses'!$E$7:$E$1506,'Expenses'!$C$7:$C$1506,$J31,'Expenses'!$B$7:$B$1506,">="&cfg_Start,'Expenses'!$B$7:$B$1506,"<="&cfg_End)) | O31: =IF(OR($J31="",$G$35=0),"",$N31/$G$35)
B32: Labour | G32: =SUMIFS('Expenses'!$E$7:$E$1506,'Expenses'!$B$7:$B$1506,">="&cfg_Start,'Expenses'!$B$7:$B$1506,"<="&cfg_End,'Expenses'!$H$7:$H$1506,"Labor") | J32: =IF(OR('Lists'!$F$13="",LEFT('Lists'!$G$13,8)="Excluded"),"",'Lists'!$F$13) | M32: =IF($J32="","",'Lists'!$G$13) | N32: =IF($J32="","",SUMIFS('Expenses'!$E$7:$E$1506,'Expenses'!$C$7:$C$1506,$J32,'Expenses'!$B$7:$B$1506,">="&cfg_Start,'Expenses'!$B$7:$B$1506,"<="&cfg_End)) | O32: =IF(OR($J32="",$G$35=0),"",$N32/$G$35)
B33: Event fees | G33: =SUMIFS('Expenses'!$E$7:$E$1506,'Expenses'!$B$7:$B$1506,">="&cfg_Start,'Expenses'!$B$7:$B$1506,"<="&cfg_End,'Expenses'!$H$7:$H$1506,"Event Fees") | J33: =IF(OR('Lists'!$F$14="",LEFT('Lists'!$G$14,8)="Excluded"),"",'Lists'!$F$14) | M33: =IF($J33="","",'Lists'!$G$14) | N33: =IF($J33="","",SUMIFS('Expenses'!$E$7:$E$1506,'Expenses'!$C$7:$C$1506,$J33,'Expenses'!$B$7:$B$1506,">="&cfg_Start,'Expenses'!$B$7:$B$1506,"<="&cfg_End)) | O33: =IF(OR($J33="",$G$35=0),"",$N33/$G$35)
B34: Other variable costs | G34: =SUMIFS('Expenses'!$E$7:$E$1506,'Expenses'!$B$7:$B$1506,">="&cfg_Start,'Expenses'!$B$7:$B$1506,"<="&cfg_End,'Expenses'!$H$7:$H$1506,"Variable") | J34: =IF(OR('Lists'!$F$15="",LEFT('Lists'!$G$15,8)="Excluded"),"",'Lists'!$F$15) | M34: =IF($J34="","",'Lists'!$G$15) | N34: =IF($J34="","",SUMIFS('Expenses'!$E$7:$E$1506,'Expenses'!$C$7:$C$1506,$J34,'Expenses'!$B$7:$B$1506,">="&cfg_Start,'Expenses'!$B$7:$B$1506,"<="&cfg_End)) | O34: =IF(OR($J34="",$G$35=0),"",$N34/$G$35)
B35: Total operating expenses | G35: =$G$31+$G$32+$G$33+$G$34 | J35: =IF(OR('Lists'!$F$16="",LEFT('Lists'!$G$16,8)="Excluded"),"",'Lists'!$F$16) | M35: =IF($J35="","",'Lists'!$G$16) | N35: =IF($J35="","",SUMIFS('Expenses'!$E$7:$E$1506,'Expenses'!$C$7:$C$1506,$J35,'Expenses'!$B$7:$B$1506,">="&cfg_Start,'Expenses'!$B$7:$B$1506,"<="&cfg_End)) | O35: =IF(OR($J35="",$G$35=0),"",$N35/$G$35)
B36: NET PROFIT (before tax) | G36: =$G$28-$G$30-$G$35 | J36: =IF(OR('Lists'!$F$17="",LEFT('Lists'!$G$17,8)="Excluded"),"",'Lists'!$F$17) | M36: =IF($J36="","",'Lists'!$G$17) | N36: =IF($J36="","",SUMIFS('Expenses'!$E$7:$E$1506,'Expenses'!$C$7:$C$1506,$J36,'Expenses'!$B$7:$B$1506,">="&cfg_Start,'Expenses'!$B$7:$B$1506,"<="&cfg_End)) | O36: =IF(OR($J36="",$G$35=0),"",$N36/$G$35)
B37: Net margin | G37: =IF($G$25=0,"",$G$36/$G$25) | J37: =IF(OR('Lists'!$F$18="",LEFT('Lists'!$G$18,8)="Excluded"),"",'Lists'!$F$18) | M37: =IF($J37="","",'Lists'!$G$18) | N37: =IF($J37="","",SUMIFS('Expenses'!$E$7:$E$1506,'Expenses'!$C$7:$C$1506,$J37,'Expenses'!$B$7:$B$1506,">="&cfg_Start,'Expenses'!$B$7:$B$1506,"<="&cfg_End)) | O37: =IF(OR($J37="",$G$35=0),"",$N37/$G$35)
B38: Sales entries | G38: =COUNTIFS('Sales Log'!$B$7:$B$3006,">="&cfg_Start,'Sales Log'!$B$7:$B$3006,"<="&cfg_End,'Sales Log'!$N$7:$N$3006,"OK") | J38: =IF(OR('Lists'!$F$19="",LEFT('Lists'!$G$19,8)="Excluded"),"",'Lists'!$F$19) | M38: =IF($J38="","",'Lists'!$G$19) | N38: =IF($J38="","",SUMIFS('Expenses'!$E$7:$E$1506,'Expenses'!$C$7:$C$1506,$J38,'Expenses'!$B$7:$B$1506,">="&cfg_Start,'Expenses'!$B$7:$B$1506,"<="&cfg_End)) | O38: =IF(OR($J38="",$G$35=0),"",$N38/$G$35)
B39: Average price per item | G39: =IF($G$26=0,"",$G$25/$G$26) | J39: =IF(OR('Lists'!$F$20="",LEFT('Lists'!$G$20,8)="Excluded"),"",'Lists'!$F$20) | M39: =IF($J39="","",'Lists'!$G$20) | N39: =IF($J39="","",SUMIFS('Expenses'!$E$7:$E$1506,'Expenses'!$C$7:$C$1506,$J39,'Expenses'!$B$7:$B$1506,">="&cfg_Start,'Expenses'!$B$7:$B$1506,"<="&cfg_End)) | O39: =IF(OR($J39="",$G$35=0),"",$N39/$G$35)
B40: Months with activity | G40: =SUMPRODUCT((($E$8:$E$19>0)+($O$8:$O$19>0)>0)*($C$8:$C$19>=cfg_Start)*($C$8:$C$19<=cfg_End)) | J40: =IF(OR('Lists'!$F$21="",LEFT('Lists'!$G$21,8)="Excluded"),"",'Lists'!$F$21) | M40: =IF($J40="","",'Lists'!$G$21) | N40: =IF($J40="","",SUMIFS('Expenses'!$E$7:$E$1506,'Expenses'!$C$7:$C$1506,$J40,'Expenses'!$B$7:$B$1506,">="&cfg_Start,'Expenses'!$B$7:$B$1506,"<="&cfg_End)) | O40: =IF(OR($J40="",$G$35=0),"",$N40/$G$35)
B41: Average operating expenses per month | G41: =IF($G$40=0,$G$35,$G$35/$G$40) | J41: =IF(OR('Lists'!$F$22="",LEFT('Lists'!$G$22,8)="Excluded"),"",'Lists'!$F$22) | M41: =IF($J41="","",'Lists'!$G$22) | N41: =IF($J41="","",SUMIFS('Expenses'!$E$7:$E$1506,'Expenses'!$C$7:$C$1506,$J41,'Expenses'!$B$7:$B$1506,">="&cfg_Start,'Expenses'!$B$7:$B$1506,"<="&cfg_End)) | O41: =IF(OR($J41="",$G$35=0),"",$N41/$G$35)
B42: Break-even revenue for period | G42: =IF(ISNUMBER('Break-Even'!$H$27),'Break-Even'!$H$27*cfg_Months,"") | J42: =IF(OR('Lists'!$F$23="",LEFT('Lists'!$G$23,8)="Excluded"),"",'Lists'!$F$23) | M42: =IF($J42="","",'Lists'!$G$23) | N42: =IF($J42="","",SUMIFS('Expenses'!$E$7:$E$1506,'Expenses'!$C$7:$C$1506,$J42,'Expenses'!$B$7:$B$1506,">="&cfg_Start,'Expenses'!$B$7:$B$1506,"<="&cfg_End)) | O42: =IF(OR($J42="",$G$35=0),"",$N42/$G$35)
B43: Break-even progress | G43: =IF(OR($G$42="",N($G$42)=0),"",$G$25/$G$42) | J43: =IF(OR('Lists'!$F$24="",LEFT('Lists'!$G$24,8)="Excluded"),"",'Lists'!$F$24) | M43: =IF($J43="","",'Lists'!$G$24) | N43: =IF($J43="","",SUMIFS('Expenses'!$E$7:$E$1506,'Expenses'!$C$7:$C$1506,$J43,'Expenses'!$B$7:$B$1506,">="&cfg_Start,'Expenses'!$B$7:$B$1506,"<="&cfg_End)) | O43: =IF(OR($J43="",$G$35=0),"",$N43/$G$35)
B44: Stock purchases (info only) | G44: =SUMIFS('Expenses'!$E$7:$E$1506,'Expenses'!$B$7:$B$1506,">="&cfg_Start,'Expenses'!$B$7:$B$1506,"<="&cfg_End,'Expenses'!$H$7:$H$1506,"Excluded - Stock Purchase") | J44: =IF(OR('Lists'!$F$25="",LEFT('Lists'!$G$25,8)="Excluded"),"",'Lists'!$F$25) | M44: =IF($J44="","",'Lists'!$G$25) | N44: =IF($J44="","",SUMIFS('Expenses'!$E$7:$E$1506,'Expenses'!$C$7:$C$1506,$J44,'Expenses'!$B$7:$B$1506,">="&cfg_Start,'Expenses'!$B$7:$B$1506,"<="&cfg_End)) | O44: =IF(OR($J44="",$G$35=0),"",$N44/$G$35)
B45: Expense rows needing a fix | G45: =SUMPRODUCT(('Expenses'!$I$7:$I$1506<>"")*('Expenses'!$I$7:$I$1506<>"OK"))
B48: WHERE THE MONEY GOES (selected period) - Dashboard chart source
B49: Food & packaging | G49: =$G$27
B50: Labour | G50: =$G$32
B51: Fixed costs | G51: =$G$31
B52: Other variable | G52: =$G$34
B53: Event fees | G53: =$G$33
B54: Waste | G54: =$G$30
B55: Net profit | G55: =$G$36

Sheet Break-Even
B2: Break-Even Calculator | I2: NoviraNest
B3: How many items you must sell each month to cover your costs - and to hit your profit goal.
B4: › Start Here | C4: › Dashboard | D4: › Monthly Report
B6: 1. MONTHLY FIXED COSTS (budget) | E6: 2. PER-ITEM ECONOMICS
B7: Cost | C7: ="Per month ("&cfg_Symbol&")" | E7: Driver | F7: From your data | G7: Your override | H7: Used
B8: Commissary / parking | E8: Average selling price per item | F8: =IF('Monthly Report'!$F$20>0,'Monthly Report'!$E$20/'Monthly Report'!$F$20,IFERROR(AVERAGEIF('Menu Pricing'!$O$7:$O$56,">0"),"")) | H8: =IF(ISNUMBER(G8),G8,IF(ISNUMBER(F8),F8,0))
B9: Truck loan or lease | E9: Average COGS per item (food + packaging) | F9: =IF('Monthly Report'!$F$20>0,'Monthly Report'!$G$20/'Monthly Report'!$F$20,IFERROR((SUMIFS('Menu Pricing'!$F$7:$F$56,'Menu Pricing'!$O$7:$O$56,">0")+SUMIFS('Menu Pricing'!$G$7:$G$56,'Menu Pricing'!$O$7:$O$56,">0")+SUMIFS('Menu Pricing'!$J$7:$J$56,'Menu Pricing'!$O$7:$O$56,">0"))/COUNTIF('Menu Pricing'!$O$7:$O$56,">0"),"")) | H9: =IF(ISNUMBER(G9),G9,IF(ISNUMBER(F9),F9,0))
B10: Insurance | E10: Other variable costs (% of sales) | F10: - | H10: =IF(ISNUMBER(G10),G10,IF(ISNUMBER(F10),F10,0))
B11: Licences & permits (monthly share) | E11: Service days per month | F11: - | H11: =IF(ISNUMBER(G11),G11,IF(ISNUMBER(F11),F11,0))
B12: POS & software | E12: Target monthly profit | F12: - | H12: =IF(ISNUMBER(G12),G12,IF(ISNUMBER(F12),F12,0))
B13: Phone & internet | E13: Data source: Sales Log for the reporting year; if empty, the average of your menu prices/costs.
B14: Accounting
B15: Marketing
B16: Staff wages (planned) | E16: 3. RESULTS
B17: Fuel, propane & generator | E17: Contribution per item | H17: =H8-H9-H8*H10
B18: Repairs reserve | E18: Contribution margin ratio | H18: =IF(H8<=0,"",H17/H8)
B19: Other | E19: Monthly fixed costs | H19: =C20
B20: Total monthly fixed costs | C20: =SUM(C8:C19) | E20: Break-even items per month | H20: =IF(C20<=0,"",IF(H17<=0,"Not reachable",ROUNDUP(C20/H17,0)))
B21: Actual avg opex / month (Expenses) | C21: =IF(COUNTIF('Monthly Report'!$O$8:$O$19,">0")=0,"",'Monthly Report'!$O$20/COUNTIF('Monthly Report'!$O$8:$O$19,">0")) | E21: Break-even items per service day | H21: =IF(OR(NOT(ISNUMBER(H20)),H11<=0),"",ROUNDUP(H20/H11,0))
E22: Items needed for target profit | H22: =IF(OR(C20+H12<=0,H17<=0),"",ROUNDUP((C20+H12)/H17,0))
B23: Include every monthly cost that does NOT change with each item sold: rent, loan, insurance, planned wages, typical fuel. Do NOT include ingredients or packaging - those are in the cost per item. | E23: Revenue needed for target profit | H23: =IF(NOT(ISNUMBER(H22)),"",(C20+H12)/H18)
E24: Actual average items sold per month | H24: =IF(COUNTIF('Monthly Report'!$F$8:$F$19,">0")=0,"",'Monthly Report'!$F$20/COUNTIF('Monthly Report'!$F$8:$F$19,">0"))
E25: Margin of safety (actual vs break-even) | H25: =IF(OR(NOT(ISNUMBER(H24)),NOT(ISNUMBER(H20)),N(H24)=0),"",(H24-H20)/H24)
E26: Status | H26: =IF(C20<=0,"Enter your monthly fixed costs (section 1)",IF(H8<=0,"Add menu prices or sales first",IF(H17<=0,"Each sale loses money - raise prices or cut item costs",IF(NOT(ISNUMBER(H25)),"Break-even calculated - add sales to compare",IF(H25>=0,"Above break-even by "&TEXT(H25,"0%"),"Below break-even by "&TEXT(-H25,"0%"))))))
E27: Break-even revenue per month | H27: =IF(OR(C20<=0,N(H18)<=0),"",C20/H18)
B29: 4. BREAK-EVEN CHART
B50: CHART DATA (automatic)
B51: Items sold per month | C51: Revenue | E51: Total costs | F51: Fixed costs
B52: =IF(ISNUMBER($H$20),ROUND($H$20*2*0/10,0),0) | C52: =B52*$H$8 | E52: =$C$20+B52*($H$9+$H$8*$H$10) | F52: =$C$20
B53: =IF(ISNUMBER($H$20),ROUND($H$20*2*1/10,0),100) | C53: =B53*$H$8 | E53: =$C$20+B53*($H$9+$H$8*$H$10) | F53: =$C$20
B54: =IF(ISNUMBER($H$20),ROUND($H$20*2*2/10,0),200) | C54: =B54*$H$8 | E54: =$C$20+B54*($H$9+$H$8*$H$10) | F54: =$C$20
B55: =IF(ISNUMBER($H$20),ROUND($H$20*2*3/10,0),300) | C55: =B55*$H$8 | E55: =$C$20+B55*($H$9+$H$8*$H$10) | F55: =$C$20
B56: =IF(ISNUMBER($H$20),ROUND($H$20*2*4/10,0),400) | C56: =B56*$H$8 | E56: =$C$20+B56*($H$9+$H$8*$H$10) | F56: =$C$20
B57: =IF(ISNUMBER($H$20),ROUND($H$20*2*5/10,0),500) | C57: =B57*$H$8 | E57: =$C$20+B57*($H$9+$H$8*$H$10) | F57: =$C$20
B58: =IF(ISNUMBER($H$20),ROUND($H$20*2*6/10,0),600) | C58: =B58*$H$8 | E58: =$C$20+B58*($H$9+$H$8*$H$10) | F58: =$C$20
B59: =IF(ISNUMBER($H$20),ROUND($H$20*2*7/10,0),700) | C59: =B59*$H$8 | E59: =$C$20+B59*($H$9+$H$8*$H$10) | F59: =$C$20
B60: =IF(ISNUMBER($H$20),ROUND($H$20*2*8/10,0),800) | C60: =B60*$H$8 | E60: =$C$20+B60*($H$9+$H$8*$H$10) | F60: =$C$20
B61: =IF(ISNUMBER($H$20),ROUND($H$20*2*9/10,0),900) | C61: =B61*$H$8 | E61: =$C$20+B61*($H$9+$H$8*$H$10) | F61: =$C$20
B62: =IF(ISNUMBER($H$20),ROUND($H$20*2*10/10,0),1000) | C62: =B62*$H$8 | E62: =$C$20+B62*($H$9+$H$8*$H$10) | F62: =$C$20

Sheet Event Predictor
B2: Event Profit Predictor | H2: NoviraNest
B3: Should you book this event? Forecast worst / base / best case, see the break-even order count, then compare with what actually happened.
B4: › Start Here | C4: › Dashboard | D4: › Sales Log
B6: EVENT DETAILS | G6: HOW TO USE 1. Name the event and fill the cream cells. 2. Worst / base / best change only the demand (attendance, buy rate, order value). 3. Check the verdict and the break-even orders before you pay a fee. After the event: log sales on the Sales Log with Location = the exact event name. Actual revenue, items and COGS appear here automatically. Type the actual costs in 'Your entry'.
B7: Event name (= Location in Sales Log)
B8: Event date
B9: Notes
B11: FORECAST - DEMAND (per scenario)
B12: Assumption | C12: Worst case | D12: Base case | E12: Best case
B13: Expected attendance (people at the event)
B14: % of attendees who buy from you
B15: Orders per buying customer
B16: ="Average order value ("&cfg_Symbol&")"
B18: FORECAST - EVENT COSTS (same in every scenario) | G18: FORECAST vs ACTUAL Forecast numbers are estimates and never appear on the Dashboard. To count the event's real costs in your monthly profit, enter them on the Expenses sheet (Event & Pitch Fees, Staff Wages, Fuel...). This sheet only compares - it does not add anything to your totals, so nothing is counted twice.
B19: Event participation / pitch fee
B20: Organiser commission (% of sales)
B21: Card processing (% of sales)
B22: Food & packaging cost (% of sales) | D22: =IFERROR("Your menu average: "&TEXT((SUMIFS('Menu Pricing'!$F$7:$F$56,'Menu Pricing'!$O$7:$O$56,">0")+SUMIFS('Menu Pricing'!$G$7:$G$56,'Menu Pricing'!$O$7:$O$56,">0"))/SUMIF('Menu Pricing'!$O$7:$O$56,">0"),"0%"),"")
B23: Staff working
B24: Hours per staff member (incl. setup & travel)
B25: Hourly wage incl. payroll taxes | D25: ="Settings labour rate: "&cfg_Symbol&TEXT(cfg_LaborRate,"0.00")
B26: Transportation (mileage, tolls, parking)
B27: Fuel & generator
B28: Other expenses (ice, extra permits, supplies)
B30: FORECAST RESULTS
B31: Forecast (not actual results) | C31: Worst case | D31: Base case | E31: Best case
B32: Expected buying customers | C32: =ROUND(N(C13)*N(C14),0) | D32: =ROUND(N(D13)*N(D14),0) | E32: =ROUND(N(E13)*N(E14),0)
B33: Expected orders | C33: =ROUND(C32*N(C15),0) | D33: =ROUND(D32*N(D15),0) | E33: =ROUND(E32*N(E15),0)
B34: Revenue | C34: =C33*N(C16) | D34: =D33*N(D16) | E34: =E33*N(E16)
B35: Food & packaging | C35: =C34*N($C$22) | D35: =D34*N($C$22) | E35: =E34*N($C$22)
B36: Commission + card fees | C36: =C34*(N($C$20)+N($C$21)) | D36: =D34*(N($C$20)+N($C$21)) | E36: =E34*(N($C$20)+N($C$21))
B37: Contribution (after variable costs) | C37: =C34-C35-C36 | D37: =D34-D35-D36 | E37: =E34-E35-E36
B38: Staffing cost | C38: =N($C$23)*N($C$24)*N($C$25) | D38: =N($C$23)*N($C$24)*N($C$25) | E38: =N($C$23)*N($C$24)*N($C$25)
B39: Fixed event costs (fee, staff, travel, fuel, other) | C39: =(N($C$19)+N($C$23)*N($C$24)*N($C$25)+N($C$26)+N($C$27)+N($C$28)) | D39: =(N($C$19)+N($C$23)*N($C$24)*N($C$25)+N($C$26)+N($C$27)+N($C$28)) | E39: =(N($C$19)+N($C$23)*N($C$24)*N($C$25)+N($C$26)+N($C$27)+N($C$28))
B40: ESTIMATED PROFIT | C40: =C37-C39 | D40: =D37-D39 | E40: =E37-E39
B41: Profit margin | C41: =IF(C34=0,"",C40/C34) | D41: =IF(D34=0,"",D40/D34) | E41: =IF(E34=0,"",E40/E34)
B42: Break-even orders | C42: =IF(N(C16)*(1-($C$20+$C$21+$C$22))<=0,"n/a",ROUNDUP((N($C$19)+N($C$23)*N($C$24)*N($C$25)+N($C$26)+N($C$27)+N($C$28))/(N(C16)*(1-($C$20+$C$21+$C$22))),0)) | D42: =IF(N(D16)*(1-($C$20+$C$21+$C$22))<=0,"n/a",ROUNDUP((N($C$19)+N($C$23)*N($C$24)*N($C$25)+N($C$26)+N($C$27)+N($C$28))/(N(D16)*(1-($C$20+$C$21+$C$22))),0)) | E42: =IF(N(E16)*(1-($C$20+$C$21+$C$22))<=0,"n/a",ROUNDUP((N($C$19)+N($C$23)*N($C$24)*N($C$25)+N($C$26)+N($C$27)+N($C$28))/(N(E16)*(1-($C$20+$C$21+$C$22))),0))
B43: Break-even attendance | C43: =IF(OR(NOT(ISNUMBER(C42)),N(C14)*N(C15)=0),"n/a",ROUNDUP(C42/(N(C14)*N(C15)),0)) | D43: =IF(OR(NOT(ISNUMBER(D42)),N(D14)*N(D15)=0),"n/a",ROUNDUP(D42/(N(D14)*N(D15)),0)) | E43: =IF(OR(NOT(ISNUMBER(E42)),N(E14)*N(E15)=0),"n/a",ROUNDUP(E42/(N(E14)*N(E15)),0))
B44: Orders above / below break-even | C44: =IF(ISNUMBER(C42),C33-C42,"") | D44: =IF(ISNUMBER(D42),D33-D42,"") | E44: =IF(ISNUMBER(E42),E33-E42,"")
B46: Verdict | C46: =IF(N(D16)=0,"Enter attendance, buy rate and order value to see a verdict",IF(C40>0,"LOW RISK - profitable even in the worst case",IF(D40>0,"MODERATE RISK - profitable in the base case, loss in the worst case",IF(E40>0,"HIGH RISK - only the best case makes money","NOT VIABLE at these assumptions - negotiate the fee or skip"))))
B48: ACTUAL RESULTS (after the event)
B49: Actual | C49: From your logs | D49: Your entry | E49: Used
B50: Actual revenue | C50: =IF($C$7="","",SUMIFS('Sales Log'!$I$7:$I$3006,'Sales Log'!$G$7:$G$3006,$C$7,'Sales Log'!$N$7:$N$3006,"OK")) | E50: =IF(ISNUMBER(D50),D50,IF(ISNUMBER(C50),C50,0))
B51: Actual items sold | C51: =IF($C$7="","",SUMIFS('Sales Log'!$D$7:$D$3006,'Sales Log'!$G$7:$G$3006,$C$7,'Sales Log'!$N$7:$N$3006,"OK")) | E51: =IF(ISNUMBER(D51),D51,IF(ISNUMBER(C51),C51,0))
B52: Actual food & packaging (COGS) | C52: =IF($C$7="","",SUMIFS('Sales Log'!$K$7:$K$3006,'Sales Log'!$G$7:$G$3006,$C$7,'Sales Log'!$N$7:$N$3006,"OK")) | E52: =IF(ISNUMBER(D52),D52,IF(ISNUMBER(C52),C52,0))
B53: Actual fee + commission + card fees | C53: - | E53: =IF(ISNUMBER(D53),D53,IF(ISNUMBER(C53),C53,0))
B54: Actual staffing cost | C54: - | E54: =IF(ISNUMBER(D54),D54,IF(ISNUMBER(C54),C54,0))
B55: Actual transport, fuel & other | C55: - | E55: =IF(ISNUMBER(D55),D55,IF(ISNUMBER(C55),C55,0))
B56: ACTUAL PROFIT | E56: =IF(AND(E50=0,E53+E54+E55=0),"",E50-E52-E53-E54-E55)
B57: Base-case forecast profit | E57: =D40
B58: Variance (actual - base forecast) | E58: =IF(E56="","",E56-D40)
B59: Revenue vs base forecast | E59: =IF(OR(E56="",N(D34)=0),"",E50/D34)

Sheet Scenario Simulator
B2: Scenario Simulator | M2: NoviraNest
B3: What happens to profit if costs, prices or sales change? Your real data is never modified.
B4: › Start Here | C4: › Dashboard | D4: › Monthly Report
B6: 1. BASELINE - an average month
B7: Baseline item | C7: From your data | D7: Your override | E7: Baseline used
B8: Items sold per month | C8: =IF($C$17=0,"",'Monthly Report'!$F$20/$C$17) | E8: =IF(ISNUMBER(D8),D8,N(C8))
B9: Average price per item | C9: =IF(N('Monthly Report'!$F$20)=0,"",'Monthly Report'!$E$20/'Monthly Report'!$F$20) | E9: =IF(ISNUMBER(D9),D9,N(C9))
B10: Ingredient cost per item | C10: =IF(N('Monthly Report'!$F$20)=0,"",'Monthly Report'!$S$20/'Monthly Report'!$F$20) | E10: =IF(ISNUMBER(D10),D10,N(C10))
B11: Packaging & other variable cost per item | C11: =IF(N('Monthly Report'!$F$20)=0,"",('Monthly Report'!$G$20-'Monthly Report'!$S$20)/'Monthly Report'!$F$20) | E11: =IF(ISNUMBER(D11),D11,N(C11))
B12: Staff wages per month | C12: =IF($C$17=0,"",'Monthly Report'!$L$20/$C$17) | E12: =IF(ISNUMBER(D12),D12,N(C12))
B13: Event & pitch fees per month | C13: =IF($C$17=0,"",'Monthly Report'!$M$20/$C$17) | E13: =IF(ISNUMBER(D13),D13,N(C13))
B14: Other operating costs per month (fixed + variable) | C14: =IF($C$17=0,"",('Monthly Report'!$K$20+'Monthly Report'!$N$20)/$C$17) | E14: =IF(ISNUMBER(D14),D14,N(C14))
B15: Waste per month | C15: =IF($C$17=0,"",'Monthly Report'!$J$20/$C$17) | E15: =IF(ISNUMBER(D15),D15,N(C15))
B17: Months of sales data used for the averages | C17: =COUNTIF('Monthly Report'!$E$8:$E$19,">0") | D17: =IF(C17=0,"No sales yet - type a baseline in the override column","Reporting year "&cfg_Year)
B19: 2. CHOOSE A SCENARIO
B20: Scenario | C20: Custom (use my levers)
H21: PRESETS (editable)
B22: Lever (% change) | C22: My levers (Custom) | D22: Preset value | E22: Applied | H22: Preset | I22: Ingredients | J22: Volume | K22: Menu price | L22: Labour | M22: Event fees
B23: Ingredient prices | D23: =IFERROR(INDEX($I$23:$I$31,MATCH($C$20,$H$23:$H$31,0)),0) | E23: =IF(OR($C$20=$H$23,$C$20=""),N(C23),D23) | H23: Custom (use my levers) | I23: - | J23: - | K23: - | L23: - | M23: -
B24: Sales volume (items sold) | D24: =IFERROR(INDEX($J$23:$J$31,MATCH($C$20,$H$23:$H$31,0)),0) | E24: =IF(OR($C$20=$H$23,$C$20=""),N(C24),D24) | H24: Ingredient inflation +10% | I24: 0.1 | J24: 0 | K24: 0 | L24: 0 | M24: 0
B25: Menu prices | D25: =IFERROR(INDEX($K$23:$K$31,MATCH($C$20,$H$23:$H$31,0)),0) | E25: =IF(OR($C$20=$H$23,$C$20=""),N(C25),D25) | H25: Menu price increase +5% | I25: 0 | J25: 0 | K25: 0.05 | L25: 0 | M25: 0
B26: Labour costs | D26: =IFERROR(INDEX($L$23:$L$31,MATCH($C$20,$H$23:$H$31,0)),0) | E26: =IF(OR($C$20=$H$23,$C$20=""),N(C26),D26) | H26: Price +5%, volume -3% | I26: 0 | J26: -0.03 | K26: 0.05 | L26: 0 | M26: 0
B27: Event fees | D27: =IFERROR(INDEX($M$23:$M$31,MATCH($C$20,$H$23:$H$31,0)),0) | E27: =IF(OR($C$20=$H$23,$C$20=""),N(C27),D27) | H27: Busy season (+25% volume) | I27: 0 | J27: 0.25 | K27: 0 | L27: 0.1 | M27: 0
H28: Slow season (-30% volume) | I28: 0 | J28: -0.3 | K28: 0 | L28: -0.15 | M28: 0
H29: Wage increase +8% | I29: 0 | J29: 0 | K29: 0 | L29: 0.08 | M29: 0
H30: Event fees +20% | I30: 0 | J30: 0 | K30: 0 | L30: 0 | M30: 0.2
H31: Perfect storm | I31: 0.12 | J31: -0.15 | K31: 0 | L31: 0.08 | M31: 0.2
B33: 3. IMPACT (per month)
B34: Metric | C34: Baseline | D34: Scenario | E34: Change | F34: Change % | H34: HOW IT WORKS Baseline = your average month in the reporting year (or your overrides). The scenario multiplies the baseline by the applied levers. Price changes do not automatically change volume - use 'Price +5%, volume -3%' or your own levers to model customer reaction. Nothing on your other sheets changes.
B35: Items sold | C35: =E8 | D35: =C35*(1+$E$24) | E35: =IF(AND(ISNUMBER(C35),ISNUMBER(D35)),D35-C35,"") | F35: =IF(AND(ISNUMBER(C35),ISNUMBER(D35),N(C35)<>0),(D35-C35)/ABS(C35),"")
B36: Average price per item | C36: =E9 | D36: =C36*(1+$E$25) | E36: =IF(AND(ISNUMBER(C36),ISNUMBER(D36)),D36-C36,"") | F36: =IF(AND(ISNUMBER(C36),ISNUMBER(D36),N(C36)<>0),(D36-C36)/ABS(C36),"")
B37: Revenue | C37: =C35*C36 | D37: =D35*D36 | E37: =IF(AND(ISNUMBER(C37),ISNUMBER(D37)),D37-C37,"") | F37: =IF(AND(ISNUMBER(C37),ISNUMBER(D37),N(C37)<>0),(D37-C37)/ABS(C37),"")
B38: Ingredient costs | C38: =C35*E10 | D38: =D35*E10*(1+$E$23) | E38: =IF(AND(ISNUMBER(C38),ISNUMBER(D38)),D38-C38,"") | F38: =IF(AND(ISNUMBER(C38),ISNUMBER(D38),N(C38)<>0),(D38-C38)/ABS(C38),"")
B39: Packaging & other variable | C39: =C35*E11 | D39: =D35*E11 | E39: =IF(AND(ISNUMBER(C39),ISNUMBER(D39)),D39-C39,"") | F39: =IF(AND(ISNUMBER(C39),ISNUMBER(D39),N(C39)<>0),(D39-C39)/ABS(C39),"")
B40: Gross profit | C40: =C37-C38-C39 | D40: =D37-D38-D39 | E40: =IF(AND(ISNUMBER(C40),ISNUMBER(D40)),D40-C40,"") | F40: =IF(AND(ISNUMBER(C40),ISNUMBER(D40),N(C40)<>0),(D40-C40)/ABS(C40),"")
B41: Gross margin | C41: =IF(C37=0,"",C40/C37) | D41: =IF(D37=0,"",D40/D37) | E41: =IF(OR(C41="",D41=""),"",(D41-C41)*100)
B42: Staff wages | C42: =E12 | D42: =E12*(1+$E$26) | E42: =IF(AND(ISNUMBER(C42),ISNUMBER(D42)),D42-C42,"") | F42: =IF(AND(ISNUMBER(C42),ISNUMBER(D42),N(C42)<>0),(D42-C42)/ABS(C42),"")
B43: Event & pitch fees | C43: =E13 | D43: =E13*(1+$E$27) | E43: =IF(AND(ISNUMBER(C43),ISNUMBER(D43)),D43-C43,"") | F43: =IF(AND(ISNUMBER(C43),ISNUMBER(D43),N(C43)<>0),(D43-C43)/ABS(C43),"")
B44: Other operating costs | C44: =E14 | D44: =E14 | E44: =IF(AND(ISNUMBER(C44),ISNUMBER(D44)),D44-C44,"") | F44: =IF(AND(ISNUMBER(C44),ISNUMBER(D44),N(C44)<>0),(D44-C44)/ABS(C44),"")
B45: Waste (moves with ingredient prices) | C45: =E15 | D45: =E15*(1+$E$23) | E45: =IF(AND(ISNUMBER(C45),ISNUMBER(D45)),D45-C45,"") | F45: =IF(AND(ISNUMBER(C45),ISNUMBER(D45),N(C45)<>0),(D45-C45)/ABS(C45),"")
B46: NET PROFIT | C46: =C40-SUM(C42:C45) | D46: =D40-SUM(D42:D45) | E46: =IF(AND(ISNUMBER(C46),ISNUMBER(D46)),D46-C46,"") | F46: =IF(AND(ISNUMBER(C46),ISNUMBER(D46),N(C46)<>0),(D46-C46)/ABS(C46),"")
B47: Net margin | C47: =IF(C37=0,"",C46/C37) | D47: =IF(D37=0,"",D46/D37) | E47: =IF(OR(C47="",D47=""),"",(D47-C47)*100) | H47: Chart | I47: Baseline | J47: Scenario
B48: Break-even items per month | C48: =IF(C36-E10-E11<=0,"n/a",ROUNDUP(SUM(C42:C45)/(C36-E10-E11),0)) | D48: =IF(D36-E10*(1+$E$23)-E11<=0,"n/a",ROUNDUP(SUM(D42:D45)/(D36-E10*(1+$E$23)-E11),0)) | E48: =IF(AND(ISNUMBER(C48),ISNUMBER(D48)),D48-C48,"") | F48: =IF(AND(ISNUMBER(C48),ISNUMBER(D48),N(C48)<>0),(D48-C48)/ABS(C48),"") | H48: Revenue | I48: =C37 | J48: =D37
H49: Gross profit | I49: =C40 | J49: =D40
B50: Average price needed to keep your baseline net profit | D50: =IF(OR(D35<=0,C35<=0),"",(C46+SUM(D42:D45))/D35+E10*(1+$E$23)+E11) | E50: =IF(OR(D50="",N(C36)=0),"",D50/C36-1) | H50: Net profit | I50: =C46 | J50: =D46
B51: =IF(D50="","",IF(E50>0.0005,"To keep today's profit in this scenario, raise your average price by "&TEXT(E50,"0.0%")&" (to "&cfg_Symbol&TEXT(D50,"0.00")&").",IF(E50<-0.0005,"This scenario is more profitable: you could lower prices by up to "&TEXT(-E50,"0.0%")&" and keep today's profit.","Your profit is unchanged in this scenario.")))
B52: BASELINE vs SCENARIO (per month)

Sheet Lists
B2: Lists & Units | T2: NoviraNest
B3: Dropdown sources and unit conversion factors. Add your own categories in the empty cream rows.
B4: › Start Here | D4: › Dashboard | F4: › Settings
B5: Unit | C5: Dimension | D5: Factor to base (g / ml / each) | F5: Expense category | G5: Cost type | H5: What goes here | J5: Payment method | L5: Menu category | N5: Waste reason | P5: Dashboard period | R5: Currency | T5: Price rounding step | V5: Cost types
B6: g | C6: Mass | D6: 1 | F6: Commissary / Parking | G6: Fixed | H6: Kitchen rental, overnight parking | J6: Card | L6: Mains | N6: Expired | P6: Full Year | R6: USD | T6: 0 | V6: Fixed
B7: kg | C7: Mass | D7: 1000 | F7: Truck Loan / Lease | G7: Fixed | H7: Monthly truck or trailer payment | J7: Cash | L7: Sides | N7: Spoiled | P7: January | R7: GBP | T7: 0.05 | V7: Labor
B8: oz | C8: Mass | D8: 28.349523 | F8: Insurance | G8: Fixed | H8: Liability, vehicle, equipment | J8: Mobile Wallet | L8: Drinks | N8: Over-prepped | P8: February | T8: 0.1 | V8: Event Fees
B9: lb | C9: Mass | D9: 453.59237 | F9: Licenses & Permits | G9: Fixed | H9: Health permits, business licences | J9: Online / App | L9: Desserts | N9: Dropped / Damaged | P9: March | T9: 0.25 | V9: Variable
B10: ml | C10: Volume | D10: 1 | F10: POS / Software | G10: Fixed | H10: Point of sale, apps, subscriptions | J10: Bank Transfer | L10: Kids | N10: Quality reject | P10: April | T10: 0.5 | V10: Excluded - Stock Purchase
B11: l | C11: Volume | D11: 1000 | F11: Phone & Internet | G11: Fixed | H11: Mobile data, hotspot | J11: Invoice | L11: Specials | N11: Staff error | P11: May | T11: 1 | V11: Excluded - Owner Draw
B12: tsp | C12: Volume | D12: 4.9289216 | F12: Accounting & Legal | G12: Fixed | H12: Bookkeeper, accountant, legal | J12: Other | L12: Combos | N12: Other | P12: June
B13: tbsp | C13: Volume | D13: 14.786765 | F13: Marketing & Advertising | G13: Fixed | H13: Social ads, printing, signage | L13: Catering | P13: July
B14: cup (US) | C14: Volume | D14: 236.58824 | F14: Staff Wages & Payroll | G14: Labor | H14: Wages incl. payroll taxes | P14: August
B15: fl oz (US) | C15: Volume | D15: 29.57353 | F15: Event & Pitch Fees | G15: Event Fees | H15: Festival, market and pitch fees | P15: September
B16: fl oz (UK) | C16: Volume | D16: 28.413062 | F16: Fuel & Generator | G16: Variable | H16: Vehicle fuel, generator fuel | P16: October
B17: pint (US) | C17: Volume | D17: 473.17647 | F17: Propane / Cooking Gas | G17: Variable | H17: Cooking gas refills | P17: November
B18: pint (UK) | C18: Volume | D18: 568.26125 | F18: Card Processing Fees | G18: Variable | H18: Card reader / payment fees | P18: December
B19: gal (US) | C19: Volume | D19: 3785.4118 | F19: Repairs & Maintenance | G19: Variable | H19: Truck and equipment repairs
B20: gal (UK) | C20: Volume | D20: 4546.09 | F20: Cleaning & Disposables | G20: Variable | H20: Cleaning products, gloves
B21: each | C21: Count | D21: 1 | F21: Other Operating Expense | G21: Variable | H21: Anything else that runs the business
B22: dozen | C22: Count | D22: 12 | F22: Ingredient & Packaging Purchases | G22: Excluded - Stock Purchase | H22: Logged for cash records only; profit uses recipe COGS
B23: portion | C23: Count | D23: 1 | F23: Owner's Draw | G23: Excluded - Owner Draw | H23: Money you pay yourself; not a business expense
B33: Units convert only within the same dimension (Mass, Volume, Count). Weight-to-volume needs a density and is never guessed: the line is flagged 'Unit mismatch' instead.
F38: Cost types: Fixed, Labor, Event Fees and Variable count as operating expenses. 'Excluded' types are recorded for your cash records but NOT deducted from profit (food used is already in COGS; owner's draw is not a business expense).
